Workbook
Name a: #REF!
Name B: #REF!
Name PAC_ORIGINAL: Domínios!#REF!
Name PAC_SELEÇÕES: Domínios!$AG$3:$AG$25
Name status_intervencao: Domínios!$L$3:$L$10
Name status_pleito: Domínios!$L$8:$L$8

Sheet PAC
F1: Quantidade por FASE | J1: QTD TOTAL | K1: INVESTIMENTO TOTAL
F2: CAPTAÇÃO | G2: LICITAÇÃO | H2: EXECUÇÃO | I2: CONCLUÍDAS | K2: VALOR SOLICITADO FINANCIAMENTO | L2: VALOR SOLICITADO OGU | M2: APOIADO | N2: CONTRAPARTIDA | O2: COMPLEMENTAR | P2: FINANCIAMENTO | Q2: PLANEJAMENTO ORÇAMENTÁRIO DESCONSIDERANDO AS OBRAS JÁ CONTRATADAS | R2: APOIADO CONTRATADO | S2: CONTRAPARTIDA CONTRATADA | T2: COMPLEMENTAR CONTRATADO | U2: FINANCIAMENTO CONTRATADO | V2: VALOR CONTRATADO | W2: INVESTIMENTO TOTAL
F3: =SUBTOTAL(9,PAC!$BB$6:$BB$581) -> 0 | G3: =SUBTOTAL(9,PAC!$BC$6:$BC$581) -> 0 | H3: =SUBTOTAL(9,PAC!$BD$6:$BD$581) -> 1 | I3: =SUBTOTAL(9,PAC!$BE$6:$BE$581) -> 0 | J3: =SUBTOTAL(3,J6:J581) -> 1 | K3: =SUBTOTAL(9,PAC!K$6:K$581) -> 0 | L3: =SUBTOTAL(9,PAC!L$6:L$581) -> 0 | M3: =SUBTOTAL(9,PAC!M$6:M$581) -> 11440559 | N3: =SUBTOTAL(9,PAC!N$6:N$581) -> 139742.41 | O3: =SUBTOTAL(9,PAC!O$6:O$581) -> 1915931 | P3: =SUBTOTAL(9,PAC!P$6:P$581) -> 0 | Q3: =SUBTOTAL(9,PAC!$BF$6:$BF$581) -> 0 | R3: =SUBTOTAL(9,PAC!R$6:R$581) -> 10947985 | S3: =SUBTOTAL(9,PAC!S$6:S$581) -> 139742.41 | T3: =SUBTOTAL(9,PAC!T$6:T$581) -> 1412523.9 | U3: =SUBTOTAL(9,PAC!U$6:U$581) -> 0 | V3: =SUBTOTAL(9,PAC!V$6:V$581) -> 12500251 | W3: =SUBTOTAL(9,PAC!W$6:W$581) -> 12500251
A5: ITEM | B5: ANO DE CADASTRO | C5: TIPO | D5: PAC | E5: DESCRIÇÃO | F5: EIXO | G5: OBJETO | H5: SECRETARIA/ ÓRGÃO | I5: ORGÃO EXECUTOR | J5: MUNICÍPIO | K5: VALOR SOLICITADO (FINANCIAMENTO) | L5: VALOR SOLICITADO (OGU) | M5: APOIADO | N5: CONTRAPARTIDA | O5: COMPLEMENTAR | P5: FINANCIAMENTO | Q5: PLANEJAMENTO ORÇAMENTÁRIO | R5: APOIADO CONTRATADO | S5: CONTRAPARTIDA CONTRATADA | T5: COMPLEMENTAR CONTRATADO | U5: FINANCIAMENTO CONTRATADO | V5: VALOR CONTRATADO | W5: INVESTIMENTO TOTAL | X5: EMPRESA CONTRATADA | Y5: FONTE DE RECURSO | Z5: FONTE DE FINANCIAMENTO | AA5: PRAZO EXECUÇÃO (MESES) | AB5: FASE | AC5: STATUS | AD5: PRAZO DE CONCLUSÃO DA FASE | AE5: AVANÇO DA OBRA (%) | AF5: PENDÊNCIAS / TAREFA | AG5: PROVIDÊNCIAS (DATAS) | AH5: PRAZO DA PENDÊNCIA / TAREFA | AI5: PRÓXIMOS PASSOS | AJ5: Nº DA PROPOSTA PAC | AK5: Nº DO TERMO DE COMP. (TC) / CT FINANCIAMENTO | AL5: CLÁUSULA SUSPENSIVA | AM5: MOTIVO DA CLÁUSULA SUSPENSIVA | AN5: VIGÊNCIA | AO5: LINK_MONITORA | AP5: LINK_LOCALIZAÇÃO | AQ5: STATUS ANTERIOR SELEÇÃO 2023 | AR5: AVISO DE LICITAÇÃO | AS5: ABERTURA DE LICITAÇÃO | AT5: PREVISÃO DE CONTRATAÇÃO | AU5: EMISSÃO DE O.S. | AV5: DATA DE CONCLUSÃO ORIGINAL | AW5: PREVISÃO DE CONCLUSÃO ATUAL | AX5: OBSERVAÇÕES | AY5: DETALHE DO STATUS | AZ5: DATA DA SELEÇÃO | BA5: DET. DO PROJETO - PAC | BB5: CAPTAÇÃO | BC5: LICITAÇÃO | BD5: OBRA | BE5: CONCLUÍDAS | BF5: PLANEJAMENTO ORÇAMENTÁRIO SEM O VALOR CONTRATADO
A6: =ROW()-5 -> 1 | B6: 2023 | C6: OBRA | D6: PAC ORIGINAL | E6: Adutora da Fé – 1ª Etapa | F6: Água Para Todos | G6: Adutora da Fé | H6: GESTÃO FEDERAL | I6: 07 - Gov. Federal - CODEVASF | J6: Bom Jesus da Lapa | M6: 47303701 | Q6: =SUM(PAC!$M6:$P6) -> 47303701 | W6: =IF(PAC!$V6>0,PAC!$V6,PAC!$Q6) -> 47303701 | Y6: OGU | AB6: F04 - CONCLUÍDA | AC6: 18 - INAUGURADA | AE6: 100 | AF6: Publicar Contrato de Execução | AY6: Obra inaugurada em 07/02/25 pelo Presidente Lula. | BB6: =IFERROR(IF(PAC!$AB6="F01 - CAPTAÇÃO DE RECURSO",1,""),"") | BC6: =IFERROR(IF(PAC!$AB6="F02 - LICITAÇÃO",1,""),"") | BD6: =IFERROR(IF(PAC!$AB$6:$AB$581="F03 - EXECUÇÃO DO OBJETO",1,""),"") | BE6: =IFERROR(IF(PAC!$AB$6:$AB$581="F04 - CONCLUÍDA",1,""),"") -> 1 | BF6: =IF(PAC!$V6>0,0,PAC!$Q6) -> 47303701
A7: =ROW()-5 -> 2 | B7: 2023 | C7: OBRA | D7: PAC ORIGINAL | E7: Adutora da Fé – 2ª Etapa | F7: Água Para Todos | G7: Adutora da Fé | H7: GESTÃO FEDERAL | I7: 07 - Gov. Federal - CODEVASF | J7: Bom Jesus da Lapa | M7: 2.5883994e+08 | Q7: =SUM(PAC!$M7:$P7) -> 2.5883994e+08 | W7: =IF(PAC!$V7>0,PAC!$V7,PAC!$Q7) -> 2.5883994e+08 | Y7: OGU | AB7: F03 - EXECUÇÃO DO OBJETO | AC7: 03 - AGUARDANDO ORDEM DE SERVIÇO | AI7: Iniciar as obras | AX7: Informação recebida em 13/08/2025: _ A responsabilidade pela execução da totalidade da obra será da Eletrobrás, que fará a contratação da empresa construtora. _ O projeto inicial é da CODEVASF, porém a Eletrobrás contratou uma empresa para revisar o Projeto Básico, tendo em vista dificuldades para a execução da obra em trechos urbanos (municípios de Riacho de Santana e Igaporã) com interferência na malha rodoviária administrada pelo DNIT. _ Foi aberto requerimento para início do procedimento da Licença dessa fase da obra, porém está pendente até a conclusão da revisão do projeto. Assim, ainda não há expectativa para início das obras da 2ª etapa e do cronograma para a sua implantação. | AY7: (Obra contratada pela Eletrobrás - contrato assinado em 21/01/25 - Inf. Codevasf) Verificar a coluna de observações "...não há expectativa para início das obras da 2ª etapa e do cronograma para a sua implantação." | BB7: =IFERROR(IF(PAC!$AB7="F01 - CAPTAÇÃO DE RECURSO",1,""),"") | BC7: =IFERROR(IF(PAC!$AB7="F02 - LICITAÇÃO",1,""),"") | BD7: =IFERROR(IF(PAC!$AB$6:$AB$581="F03 - EXECUÇÃO DO OBJETO",1,""),"") -> 1 | BE7: =IFERROR(IF(PAC!$AB$6:$AB$581="F04 - CONCLUÍDA",1,""),"") | BF7: =IF(PAC!$V7>0,0,PAC!$Q7) -> 2.5883994e+08
A8: =ROW()-5 -> 3 | B8: 2023 | C8: OBRA | D8: PAC ORIGINAL | E8: Aeroporto de Barreiras (INFRA) | F8: Infraestrutura | G8: Aeroporto (INFRA) | H8: SEINFRA | I8: 01 - Gov. Estado - SEINFRA | J8: Barreiras | L8: 100000000 | M8: 44086568 | Q8: =SUM(PAC!$M8:$P8) -> 44086568 | V8: 44086568 | W8: =IF(PAC!$V8>0,PAC!$V8,PAC!$Q8) -> 44086568 | X8: CONSORCIO AEROPORTO DE BARREIRAS PORTICO - ETERC - EBSA | Y8: OGU | AA8: 11 | AB8: F03 - EXECUÇÃO DO OBJETO | AC8: 02 - ANDAMENTO | AD8: 46326 | AE8: 42 | AF8: Execução da Obra | AG8: Conforme NT de 12/08 devido às chuvas, foi formalizado aditivo de prazo reprogramando a conclusão da obra de 30/09/26 para OUT/26. Obras de terraplenagem para ampliação da cabeceira, em fase final. Serão iniciados os serviços de execução das camadas de sub-base e base. OBSERVAÇÕES: - Existem tratativas técnicas para atender às necessidades da LATAM de iniciar as operações do Aeroporto em NOV/26. Segundo a DTE, a operação independe do conclusão do TPS. Conforme DTE/SEINFRA, não será possível a compatibilização dos cronogramas de execução de INFRA e TPS para entrega total do equipamento em data única, devido às demandas específicas do TPS. | AH8: 46326 | AI8: Monitorar andamento das obras. | AK8: 06/2018 | AO8: https://governodabahia.plataformatarget.com.br/web/a1391b0c-f58d-4537-8193-51235efc7385/home | AP8: https://maps.app.goo.gl/y2A6Z8frmTDtxnL48 | AR8: 45584 | AS8: 45667 | AT8: 45806 | AU8: 45833 | AV8: 46163 | AW8: 46326 | AX8: 16/06/2026 - Conforme Ofício GASEC nº 271/2025, de 05/06/2025, a SEINFRA solicitou à SAC a supressão do TPS e equipamentos e mobiliários do TC 06/2018, para que os mesmos sejam executados com recursos próprios, mantendo apenas a INFRA com recurso do PAC. Processo SEI nº: 024.2058.2024.0008514-17 - Objeto: Execução de obras de reforma e ampliação da PPD, reforma e adequação da taxiway, construção do novo pátio de aeronaves e serviços complementares de: drenagem e infra do balizamento noturno e auxílios à navegação, do Aeroporto de Barreiras - Dom Ricardo Weberberger - Bahia (SNBR). Fonte de Recurso - Governo Federal - Fundo Nacional de Aviação (FNAC) (INFRA + Equipamentos)*: R$ 65,7 milhões (VALOR INICIALMENTE APROVADO E APOIADO CONFORME SELEÇÃO PAC EM 2023) VIGÊNCIA DO TC 31/12/2024. Licença de Alteração, Portaria INEMA n° 30.754, vigência 14/11/2028) Conforme Seinfra (27/09 - Grupo Whatsapp) a Concessão pemanecerá com a Agerba, vigência até 03/08/2032. 07/10 - Edital analisado pela PGE e SAEB, uma vez que o BB ainda não disponibilizou Plataforma para licitação concorrência eletrônica para julgamento técnica e preço. Conforme SEINFRA, não há previsão para o certame de equipamentos/mobiliários; 18/09 - Autorização da SAC para início do processo licitatório, com glosa e ressalvas, conforme Ofício 529/2024/SAC-MPOR. 13/09 - Entregues à SAC (plataforma) relatório assinado pela Seinfra e licença ambiental. 02/09 - Adequações de orçamento entregues na plataforma da SAC, pendente parecer final. Financiamento: FNAC | AY8: 16/06/2026 - Conforme Ofício GASEC nº 271/2025, de 05/06/2025, a SEINFRA solicitou à SAC a supressão do TPS e equipamentos e mobiliários do TC 06/2018, para que os mesmos sejam executados com recursos próprios, mantendo apenas a INFRA com recurso do PAC. 09/12/25 - Percentual de execução atualizado 16,24%, conforme retorno DTE (Whatsapp Roberval). 02/09/25 - Obra em andamento ainda sem % de execução. Conforme Diretoria de Terminais a obra foi iniciada em 15/08/25, um dia após emissão de NOTAM pela ANAC (autorização necessária para início) e não após emissão da O.S., tendo a previsão de conclusão ajustada para ABR/26. 25/06/25 - Assinatura da Ordem de Serviço. 30/05/25 - Publicado resumo de contrato, execução 330 dias. Pendente emissão O.S. | BB8: =IFERROR(IF(PAC!$AB8="F01 - CAPTAÇÃO DE RECURSO",1,""),"") | BC8: =IFERROR(IF(PAC!$AB8="F02 - LICITAÇÃO",1,""),"") | BD8: =IFERROR(IF(PAC!$AB$6:$AB$581="F03 - EXECUÇÃO DO OBJETO",1,""),"") -> 1 | BE8: =IFERROR(IF(PAC!$AB$6:$AB$581="F04 - CONCLUÍDA",1,""),"") | BF8: =IF(PAC!$V8>0,0,PAC!$Q8) -> 0
A9: =ROW()-5 -> 4 | B9: 2023 | C9: EQUIPAMENTOS | D9: PAC ORIGINAL | E9: Aeroporto de Barreiras (EQUIPAMENTOS DE BALIZAMENTO - PISTA/INFRA) Sinalização: iluminação de pátio, luminoso PPD e TWY, Biruta, Farol, Papi, etc. | F9: Infraestrutura | G9: Aeroporto (EQUIPAMENTOS) | H9: SEINFRA | I9: 01 - Gov. Estado - SEINFRA | J9: Barreiras | N9: 4050508.4 | Q9: =SUM([1]PAC!$M9:$P9) -> 4050508.4 | V9: 3300969.6 | W9: =IF(PAC!$V9>0,PAC!$V9,PAC!$Q9) -> 3300969.6 | X9: METROL ENGENHARIA LTDA. | Y9: CONTRAPARTIDA | AA9: 3 | AB9: F03 - EXECUÇÃO DO OBJETO | AC9: 02 - ANDAMENTO | AD9: 46387 | AE9: 0 | AF9: Execução da Obra | AG9: CONFORME DEFINIDO EM REUNIÃO COM MINISTÉRIO, GOVERNADOR E SECRETÁRIOS DA C.CIVIL E SEINFRA (29/07/26), OS EQUIPAMENTOS MOBILIÁRIOS FICARÃO SOB A RESPONSABILIDADE DA CONCESSIONÁRIA. O ESTADO NÃO FARÁ AQUISIÇÃO. Contrato publicado em 18/09 e OS. assinada em 21/09/2026. Licitação homologada e adjudicada, com pulicação no DOE em 20/08/2026. Empresa vencedora: Metrol Engenharia Ltda. Publicado AVISO DE LICITAÇÃO - PREGÃO ELETRÔNICO Nº 1/2026 - SEINFRA/SIT - BB Nº 1090760, em 03/04/2026. Abertura dos envelopes ocorrida em 22/04/26. | AH9: 46387 | AI9: CONFORME DEFINIDO EM REUNIÃO COM MINISTÉRIO, GOVERNADOR E SECRETÁRIOS DA C.CIVIL E SEINFRA (29/07/26), OS EQUIPAMENTOS MOBILIÁRIOS FICARÃO SOB A RESPONSABILIDADE DA CONCESSIONÁRIA. O ESTADO NÃO FARÁ AQUISIÇÃO. Assinatura do contrato com a empresa para iniciar serviços de instalação da sinalização. | AO9: https://governodabahia.plataformatarget.com.br/web/fbb30a88-ec24-4177-87a2-2b54f6b0731e | AP9: https://maps.app.goo.gl/y2A6Z8frmTDtxnL48 | AR9: 46115 | AS9: 46134 | AT9: 46283 | AU9: 46286 | AV9: 46387 | AW9: 46387 | AX9: CONFORME DEFINIDO EM REUNIÃO COM MINISTÉRIO, GOVERNADOR E SECRETÁRIOS DA C.CIVIL E SEINFRA (29/07/26), OS EQUIPAMENTOS MOBILIÁRIOS FICARÃO SOB A RESPONSABILIDADE DA CONCESSIONÁRIA. O ESTADO NÃO FARÁ AQUISIÇÃO. 16/06/2026 - Conforme Ofício GASEC nº 271/2025, de 05/06/2025, a SEINFRA solicitou à SAC a supressão do TPS e equipamentos e mobiliários do TC 06/2018, para que os mesmos sejam executados com recursos próprios, mantendo apenas a INFRA com recurso do PAC. Processo SEI nº: 024.2058.2024.0008514-17 - Objeto: Execução de obras de reforma e ampliação da PPD, reforma e adequação da taxiway, construção do novo pátio de aeronaves e serviços complementares de: drenagem e infra do balizamento noturno e auxílios à navegação, do Aeroporto de Barreiras - Dom Ricardo Weberberger - Bahia (SNBR). Fonte de Recurso - Governo Federal - Fundo Nacional de Aviação (FNAC) (INFRA + Equipamentos)*: R$ 65,7 milhões (VALOR INICIALMENTE APROVADO E APOIADO CONFORME SELEÇÃO PAC EM 2023) VIGÊNCIA DO TC 31/12/2024. Licença de Alteração, Portaria INEMA n° 30.754, vigência 14/11/2028) Conforme Seinfra (27/09 - Grupo Whatsapp) a Concessão pemanecerá com a Agerba, vigência até 03/08/2032. Financiamento: FNAC | AY9: CONFORME DEFINIDO EM REUNIÃO COM MINISTÉRIO, GOVERNADOR E SECRETÁRIOS DA C.CIVIL E SEINFRA (29/07/26), OS EQUIPAMENTOS MOBILIÁRIOS FICARÃO SOB A RESPONSABILIDADE DA CONCESSIONÁRIA. O ESTADO NÃO FARÁ AQUISIÇÃO. 16/06/2026 - Conforme Ofício GASEC nº 271/2025, de 05/06/2025, a SEINFRA solicitou à SAC a supressão do TPS e equipamentos e mobiliários do TC 06/2018, para que os mesmos sejam executados com recursos próprios, mantendo apenas a INFRA com recurso do PAC. 08/01/26 - Segundo SEINFRA, a previsão para a divulgação do aviso de licitação da Sinalização é MAR/26, permanecendo sem data a do Mobiliário. 05/11 - Conforme SEINFRA, o novo prazo para publicação de licitação é NOV/25 (iluminação de pátio, luminoso PPD e TWY, Biruta, Farol, Papi, etc.). OBS: Prazo inicial SET/25 foi alterado, devido atraso na apresentação de documentação pela empresa contratada. O TR está em elaboração, o mesmo deve ser encaminhado à PGE após conclusão; Mobiliário: Licitação depende da conclusão do projeto executivo (até DEZ/25) em elaboração pela empresa executora do TPS, para levantamento das necessidades e elaboração de TR e Edital. | BB9: =IFERROR(IF(PAC!$AB9="F01 - CAPTAÇÃO DE RECURSO",1,""),"") | BC9: =IFERROR(IF(PAC!$AB9="F02 - LICITAÇÃO",1,""),"") | BD9: =IFERROR(IF(PAC!$AB$6:$AB$581="F03 - EXECUÇÃO DO OBJETO",1,""),"") -> 1 | BE9: =IFERROR(IF(PAC!$AB$6:$AB$581="F04 - CONCLUÍDA",1,""),"") | BF9: =IF(PAC!$V9>0,0,PAC!$Q9) -> 0
A10: =ROW()-5 -> 5 | B10: 2023 | C10: OBRA | D10: PAC ORIGINAL | E10: Aeroporto de Barreiras (TPS) | F10: Infraestrutura | G10: Aeroporto (TPS) | H10: SEINFRA | I10: 01 - Gov. Estado - SEINFRA | J10: Barreiras | N10: 19342946 | Q10: =SUM(PAC!$M10:$P10) -> 19342946 | V10: 19342946 | W10: =IF(PAC!$V10>0,PAC!$V10,PAC!$Q10) -> 19342946 | X10: CONSORCIO PROJETISTA BARREIRAS | Y10: CONTRAPARTIDA | AA10: 16 | AB10: F03 - EXECUÇÃO DO OBJETO | AC10: 02 - ANDAMENTO | AD10: 46326 | AE10: 52 | AF10: Execução da Obra | AG10: Em fase final da montagem dos pilares metálicos para iniciar cobertura. Novo término de obra previsto para OUT/2026 (medições estão abaixo do desejado). Obra do Terminal iniciada em Jan/26, em regime de contratação integrada. OBSERVAÇÕES: - Existem tratativas técnicas para atender às necessidades da LATAM de iniciar as operações do Aeroporto em NOV/26. Segundo a DTE, a operação independe do conclusão do TPS. - CONFORME DEFINIDO EM REUNIÃO COM MINISTÉRIO, GOVERNADOR E SECRETÁRIOS DA C.CIVIL E SEINFRA (29/07/26), OS EQUIPAMENTOS MOBILIÁRIOS FICARÃO SOB A RESPONSABILIDADE DA CONCESSIONÁRIA. O ESTADO NÃO FARÁ AQUISIÇÃO. Segundo DTE/SEINFRA, não será possível a compatibilização dos cronogramas de execução de INFRA e TPS para entrega total do equipamento em data única, devido às demandas específicas do TPS. | AH10: 46326 | AI10: Monitorar andamento das obras. | AO10: https://governodabahia.plataformatarget.com.br/web/aadaf15d-57f0-4185-8794-6c12c73234bb/home | AP10: https://maps.app.goo.gl/y2A6Z8frmTDtxnL48 | AR10: 45505 | AS10: 45597 | AT10: 45859 | AU10: 45862 | AV10: 46264 | AW10: 46326 | AX10: 16/06/2026 - Conforme Ofício GASEC nº 271/2025, de 05/06/2025, a SEINFRA solicitou à SAC a supressão do TPS e equipamentos e mobiliários do TC 06/2018, para que os mesmos sejam executados com recursos próprios, mantendo apenas a INFRA com recurso do PAC. Orçamento Inicial - R$ 25 milhões. SEI: 024.2058.2024.0005354-18 30/11/24 - Remarcada sessão para divulgação do julgamento das propostas técnicas e de preços de 03/12 para 20/12. 13/11/24 - Remarcada sessão para divulgação do julgamento das propostas técnicas e de preços de 14/11 para 03/12. 01/08 - Publicado Aviso de Licitação CP 027/2024, referente à Contratação integrada para elaboração de Projetos Básicos, Executivos e Construção de Terminal de Passageiros. Abertura 01/11/2024. Elaboração do Projeto básico de TPS e EQUIPAMENTOS/MOBILIÁRIO pela EGIS, foi suspenso, devido a não conclusão, conforme contratação. Definido que o Estado fará licitação com recursos próprios na modalidade Contratação Integrada. TR e Edital para a licitação do TPS finalizados e analisados pela PGE. | AY10: 16/06/2026 - Conforme Ofício GASEC nº 271/2025, de 05/06/2025, a SEINFRA solicitou à SAC a supressão do TPS e equipamentos e mobiliários do TC 06/2018, para que os mesmos sejam executados com recursos próprios, mantendo apenas a INFRA com recurso do PAC. 02/09/25 - Obra em início de mobilização (regime de contratação integrada). Previsão de conclusão conforme Monitora. 24/07/25 - Assinatura da Ordem de Serviço. 23/07/25 - Publicado contrato para elaboração de Projetos Básicos, Executivos e Construção de TPS e edificações auxiliares do Aeroporto de Barreiras, execução 480 dias. | BB10: =IFERROR(IF(PAC!$AB10="F01 - CAPTAÇÃO DE RECURSO",1,""),"") | BC10: =IFERROR(IF(PAC!$AB10="F02 - LICITAÇÃO",1,""),"") | BD10: =IFERROR(IF(PAC!$AB$6:$AB$581="F03 - EXECUÇÃO DO OBJETO",1,""),"") -> 1 | BE10: =IFERROR(IF(PAC!$AB$6:$AB$581="F04 - CONCLUÍDA",1,""),"") | BF10: =IF(PAC!$V10>0,0,PAC!$Q10) -> 0
A11: =ROW()-5 -> 6 | B11: 2023 | C11: OBRA | D11: PAC ORIGINAL | E11: Barragem de Catolé | F11: Água Para Todos | G11: Barragem | H11: SIHS | I11: 05 - Gov. Estado - EMBASA | J11: Barra do Choça | M11: 1.2737858e+08 | N11: 1.0810276e+08 | O11: 6962472.3 | Q11: =SUM(PAC!$M11:$P11) -> 2.4244381e+08 | R11: 1.2737858e+08 | S11: 1.0810276e+08 | T11: 6962472.3 | V11: 2.4244381e+08 | W11: =IF(PAC!$V11>0,PAC!$V11,PAC!$Q11) -> 2.4244381e+08 | X11: CONSÓRCIO CNA (Constituído pelas empresas, CETENCO ENGENHARIA S.A, NOVATEC CONSTRUÇÕES E EMPREENDIMENTOS LTDAe AJDV ENGENHARIA S.A) | Y11: OGU CONTRAPARTIDA COMPLEMENTAR | AA11: 30 | AB11: F03 - EXECUÇÃO DO OBJETO | AC11: 02 - ANDAMENTO | AD11: 46438 | AE11: 70 | AF11: Execução da Obra | AG11: Monitorar a execução da obra | AK11: 0394941-94/2012 | AP11: https://maps.app.goo.gl/tyvHyi6RUcoziRid7 | AR11: 45449 | AS11: 45477 | AT11: 45530 | AU11: 45537 | AV11: 46438 | AW11: 46438 | AX11: Regime de Execução: Empreitada por Preço Global A contrapartida e o valor complementar são de responsabilidade da EMBASA. Ordem de Serviço emitida em 02/09/2024 - retomada de obra (informação EMBASA); Contrato assinado em 27/8/24 com o Consórcio CNA (Cetenco Eng. S.A, Novatec Construções e Emp. Ltda e AJDV Engenhariada - valor R$ 242.443.812,89 | AY11: Obra em execução - PAC II OGU. Valor Termo de Compromisso: R$ 249.132.763,63 Avanço físico Termo de Compromisso: 68,0% O novo modelo de QCI, associando apenas contratos executados e em execução, possibilitou reestruturar a condição dos recursos retidos, assim como o último desbloqueio realizado, eliminou as glosas do empreendimento. Além disso, cabe esclarecer que o valor da Embasa é superior ao acompanhado pela Caixa pois é composto pelo valor contratado mais o valor exclusivo de recursos próprios (Extra TC). | BB11: =IFERROR(IF(PAC!$AB11="F01 - CAPTAÇÃO DE RECURSO",1,""),"") | BC11: =IFERROR(IF(PAC!$AB11="F02 - LICITAÇÃO",1,""),"") | BD11: =IFERROR(IF(PAC!$AB$6:$AB$581="F03 - EXECUÇÃO DO OBJETO",1,""),"") -> 1 | BE11: =IFERROR(IF(PAC!$AB$6:$AB$581="F04 - CONCLUÍDA",1,""),"") | BF11: =IF(PAC!$V11>0,0,PAC!$Q11) -> 0
A12: =ROW()-5 -> 7 | B12: 2023 | C12: OBRA | D12: PAC ORIGINAL | E12: Barragem de Baraúnas / Vazante | F12: Água Para Todos | G12: Barragem | H12: SIHS | I12: 06 - Gov. Estado - CERB | J12: Seabra | M12: 48490064 | N12: 7026635.5 | O12: =20446802.96+11012079.78 -> 31458883 | Q12: =SUM(PAC!$M12:$P12) -> 86975582 | R12: 48490064 | S12: 7026635.5 | T12: =20446802.96+11012079.78 -> 31458883 | V12: 86975582 | W12: =IF(PAC!$V12>0,PAC!$V12,PAC!$Q12) -> 86975582 | X12: Consórcio Barragem Baráunas (RCA Construções e Construtora Augusto Velloso S.A) | Y12: OGU CONTRAPARTIDA COMPLEMENTAR | AB12: F03 - EXECUÇÃO DO OBJETO | AC12: 02 - ANDAMENTO | AD12: 46325 | AE12: 96.13 | AF12: Execução da Obra | AG12: Monitorar a execução da obra | AH12: 46325 | AK12: 421922-59/2013 | AP12: https://maps.app.goo.gl/sTyVoZkV6bZiCSo28 | AR12: 44310 | AS12: 44378 | AT12: 44497 | AU12: 44495 | AV12: 44860 | AW12: 46325 | AX12: CONTRATOS COMPANHIA DE ENGENHARIA HÍDRICA E DE SANEAMENTO DA BAHIA - CERB Extrato do Termo Aditivo nº 137/2025 ao Contrato de Empreitada nº 045/2021 - Processo SEI nº 039.0792.2025.0006319-16. Partes: CERB e o Consórcio Barragem de Baraúnas. Objeto: Alteração do contrato originário com o 2º Reequilíbrio Econômico-financeiro, no valor de R$ 11.012.079,78, que passa a ter o valor total de R$ 99.802.320,54. Data da Assinatura: 04.12.2025. JAYME DE SOUZA VIEIRA LIMA FILHO - Diretor Presidente-CERB. | AY12: Termo Aditivo de Prazo Proposto: Prazo: 122 Dias Final do Prazo de Execução: 30/10/2026 Nova Vigência: 16/12/2026 | BB12: =IFERROR(IF(PAC!$AB12="F01 - CAPTAÇÃO DE RECURSO",1,""),"") | BC12: =IFERROR(IF(PAC!$AB12="F02 - LICITAÇÃO",1,""),"") | BD12: =IFERROR(IF(PAC!$AB$6:$AB$581="F03 - EXECUÇÃO DO OBJETO",1,""),"") -> 1 | BE12: =IFERROR(IF(PAC!$AB$6:$AB$581="F04 - CONCLUÍDA",1,""),"") | BF12: =IF(PAC!$V12>0,0,PAC!$Q12) -> 0
A13: =ROW()-5 -> 8 | B13: 2023 | C13: OBRA | D13: PAC ORIGINAL | E13: Barragem de Morrinhos | F13: Água Para Todos | G13: Barragem | H13: SIHS | I13: 06 - Gov. Estado - CERB | J13: Piripá | L13: 1.3618782e+08 | M13: 1.3618782e+08 | Q13: =SUM(PAC!$M13:$P13) -> 1.3618782e+08 | V13: 1.2942677e+08 | W13: =IF(PAC!$V13>0,PAC!$V13,PAC!$Q13) -> 1.2942677e+08 | X13: CONSÓRCIO BARRAGEM MORRINHOS | Y13: OGU | AA13: 21 | AB13: F02 - LICITAÇÃO | AC13: 04 - LICITAÇÃO /CONTRATAÇÃO | AD13: 46356 | AF13: Enviar documentos para atendimento à Cláusula Suspensiva | AG13: Formalização do Termo Aditivo para acréscimo da contrapartida estadual. Ordem de Serviço parcial emitida em 03/07/2026. A CERB está cumprindo as condicionantes exigidas para obtenção da Licença de Instalação. | AH13: 46356 | AI13: A emissão da Ordem de Serviço definitiva está condicionada à obtenção da licença ambiental, com previsão para agosto de 2027. | AJ13: 092/2024 | AK13: 958195/2024 | AL13: 03 - Cláusula Vigente | AM13: Devido ao acréscimo de serviços para atendimento a licença ambiental o valor inicial da obra foi alterado. O Governo do Estado da Bahia conseguiu destinar a dotação complementar para que a execução da obra da Barragem de Morrinhos seja realizada com o êxito esperado pelo Governo Federal e Estadual. Para tanto se faz necessária a formalização do Termo Aditivo para acréscimo da contrapartida estadual. | AN13: 46356 | AR13: 46097 | AS13: 46120 | AT13: 46206 | AX13: Em processo de formalização do Termo Aditivo de readequação do Plano de Trabalho, bem como a ampliação do valor, com valor da contrapartida Estadual para Execução da Obra: R$ 32.000.000,00 (trinta e dois milhões de reais), para participação, a título de Contrapartida Financeira, no repasse de recursos destinados a Obra e Implantação da Barragem de Morrinhos Ordem de Serviço parcial emitida em 03/07/2026. A CERB está cumprindo as condicionantes exigidas para obtenção da Licença de Instalação. A emissão da Ordem de Serviço definitiva está condicionada à obtenção da licença ambiental, com previsão para agosto de 2027. | AY13: SECRETARIA DE INFRAESTRUTURA HÍDRICA E SANEAMENTO - SIHS COMPANHIA DE ENGENHARIA HÍDRICA E DE SANEAMENTO DA BAHIA - CERB Extrato de Contrato nº 052/2026. Processo Sei nº 039.0781.2024.0005392-92. Partes: CERB e CONSÓRCIO BARRAGEM MORRINHOS. Objeto: contratação de empresa especializada para execução da obra de implantação da Barragem de Morrinhos, situada na Bacia do Rio Gavião, nos Municípios de Piripá, Presidente Jânio Quadros, Condeúba e Cordeiros, no Estado da Bahia. Fundamento: Licitação Pública nº 2026007. Valor: R$ 129.426.772,84. Prazo de execução: 630dias, iniciando-se sua contagem a partir do 7º (sétimo) dia após a emissão da Ordem de Serviço expedida pela CERB. Prazo de vigência: 750 dias, contado do primeiro dia útil subsequente à sua assinatura. Data da Assinatura: 03/07/2026. Larissa Gomes Moraes - Diretora Presidente -CERB. | BB13: =IFERROR(IF(PAC!$AB13="F01 - CAPTAÇÃO DE RECURSO",1,""),"") | BC13: =IFERROR(IF(PAC!$AB13="F02 - LICITAÇÃO",1,""),"") -> 1 | BD13: =IFERROR(IF(PAC!$AB$6:$AB$581="F03 - EXECUÇÃO DO OBJETO",1,""),"") | BE13: =IFERROR(IF(PAC!$AB$6:$AB$581="F04 - CONCLUÍDA",1,""),"") | BF13: =IF(PAC!$V13>0,0,PAC!$Q13) -> 0
A14: =ROW()-5 -> 9 | B14: 2023 | C14: OBRA | D14: PAC ORIGINAL | E14: Barragem de Rio da Caixa | F14: Água Para Todos | G14: Barragem | H14: SIHS | I14: 06 - Gov. Estado - CERB | J14: Rio do Pires | L14: 1.231656e+08 | M14: 1.231656e+08 | O14: 12675392 | Q14: =SUM(PAC!$M14:$P14) -> 1.3584099e+08 | R14: 1.1750931e+08 | T14: 1272765.9 | V14: 1.1878208e+08 | W14: =IF(PAC!$V14>0,PAC!$V14,PAC!$Q14) -> 1.1878208e+08 | X14: Consórcio Barragem Rio da Caixa (RCA, COASTAL e CMR4) | Y14: OGU COMPLEMENTAR | AA14: 21 | AB14: F03 - EXECUÇÃO DO OBJETO | AC14: 02 - ANDAMENTO | AD14: 46590 | AE14: 13.52 | AF14: Execução da Obra | AG14: Monitorar a execução da obra Em análise pelo Ministério a solicitação de PAD - Planilha de Ajustes e Desvios. | AH14: 46590 | AI14: Monitorar a execução da obra | AJ14: 089/2024 | AK14: 958204/2024 | AL14: 01 - Retirada Total | AN14: 46618 | AP14: https://maps.app.goo.gl/DMdCohB9uWSEGHvL6 | AR14: 44792 | AS14: 44817 | AT14: 45376 | AU14: 45553 | AV14: 46198 | AW14: 46590 | AX14: Licitação pretérita EXTRATO De termo aditivo Publicado em: 05/02/2025 | Edição: 25 | Seção: 3 DOU Alteração no valor do repasse do MIDR que passa a ser R$ 123.165.596,20, sendo apenas R$117.509.310,18 para a obra necessitando assim uma complementação financeira do Estado de R$ 1.272.765,95 para atender o valor de contrato para execução da obra. Emitida OS Nº006/2024 - complementar em 18/09/2024. Esta OS é complementar a OS 006/2024 Parcial, de 25/04/2024 ; | AY14: Monitorar a execução da obra Extrato do Termo Aditivo nº 093/2026 ao Contrato nº 022/2024 - Processo SEI n° 039.0795.2026.0004750-71. Partes: CERB e o Consórcio Barragem Rio da Caixa. Objeto: Objeto: Acréscimo no valor do contrato originário em R$ 11.402.625,93, e com a alteração o valor do contrato passa a ser de R$ 130.184.702,06. Data da Assinatura: 29/07/2026.Larissa Gomes Moraes - Diretora Presidente/CERB. | BB14: =IFERROR(IF(PAC!$AB14="F01 - CAPTAÇÃO DE RECURSO",1,""),"") | BC14: =IFERROR(IF(PAC!$AB14="F02 - LICITAÇÃO",1,""),"") | BD14: =IFERROR(IF(PAC!$AB$6:$AB$581="F03 - EXECUÇÃO DO OBJETO",1,""),"") -> 1 | BE14: =IFERROR(IF(PAC!$AB$6:$AB$581="F04 - CONCLUÍDA",1,""),"") | BF14: =IF(PAC!$V14>0,0,PAC!$Q14) -> 0
A15: =ROW()-5 -> 10 | B15: 2023 | C15: OBRA | D15: PAC ORIGINAL | E15: Cont. empresa p/ elaboração de proj. executivo e execução das obras p/ implementação da tomada d’água no RC500 e do canal CP-500/2 – Perímetro de Irrigação Salitre, p/ integração ao Canal do Sertão Baiano. | F15: Água Para Todos | G15: Canal do Sertão | H15: GESTÃO FEDERAL | I15: 07 - Gov. Federal - CODEVASF | J15: Juazeiro | M15: 118800000 | Q15: =SUM(PAC!$M15:$P15) -> 118800000 | W15: =IF(PAC!$V15>0,PAC!$V15,PAC!$Q15) -> 118800000 | Y15: OGU | AA15: 26 | AB15: F03 - EXECUÇÃO DO OBJETO | AC15: 03 - AGUARDANDO ORDEM DE SERVIÇO | AG15: · Alocação da dotação orçamentária necessária para a cobertura da despesa; | AI15: Acompanhamento das obras (Codevasf) | AX15: Regime de Execução: Contratação Semi-Integrada; Extrato de contrato publicado no DOU de 21/01/25 - Empresa: Consórcio Construtor Sertão Baiano - CCSB, formado pelas empresas ÁLYA Construroa SA e Ankara Engenharia Ltda. - Valor: R$ 118.800.000,00; - Prazo de execução: 780 dias. | AY15: Ordem de Serviço dada pelo Presidente Lula em 07/02/25. | BB15: =IFERROR(IF(PAC!$AB15="F01 - CAPTAÇÃO DE RECURSO",1,""),"") | BC15: =IFERROR(IF(PAC!$AB15="F02 - LICITAÇÃO",1,""),"") | BD15: =IFERROR(IF(PAC!$AB$6:$AB$581="F03 - EXECUÇÃO DO OBJETO",1,""),"") -> 1 | BE15: =IFERROR(IF(PAC!$AB$6:$AB$581="F04 - CONCLUÍDA",1,""),"") | BF15: =IF(PAC!$V15>0,0,PAC!$Q15) -> 118800000
A16: =ROW()-5 -> 11 | B16: 2023 | C16: OBRA | D16: PAC SELEÇÕES | E16: Centro de Parto Natural - CPN | F16: Saúde | G16: Centro de Parto | H16: SESAB | I16: 11 - Gov. Estado - SESAB | J16: Ibotirama | L16: 5000000 | M16: 2588139.3 | Q16: =SUM(PAC!$M16:$P16) -> 2588139.3 | V16: 3058146.1 | W16: =IF(PAC!$V16>0,PAC!$V16,PAC!$Q16) -> 3058146.1 | X16: TRILHO ENGENHARIA LTDA | Y16: OGU | AA16: 8 | AB16: F04 - CONCLUÍDA | AC16: 18 - INAUGURADA | AD16: 46094 | AE16: 100 | AI16: - | AJ16: 36000001398/2023 | AO16: https://governodabahia.plataformatarget.com.br/web/a1f7de2e-8d06-4853-ace4-410ad9ffb441/home | AP16: https://maps.app.goo.gl/ZmoJFNyGgdYQ2TP58 | AR16: 45588 | AS16: 45639 | AT16: 45714 | AU16: 45727 | AV16: 45969 | AW16: 46094 | AX16: Valor apoiado pelo Ministério da Saúde: R$3.100.000,00 Planilha orçamentária: R$3.449.948,73 Inaugurada em 22/05/2026 | BA16: OBRA - Projeto Padrão | BB16: =IFERROR(IF(PAC!$AB16="F01 - CAPTAÇÃO DE RECURSO",1,""),"") | BC16: =IFERROR(IF(PAC!$AB16="F02 - LICITAÇÃO",1,""),"") | BD16: =IFERROR(IF(PAC!$AB$6:$AB$581="F03 - EXECUÇÃO DO OBJETO",1,""),"") | BE16: =IFERROR(IF(PAC!$AB$6:$AB$581="F04 - CONCLUÍDA",1,""),"") -> 1 | BF16: =IF(PAC!$V16>0,0,PAC!$Q16) -> 0
A17: =ROW()-5 -> 12 | B17: 2026 | C17: OBRA | D17: PAC SELEÇÕES | E17: Centro Especializado em Reabilitação - CER, Tipo IV | F17: Saúde | G17: CER | H17: SESAB | I17: 11 - Gov. Estado - SESAB | J17: Camaçari | M17: 13847802 | Q17: =SUM(PAC!$M17:$P17) -> 13847802 | V17: 13847802 | W17: =IF(PAC!$V17>0,PAC!$V17,PAC!$Q17) -> 13847802 | X17: Holtz Engenharia Ltda | Y17: OGU | AA17: 10 | AB17: F03 - EXECUÇÃO DO OBJETO | AC17: 02 - ANDAMENTO | AD17: 46472 | AE17: 13 | AF17: Execução da Obra | AG17: Monitorar execução da obra. | AI17: Monitoramento da execução da obra. | AK17: 05816.6300001/25-006 | AP17: https://maps.app.goo.gl/kkjkEj2YgvwCVFmd6?g_st=iw | AR17: 46095 | AS17: 46153 | AT17: 46167 | AU17: 46169 | AV17: 46472 | AW17: 46472 | BA17: OBRA - Projeto Padrão | BB17: =IFERROR(IF(PAC!$AB17="F01 - CAPTAÇÃO DE RECURSO",1,""),"") | BC17: =IFERROR(IF(PAC!$AB17="F02 - LICITAÇÃO",1,""),"") | BD17: =IFERROR(IF(PAC!$AB$6:$AB$581="F03 - EXECUÇÃO DO OBJETO",1,""),"") -> 1 | BE17: =IFERROR(IF(PAC!$AB$6:$AB$581="F04 - CONCLUÍDA",1,""),"") | BF17: =IF(PAC!$V17>0,0,PAC!$Q17) -> 0
A18: =ROW()-5 -> 13 | B18: 2026 | C18: OBRA | D18: PAC SELEÇÕES | E18: Centro Especializado em Reabilitação - CER, Tipo IV | F18: Saúde | G18: CER | H18: SESAB | I18: 11 - Gov. Estado - SESAB | J18: Juazeiro | M18: 12532185 | Q18: =SUM(PAC!$M18:$P18) -> 12532185 | V18: 12532185 | W18: =IF(PAC!$V18>0,PAC!$V18,PAC!$Q18) -> 12532185 | X18: Nove Engenharia LTDA | Y18: OGU | AA18: 10 | AB18: F03 - EXECUÇÃO DO OBJETO | AC18: 02 - ANDAMENTO | AD18: 46485 | AE18: 6 | AF18: Execução da Obra | AG18: Monitorar execução da obra. | AI18: Monitoramento da execução da obra. | AK18: 05816.6300001/25-007 | AP18: https://maps.app.goo.gl/2UqqijCSWKzvdqb67?g_st=iw | AR18: 46095 | AS18: 46155 | AT18: 46185 | AU18: 46185 | AV18: 46485 | AW18: 46485 | BA18: OBRA - Projeto Padrão | BB18: =IFERROR(IF(PAC!$AB18="F01 - CAPTAÇÃO DE RECURSO",1,""),"") | BC18: =IFERROR(IF(PAC!$AB18="F02 - LICITAÇÃO",1,""),"") | BD18: =IFERROR(IF(PAC!$AB$6:$AB$581="F03 - EXECUÇÃO DO OBJETO",1,""),"") -> 1 | BE18: =IFERROR(IF(PAC!$AB$6:$AB$581="F04 - CONCLUÍDA",1,""),"") | BF18: =IF(PAC!$V18>0,0,PAC!$Q18) -> 0
A19: =ROW()-5 -> 14 | B19: 2026 | C19: OBRA | D19: PAC SELEÇÕES | E19: Centro Especializado em Reabilitação - CER, Tipo IV | F19: Saúde | G19: CER | H19: SESAB | I19: 11 - Gov. Estado - SESAB | J19: Conceição do Coité | M19: 12030678 | Q19: =SUM(PAC!$M19:$P19) -> 12030678 | V19: 12030678 | W19: =IF(PAC!$V19>0,PAC!$V19,PAC!$Q19) -> 12030678 | X19: Holtz Engenharia Ltda | Y19: OGU | AA19: 10 | AB19: F03 - EXECUÇÃO DO OBJETO | AC19: 02 - ANDAMENTO | AD19: 46562 | AE19: 0 | AF19: Execução da Obra | AG19: Monitorar execução da obra. | AI19: Monitoramento da execução da obra. | AK19: 05816.6300001/25-012 | AP19: https://maps.app.goo.gl/twd22R7g9MUY82N87?g_st=iw | AR19: 46095 | AS19: 46157 | AT19: 46256 | AU19: 46258 | AV19: 46562 | AW19: 46562 | BA19: OBRA - Projeto Padrão | BB19: =IFERROR(IF(PAC!$AB19="F01 - CAPTAÇÃO DE RECURSO",1,""),"") | BC19: =IFERROR(IF(PAC!$AB19="F02 - LICITAÇÃO",1,""),"") | BD19: =IFERROR(IF(PAC!$AB$6:$AB$581="F03 - EXECUÇÃO DO OBJETO",1,""),"") -> 1 | BE19: =IFERROR(IF(PAC!$AB$6:$AB$581="F04 - CONCLUÍDA",1,""),"") | BF19: =IF(PAC!$V19>0,0,PAC!$Q19) -> 0
A20: =ROW()-5 -> 15 | B20: 2023 | C20: OBRA | D20: PAC SELEÇÕES | E20: Construção do CEU da Cultura | F20: Turismo e Cultura | G20: CEU da Cultura | H20: SECULT | I20: 14 - Gov. Estado - CONDER | J20: Camaçari | M20: 2066482.2 | O20: 718166.39 | Q20: =SUM(PAC!$M20:$P20) -> 2784648.6 | V20: 3251366.2 | W20: =IF(PAC!$V20>0,PAC!$V20,PAC!$Q20) -> 3251366.2 | Y20: OGU COMPLEMENTAR | AA20: 8 | AB20: F02 - LICITAÇÃO | AC20: 03 - AGUARDANDO ORDEM DE SERVIÇO | AF20: Homologar e Adjudicar Licitação | AI20: *VRPL *AIO *OS *Execução da Obra | AJ20: 005325/2024 42000000020/2023 | AK20: 963515/2024 | AL20: 01 - Retirada Total | AO20: https://governodabahia.plataformatarget.com.br/web/daf5d385-da94-4a43-8508-bba423304821/home | AP20: https://maps.app.goo.gl/PyseNPsBHpBCHmAR8 | AR20: 46066 | AS20: 46148 | AX20: Ofício CE 46/2026 enviado em 04/02/2026 solicitando nova prorrogação de prazo para abertura de licitação dos CEUS da Cultura. Ofício CE 16/2026 enviado em 01/01/2026 comunicando conclusão da alteração de valores de Repasse nos Termos de Compromisso. Ofício CE 4680/2025 enviado em 17/10/2025 comunicando Celebração de Termo Aditivo (Adequação do valor de repasse - R$ 2.066.482,18 e inclusão dos valores para aquisição de equipamentos e mobiliários - R$ 492.646,42). Valor Total: R$ 2.559.128,60. | AY20: Empresas Participantes - ART Projetos Construções e Serviços LTDA Consórcio F&R Cultura LP 020 - FCK contruções e Incorporações LTDA / ROBLE Serviços LTDA IFC Engenharia LTDA Consórcio Faria Lima - L3 - CEU CULTURA - Contrutora Faria Lima / Leite Engenharia e Consultoria LTDA Aviso de Licitação publicado no DOE 13/02/26 - Abertura 06/05/26 À Licitar. Ofício CE 19/2026 enviado em 02/01/2026 prorrogando abertura da Licitação para 28/02/2026. 19/11/25 - Aguardando dotação orçamentária para licitar. Elaboração de TR e Edital. (Aguardando Secult definir recurso complementar) (Elaboração de projeto técnico pela conder com previsão até 31/10/25) | BA20: OBRA - Projeto Padrão | BB20: =IFERROR(IF(PAC!$AB20="F01 - CAPTAÇÃO DE RECURSO",1,""),"") | BC20: =IFERROR(IF(PAC!$AB20="F02 - LICITAÇÃO",1,""),"") -> 1 | BD20: =IFERROR(IF(PAC!$AB$6:$AB$581="F03 - EXECUÇÃO DO OBJETO",1,""),"") | BE20: =IFERROR(IF(PAC!$AB$6:$AB$581="F04 - CONCLUÍDA",1,""),"") | BF20: =IF(PAC!$V20>0,0,PAC!$Q20) -> 0
A21: =ROW()-5 -> 16 | B21: 2023 | C21: OBRA | D21: PAC SELEÇÕES | E21: Construção do CEU da Cultura | F21: Turismo e Cultura | G21: CEU da Cultura | H21: SECULT | I21: 14 - Gov. Estado - CONDER | J21: Catu | M21: 2066482.2 | O21: 333538.4 | Q21: =SUM(PAC!$M21:$P21) -> 2400020.6 | V21: 2716453.2 | W21: =IF(PAC!$V21>0,PAC!$V21,PAC!$Q21) -> 2716453.2 | Y21: OGU CONTRAPARTIDA COMPLEMENTAR | AA21: 8 | AB21: F02 - LICITAÇÃO | AC21: 03 - AGUARDANDO ORDEM DE SERVIÇO | AF21: Homologar e Adjudicar Licitação | AI21: *VRPL *AIO *OS *Execução da Obra | AJ21: 005341/2024 42000000335/2023 | AK21: 963558/2024 | AL21: 01 - Retirada Total | AO21: https://governodabahia.plataformatarget.com.br/web/ecd0e843-18de-4c76-abdd-2638559a3ca9/home | AP21: https://maps.app.goo.gl/yEPv7EZEEjr875vV9 | AR21: 46066 | AS21: 46148 | AX21: Ofício CE 46/2026 enviado em 04/02/2026 solicitando nova prorrogação de prazo para abertura de licitação dos CEUS da Cultura. Ofício CE 16/2026 enviado em 01/01/2026 comunicando conclusão da alteração de valores de Repasse nos Termos de Compromisso. Ofício CE 4680/2025 enviado em 17/10/2025 comunicando Celebração de Termo Aditivo (Adequação do valor de repasse - R$ 2.066.482,18 e inclusão dos valores para aquisição de equipamentos e mobiliários - R$ 492.646,42). Valor Total: R$ 2.559.128,60. CE Gigov 2408/2025 solicitação de complementação. Terrenos definidos e tecnicamente aprovados/ Projetos em desenvolvimento. Atendimento as pendências para retirada da Cláusula suspensiva. | AY21: Empresas Participantes -ART Projetos Construções e Serviços LTDA Consórcio F&R Cultura LP 020 - FCK contruções e Incorporações LTDA / ROBLE Serviços LTDA IFC Engenharia LTDA Consórcio Faria Lima - L3 - CEU CULTURA - Contrutora Faria Lima / Leite Engenharia e Consultoria LTDA Aviso de Licitação publicado no DOE 13/02/26 - Abertura 06/05/26 À Licitar. Ofício CE 19/2026 enviado em 02/01/2026 prorrogando abertura da Licitação para 28/02/2026. 19/11/25 - Aguardando dotação orçamentária para licitar. | BA21: OBRA - Projeto Padrão | BB21: =IFERROR(IF(PAC!$AB21="F01 - CAPTAÇÃO DE RECURSO",1,""),"") | BC21: =IFERROR(IF(PAC!$AB21="F02 - LICITAÇÃO",1,""),"") -> 1 | BD21: =IFERROR(IF(PAC!$AB$6:$AB$581="F03 - EXECUÇÃO DO OBJETO",1,""),"") | BE21: =IFERROR(IF(PAC!$AB$6:$AB$581="F04 - CONCLUÍDA",1,""),"") | BF21: =IF(PAC!$V21>0,0,PAC!$Q21) -> 0
A22: =ROW()-5 -> 17 | B22: 2023 | C22: OBRA | D22: PAC SELEÇÕES | E22: Construção do CEU da Cultura | F22: Turismo e Cultura | G22: CEU da Cultura | H22: SECULT | I22: 14 - Gov. Estado - CONDER | J22: Santo Amaro | M22: 2066482.2 | O22: 555569.94 | Q22: =SUM(PAC!$M22:$P22) -> 2622052.1 | V22: 3199451.6 | W22: =IF(PAC!$V22>0,PAC!$V22,PAC!$Q22) -> 3199451.6 | Y22: OGU CONTRAPARTIDA COMPLEMENTAR | AA22: 8 | AB22: F02 - LICITAÇÃO | AC22: 03 - AGUARDANDO ORDEM DE SERVIÇO | AF22: Homologar e Adjudicar Licitação | AI22: *VRPL *AIO *OS *Execução da Obra | AJ22: 005337/2024 42000000270/2023 | AK22: 963523/2024 | AL22: 01 - Retirada Total | AO22: https://governodabahia.plataformatarget.com.br/web/0d0a423d-c272-415d-b811-b0fe69a309e2/home | AP22: https://maps.app.goo.gl/RKehfZFMWzKqUiiq9 | AR22: 46066 | AS22: 46148 | AX22: Ofício CE 46/2026 enviado em 04/02/2026 solicitando nova prorrogação de prazo para abertura de licitação dos CEUS da Cultura. Ofício CE 16/2026 enviado em 01/01/2026 comunicando conclusão da alteração de valores de Repasse nos Termos de Compromisso. Ofício CE 4680/2025 enviado em 17/10/2025 comunicando Celebração de Termo Aditivo (Adequação do valor de repasse - R$ 2.066.482,18 e inclusão dos valores para aquisição de equipamentos e mobiliários - R$ 492.646,42). Valor Total: R$ 2.559.128,60. Emissão do LAE. A Conder elaborou um estudo preliminar, já ecaminhado e em posse do município, que atualmente se encontra em fase de planejamento, compatibilização e adequação dos elementos arquitetónicos passíveis de tal demandas e realidades locais. O terreno se locliza próximo á Ruínas do Irapuru muito relevante para memória regional. Terreno possui matrícula e escritura. Terrenos definidos e tecnicamente aprovados/ Projetos em desenvolvimento | AY22: Empresas Participantes -ART Projetos Construções e Serviços LTDA Consórcio F&R Cultura LP 020 - FCK contruções e Incorporações LTDA / ROBLE Serviços LTDA IFC Engenharia LTDA Consórcio Faria Lima - L3 - CEU CULTURA - Contrutora Faria Lima / Leite Engenharia e Consultoria LTDA Aviso de Licitação publicado no DOE 13/02/26 - Abertura 06/05/26 À Licitar. Ofício CE 19/2026 enviado em 02/01/2026 prorrogando abertura da Licitação para 28/02/2026. 19/11/25 - Aguardando dotação orçamentária para licitar. | BA22: OBRA - Projeto Padrão | BB22: =IFERROR(IF(PAC!$AB22="F01 - CAPTAÇÃO DE RECURSO",1,""),"") | BC22: =IFERROR(IF(PAC!$AB22="F02 - LICITAÇÃO",1,""),"") -> 1 | BD22: =IFERROR(IF(PAC!$AB$6:$AB$581="F03 - EXECUÇÃO DO OBJETO",1,""),"") | BE22: =IFERROR(IF(PAC!$AB$6:$AB$581="F04 - CONCLUÍDA",1,""),"") | BF22: =IF(PAC!$V22>0,0,PAC!$Q22) -> 0
A23: =ROW()-5 -> 18 | B23: 2023 | C23: OBRA | D23: PAC SELEÇÕES | E23: Construção do CEU da Cultura | F23: Turismo e Cultura | G23: CEU da Cultura | H23: SECULT | I23: 14 - Gov. Estado - CONDER | J23: Bom Jesus da Lapa | M23: 2066482.2 | O23: 289993.02 | Q23: =SUM(PAC!$M23:$P23) -> 2356475.2 | V23: 2541702.9 | W23: =IF(PAC!$V23>0,PAC!$V23,PAC!$Q23) -> 2541702.9 | X23: CONSÓRCIO TRILHO/FPE - (TRILHO ENGENHARIA LTDA / FÁBIO PERA ARQUITETO LTDA) | Y23: OGU CONTRAPARTIDA COMPLEMENTAR | AA23: 8 | AB23: F03 - EXECUÇÃO DO OBJETO | AC23: 02 - ANDAMENTO | AF23: Emissão do aceite VRPL | AG23: Conder enviar documentação para Caixa para obtenção do VRPL | AI23: *VRPL *AIO *OS *Execução da Obra | AJ23: 005327/2024 42000000025/2023 | AK23: 963522/2024 | AL23: 01 - Retirada Total | AO23: https://governodabahia.plataformatarget.com.br/web/bb718052-2b62-4143-ba89-4f1b5cf64f96/home | AP23: https://maps.app.goo.gl/KURtToAEqZ99jEFF6 | AR23: 46066 | AS23: 46147 | AT23: 46239 | AX23: 07/10/26 - SERVIÇOS CONCLUÍDOS: Instalação de placa de obra. SERVIÇO À INICIAR: Instalação de Tapume metálico (PREVISÃO: 13/10/2026); Serviços Preliminares; Terraplenagem ; Elaboração de Projetos; Fundações; Superestrutura; Cobertura; Paredes e painéis; Esquadrias; Sistemas hidráulicos, Sanitários e de combate a incêndio(HSI); Sistema elétrico e sistema de voz e dados; Sistemas de ar condicionado, ventilação e exaustão; Revestimentos primários; Acabamentos (revestimento para teto, parede e piso); Acabamentos (hidrossanitários); Acabamentos (elétricos, voz, dados e tv); Pintura; Urbanização e paisagismo; Desmobilização de canteiro e Limpeza final. Obs.: A empresa está em processo de elaboração dos projetos executivos, previsão para iniciar a obra após a aprovação. Ofício CE 46/2026 enviado em 04/02/2026 solicitando nova prorrogação de prazo para abertura de licitação dos CEUS da Cultura. Ofício CE 16/2026 enviado em 01/01/2026 comunicando conclusão da alteração de valores de Repasse nos Termos de Compromisso. Ofício CE 4680/2025 enviado em 17/10/2025 comunicando Celebração de Termo Aditivo (Adequação do valor de repasse - R$ 2.066.482,18 e inclusão dos valores para aquisição de equipamentos e mobiliários - R$ 492.646,42). Valor Total: R$ 2.559.128,60. Solicitação de ordenador de despesas 043.4110.2025.0017422-24 enviado para SECULT em 07/10/2025. Terrenos definidos e tecnicamente aprovados/ Projetos aprovados possíveis de licitação | AY23: NOTIFICAÇÃO DE RECURSO DA LICITAÇÃO PRESENCIAL Nº 019/26 - SERRA DO RAMALHO, BOM JESUS DA LAPA, MACAÚBAS E SEABRA - CONDER - publicada no DOE em 21/07/2026 Empresas participantes Consórcio TRILHO/FPE ( Trilho engenharia LTDA/ Fábio Pera arquiteto LTDA) e ART projetos construções e serviços LTDA Aviso de Licitação publicado no DOE 13/02/26 - Abertura 05/05/26 À Licitar. Ofício CE 19/2026 enviado em 02/01/2026 prorrogando abertura da Licitação para 28/02/2026. 19/11/25 - Aguardando dotação orçamentária para licitar. | BA23: OBRA - Projeto Padrão | BB23: =IFERROR(IF(PAC!$AB23="F01 - CAPTAÇÃO DE RECURSO",1,""),"") | BC23: =IFERROR(IF(PAC!$AB23="F02 - LICITAÇÃO",1,""),"") | BD23: =IFERROR(IF(PAC!$AB$6:$AB$581="F03 - EXECUÇÃO DO OBJETO",1,""),"") -> 1 | BE23: =IFERROR(IF(PAC!$AB$6:$AB$581="F04 - CONCLUÍDA",1,""),"") | BF23: =IF(PAC!$V23>0,0,PAC!$Q23) -> 0
A24: =ROW()-5 -> 19 | B24: 2023 | C24: OBRA | D24: PAC SELEÇÕES | E24: Construção do CEU da Cultura | F24: Turismo e Cultura | G24: CEU da Cultura | H24: SECULT | I24: 14 - Gov. Estado - CONDER | J24: Macaúbas | M24: 2066482.2 | O24: 506924.27 | Q24: =SUM(PAC!$M24:$P24) -> 2573406.5 | V24: 2889910.7 | W24: =IF(PAC!$V24>0,PAC!$V24,PAC!$Q24) -> 2889910.7 | X24: CONSÓRCIO TRILHO/FPE - (TRILHO ENGENHARIA LTDA / FÁBIO PERA ARQUITETO LTDA) | Y24: OGU CONTRAPARTIDA COMPLEMENTAR | AA24: 8 | AB24: F03 - EXECUÇÃO DO OBJETO | AC24: 02 - ANDAMENTO | AF24: Emissão do aceite VRPL | AG24: Conder enviar documentação para Caixa para obtenção do VRPL | AI24: *VRPL *AIO *OS *Execução da Obra | AJ24: 005343/2024 42000000343/2023 | AK24: 963561/2024 | AL24: 01 - Retirada Total | AO24: https://governodabahia.plataformatarget.com.br/web/81a0d0b6-c095-4caa-b78d-0655b42caed5/home | AP24: https://maps.app.goo.gl/YycXB4MzLASDnNFS8 | AR24: 46066 | AS24: 46147 | AT24: 46239 | AX24: 07/10/26 -SERVIÇO À INICIAR: Instalação de placa de obra; Instalação de Tapume metálico ; Serviços Preliminares; Terraplenagem ; Elaboração de Projetos; Fundações; Superestrutura; Cobertura; Paredes e painéis; Esquadrias; Sistemas hidráulicos, Sanitários e de combate a incêndio(HSI); Sistema elétrico e sistema de voz e dados; Sistemas de ar condicionado, ventilação e exaustão; Revestimentos primários; Acabamentos (revestimento para teto, parede e piso); Acabamentos (hidrossanitários); Acabamentos (elétricos, voz, dados e tv); Pintura; Urbanização e paisagismo; Desmobilização de canteiro e Limpeza final. Obs.: A prefeitura está fazendo a permuta do terreno. Ofício CE 46/2026 enviado em 04/02/2026 solicitando nova prorrogação de prazo para abertura de licitação dos CEUS da Cultura. Ofício CE 16/2026 enviado em 01/01/2026 comunicando conclusão da alteração de valores de Repasse nos Termos de Compromisso. Ofício CE 4680/2025 enviado em 17/10/2025 comunicando Celebração de Termo Aditivo (Adequação do valor de repasse - R$ 2.066.482,18 e inclusão dos valores para aquisição de equipamentos e mobiliários - R$ 492.646,42). Valor Total: R$ 2.559.128,60. Solicitação de ordenador de despesas 043.4110.2025.0017422-24 enviado para SECULT em 07/10/2025. Terreno indicada não cabe, mas há espaço para ampliação, foi solicitada ajuste da poligonal. Conclusão automática da SPA. Aguardando autorização pela Caixa para licitar. Aguardando definição de recurso compelementar pela Secult. Elaboração de TR e Edital. | AY24: NOTIFICAÇÃO DE RECURSO DA LICITAÇÃO PRESENCIAL Nº 019/26 - SERRA DO RAMALHO, BOM JESUS DA LAPA, MACAÚBAS E SEABRA - CONDER - publicada no DOE em 21/07/2026 Empresas participantes Consórcio TRILHO/FPE ( Trilho engenharia LTDA/ Fábio Pera arquiteto LTDA) e ART projetos construções e serviços LTDA Aviso de Licitação publicado no DOE 13/02/26 - Abertura 05/05/26 À Licitar. Ofício CE 19/2026 enviado em 02/01/2026 prorrogando abertura da Licitação para 28/02/2026. 19/11/25 - Aguardando dotação orçamentária para licitar. | BA24: OBRA - Projeto Padrão | BB24: =IFERROR(IF(PAC!$AB24="F01 - CAPTAÇÃO DE RECURSO",1,""),"") | BC24: =IFERROR(IF(PAC!$AB24="F02 - LICITAÇÃO",1,""),"") | BD24: =IFERROR(IF(PAC!$AB$6:$AB$581="F03 - EXECUÇÃO DO OBJETO",1,""),"") -> 1 | BE24: =IFERROR(IF(PAC!$AB$6:$AB$581="F04 - CONCLUÍDA",1,""),"") | BF24: =IF(PAC!$V24>0,0,PAC!$Q24) -> 0
A25: =ROW()-5 -> 20 | B25: 2023 | C25: OBRA | D25: PAC SELEÇÕES | E25: Construção do CEU da Cultura | F25: Turismo e Cultura | G25: CEU da Cultura | H25: SECULT | I25: 14 - Gov. Estado - CONDER | J25: Dias D'Ávila | M25: 2066482.2 | O25: 2034674.3 | Q25: =SUM(PAC!$M25:$P25) -> 4101156.5 | V25: 2913740.5 | W25: =IF(PAC!$V25>0,PAC!$V25,PAC!$Q25) -> 2913740.5 | X25: ROBLE SERVIÇOS LTDA e FCK CONSTRUÇÕES E INCORPORAÇÕES LTDA | Y25: OGU CONTRAPARTIDA COMPLEMENTAR | AA25: 8 | AB25: F02 - LICITAÇÃO | AC25: 03 - AGUARDANDO ORDEM DE SERVIÇO | AF25: Homologar e Adjudicar Licitação | AI25: *VRPL *AIO *OS *Execução da Obra | AK25: 963496/2024 | AL25: 01 - Retirada Total | AR25: 46066 | AS25: 46146 | AT25: 46224 | AX25: Notificação de Recurso publicada no DOE 27/06/2026 Ofício CE 46/2026 enviado em 04/02/2026 solicitando nova prorrogação de prazo para abertura de licitação dos CEUS da Cultura. Ofício CE 16/2026 enviado em 01/01/2026 comunicando conclusão da alteração de valores de Repasse nos Termos de Compromisso. Ofício CE 4680/2025 enviado em 17/10/2025 comunicando Celebração de Termo Aditivo (Adequação do valor de repasse - R$ 2.066.482,18 e inclusão dos valores para aquisição de equipamentos e mobiliários - R$ 492.646,42). Valor Total: R$ 2.559.128,60. | AY25: Empresas participantes -INO9VARE Enganharia LTDA Consórcio F&R Cultura LP 017 - FCK contruções e Incorporações LTDA / ROBLE Serviços LTDA Aviso de Licitação publicado no DOE 13/02/26 - Abertura 04/05/26 À Licitar. Ofício CE 19/2026 enviado em 02/01/2026 prorrogando abertura da Licitação para 28/02/2026. 19/11/25 - Aguardando dotação orçamentária para licitar. | BA25: OBRA - Projeto Padrão | BB25: =IFERROR(IF(PAC!$AB25="F01 - CAPTAÇÃO DE RECURSO",1,""),"") | BC25: =IFERROR(IF(PAC!$AB25="F02 - LICITAÇÃO",1,""),"") -> 1 | BD25: =IFERROR(IF(PAC!$AB$6:$AB$581="F03 - EXECUÇÃO DO OBJETO",1,""),"") | BE25: =IFERROR(IF(PAC!$AB$6:$AB$581="F04 - CONCLUÍDA",1,""),"") | BF25: =IF(PAC!$V25>0,0,PAC!$Q25) -> 0
A26: =ROW()-5 -> 21 | B26: 2023 | C26: OBRA | D26: PAC SELEÇÕES | E26: Construção do CEU da Cultura | F26: Turismo e Cultura | G26: CEU da Cultura | H26: SECULT | I26: 14 - Gov. Estado - CONDER | J26: Senhor do Bonfim | M26: 2066482.2 | O26: 368521.17 | Q26: =SUM(PAC!$M26:$P26) -> 2435003.4 | V26: 2617664.7 | W26: =IF(PAC!$V26>0,PAC!$V26,PAC!$Q26) -> 2617664.7 | X26: ART PROJETOS CONSTRUÇÕES E SERVIÇOS LTDA. | Y26: OGU CONTRAPARTIDA COMPLEMENTAR | AA26: 8 | AB26: F02 - LICITAÇÃO | AC26: 03 - AGUARDANDO ORDEM DE SERVIÇO | AF26: Homologar e Adjudicar Licitação | AI26: *AIO *OS *Execução da Obra | AJ26: 005329/2024 42000000028/2023 | AK26: 963474/2024 | AL26: 01 - Retirada Total | AO26: https://governodabahia.plataformatarget.com.br/web/a7cf4c50-61a0-435a-94b6-47c954241d7a/home | AP26: https://maps.app.goo.gl/Rrn4cPWUu2apobkQ6 | AR26: 46066 | AS26: 46147 | AX26: Ofício CE 46/2026 enviado em 04/02/2026 solicitando nova prorrogação de prazo para abertura de licitação dos CEUS da Cultura. Ofício CE 16/2026 enviado em 01/01/2026 comunicando conclusão da alteração de valores de Repasse nos Termos de Compromisso. Ofício CE 4680/2025 enviado em 17/10/2025 comunicando Celebração de Termo Aditivo (Adequação do valor de repasse - R$ 2.066.482,18 e inclusão dos valores para aquisição de equipamentos e mobiliários - R$ 492.646,42). Valor Total: R$ 2.559.128,60. Solicitação de Ordenador de Despesas 043.4110.2025.0018290-01 enviado para SECULT em 13/10/2025. Terrenos definidos e tecnicamente aprovados/ Projetos em desenvolvimento visando licitação. | AY26: Empresas participantes - ART Projetos Construções e Serviços LTDA Consórcio F&R Cultura LP 018 - FCK contruções e Incorporações LTDA / ROBLE Serviços LTDA IFC Engenharia LTDA Aviso de Licitação publicado no DOE 13/02/26 - Abertura 05/05/26 À Licitar. Ofício CE 19/2026 enviado em 02/01/2026 prorrogando abertura da Licitação para 28/02/2026. 19/11/25 - Aguardando dotação orçamentária para licitar. | BA26: OBRA - Projeto Padrão | BB26: =IFERROR(IF(PAC!$AB26="F01 - CAPTAÇÃO DE RECURSO",1,""),"") | BC26: =IFERROR(IF(PAC!$AB26="F02 - LICITAÇÃO",1,""),"") -> 1 | BD26: =IFERROR(IF(PAC!$AB$6:$AB$581="F03 - EXECUÇÃO DO OBJETO",1,""),"") | BE26: =IFERROR(IF(PAC!$AB$6:$AB$581="F04 - CONCLUÍDA",1,""),"") | BF26: =IF(PAC!$V26>0,0,PAC!$Q26) -> 0
A27: =ROW()-5 -> 22 | B27: 2023 | C27: OBRA | D27: PAC SELEÇÕES | E27: Construção do CEU da Cultura | F27: Turismo e Cultura | G27: CEU da Cultura | H27: SECULT | I27: 14 - Gov. Estado - CONDER | J27: Jeremoabo | M27: 2066482.2 | O27: 349218.83 | Q27: =SUM(PAC!$M27:$P27) -> 2415701 | V27: 2579083.4 | W27: =IF(PAC!$V27>0,PAC!$V27,PAC!$Q27) -> 2579083.4 | X27: ART PROJETOS CONSTRUÇÕES E SERVIÇOS LTDA. | Y27: OGU CONTRAPARTIDA COMPLEMENTAR | AA27: 8 | AB27: F02 - LICITAÇÃO | AC27: 03 - AGUARDANDO ORDEM DE SERVIÇO | AF27: Homologar e Adjudicar Licitação | AI27: *AIO *OS *Execução da Obra | AJ27: 005331/2024 42000000037/2023 | AK27: 963492/2024 | AL27: 01 - Retirada Total | AO27: https://governodabahia.plataformatarget.com.br/web/84198b2e-bf78-44a9-9785-8e982953e691/home | AP27: https://maps.app.goo.gl/K2qcBkesDemh3P626 | AR27: 46066 | AS27: 46147 | AX27: Ofício CE 46/2026 enviado em 04/02/2026 solicitando nova prorrogação de prazo para abertura de licitação dos CEUS da Cultura.Ofício CE 46/2026 enviado em 04/02/2026 solicitando nova prorrogação de prazo para abertura de licitação dos CEUS da Cultura. Ofício CE 16/2026 enviado em 01/01/2026 comunicando conclusão da alteração de valores de Repasse nos Termos de Compromisso. Ofício CE 4680/2025 enviado em 17/10/2025 comunicando Celebração de Termo Aditivo (Adequação do valor de repasse - R$ 2.066.482,18 e inclusão dos valores para aquisição de equipamentos e mobiliários - R$ 492.646,42). Valor Total: R$ 2.559.128,60. Solicitação de Ordenador de Despesas 043.4110.2025.0018290-01 enviado para SECULT em 13/10/2025. Terrenos definidos e tecnicamente aprovados/ Projetos em desenvolvimento visando licitação. | AY27: Empresas participantes - ART Projetos Construções e Serviços LTDA Consórcio F&R Cultura LP 018 - FCK contruções e Incorporações LTDA / ROBLE Serviços LTDA IFC Engenharia LTDA Aviso de Licitação publicado no DOE 13/02/26 - Abertura 05/05/26 À Licitar. Ofício CE 19/2026 enviado em 02/01/2026 prorrogando abertura da Licitação para 28/02/2026. 19/11/25 - Aguardando dotação orçamentária para licitar. | BA27: OBRA - Projeto Padrão | BB27: =IFERROR(IF(PAC!$AB27="F01 - CAPTAÇÃO DE RECURSO",1,""),"") | BC27: =IFERROR(IF(PAC!$AB27="F02 - LICITAÇÃO",1,""),"") -> 1 | BD27: =IFERROR(IF(PAC!$AB$6:$AB$581="F03 - EXECUÇÃO DO OBJETO",1,""),"") | BE27: =IFERROR(IF(PAC!$AB$6:$AB$581="F04 - CONCLUÍDA",1,""),"") | BF27: =IF(PAC!$V27>0,0,PAC!$Q27) -> 0
A28: =ROW()-5 -> 23 | B28: 2023 | C28: OBRA | D28: PAC SELEÇÕES | E28: Construção do CEU da Cultura | F28: Turismo e Cultura | G28: CEU da Cultura | H28: SECULT | I28: 14 - Gov. Estado - CONDER | J28: Itiúba | M28: 2066482.2 | O28: 764378.48 | Q28: =SUM(PAC!$M28:$P28) -> 2830860.7 | V28: 2784091.1 | W28: =IF(PAC!$V28>0,PAC!$V28,PAC!$Q28) -> 2784091.1 | X28: ART PROJETOS CONSTRUÇÕES E SERVIÇOS LTDA. | Y28: OGU CONTRAPARTIDA COMPLEMENTAR | AA28: 8 | AB28: F02 - LICITAÇÃO | AC28: 03 - AGUARDANDO ORDEM DE SERVIÇO | AF28: Homologar e Adjudicar Licitação | AI28: *AIO *OS *Execução da Obra | AJ28: 005342/2024 42000000342/2023 | AK28: 963560/2024 | AL28: 01 - Retirada Total | AO28: https://governodabahia.plataformatarget.com.br/web/e8527da7-efa1-44ce-b2f3-61e7763c258d/home | AP28: https://maps.app.goo.gl/PG5xfUpR8YuzVnWm9 | AR28: 46066 | AS28: 46147 | AX28: Ofício CE 46/2026 enviado em 04/02/2026 solicitando nova prorrogação de prazo para abertura de licitação dos CEUS da Cultura. Ofício CE 46/2026 enviado em 04/02/2026 solicitando nova prorrogação de prazo para abertura de licitação dos CEUS da Cultura. Ofício CE 16/2026 enviado em 01/01/2026 comunicando conclusão da alteração de valores de Repasse nos Termos de Compromisso. Ofício CE 4680/2025 enviado em 17/10/2025 comunicando Celebração de Termo Aditivo (Adequação do valor de repasse - R$ 2.066.482,18 e inclusão dos valores para aquisição de equipamentos e mobiliários - R$ 492.646,42). Valor Total: R$ 2.559.128,60. Solicitação de Ordenador de Despesas 043.4110.2025.0018290-01 enviado para SECULT em 13/10/2025. Terrenos definidos e tecnicamente aprovados/ Projetos em desenvolvimento visando licitação. | AY28: Empresas participantes - ART Projetos Construções e Serviços LTDA Consórcio F&R Cultura LP 018 - FCK contruções e Incorporações LTDA / ROBLE Serviços LTDA IFC Engenharia LTDA Aviso de Licitação publicado no DOE 13/02/26 - Abertura 05/05/26 À Licitar. Ofício CE 19/2026 enviado em 02/01/2026 prorrogando abertura da Licitação para 28/02/2026. 19/11/25 - Aguardando dotação orçamentária para licitar. | BA28: OBRA - Projeto Padrão | BB28: =IFERROR(IF(PAC!$AB28="F01 - CAPTAÇÃO DE RECURSO",1,""),"") | BC28: =IFERROR(IF(PAC!$AB28="F02 - LICITAÇÃO",1,""),"") -> 1 | BD28: =IFERROR(IF(PAC!$AB$6:$AB$581="F03 - EXECUÇÃO DO OBJETO",1,""),"") | BE28: =IFERROR(IF(PAC!$AB$6:$AB$581="F04 - CONCLUÍDA",1,""),"") | BF28: =IF(PAC!$V28>0,0,PAC!$Q28) -> 0
A29: =ROW()-5 -> 24 | B29: 2023 | C29: OBRA | D29: PAC SELEÇÕES | E29: Construção do CEU da Cultura | F29: Turismo e Cultura | G29: CEU da Cultura | H29: SECULT | I29: 14 - Gov. Estado - CONDER | J29: Juazeiro | M29: 2066482.2 | O29: 361079.96 | Q29: =SUM(PAC!$M29:$P29) -> 2427562.1 | V29: 2667050.3 | W29: =IF(PAC!$V29>0,PAC!$V29,PAC!$Q29) -> 2667050.3 | X29: ART PROJETOS CONSTRUÇÕES E SERVIÇOS LTDA. | Y29: OGU CONTRAPARTIDA COMPLEMENTAR | AA29: 8 | AB29: F02 - LICITAÇÃO | AC29: 03 - AGUARDANDO ORDEM DE SERVIÇO | AF29: Homologar e Adjudicar Licitação | AI29: *AIO *OS *Execução da Obra | AJ29: 005338/2024 42000000290/2023 | AK29: 963526/2024 | AL29: 01 - Retirada Total | AO29: https://governodabahia.plataformatarget.com.br/web/d9359efa-cc67-4a4f-87ce-ef74c9cd6bce/home | AP29: https://maps.app.goo.gl/kBMMoG4jJaEiZ3B59 | AR29: 46066 | AS29: 46147 | AX29: Ofício CE 46/2026 enviado em 04/02/2026 solicitando nova prorrogação de prazo para abertura de licitação dos CEUS da Cultura. Ofício CE 16/2026 enviado em 01/01/2026 comunicando conclusão da alteração de valores de Repasse nos Termos de Compromisso. Ofício CE 4680/2025 enviado em 17/10/2025 comunicando Celebração de Termo Aditivo (Adequação do valor de repasse - R$ 2.066.482,18 e inclusão dos valores para aquisição de equipamentos e mobiliários - R$ 492.646,42). Valor Total: R$ 2.559.128,60. Solicitação de Ordenador de Despesas 043.4110.2025.0018290-01 enviado para SECULT em 13/10/2025. A Conder elaborou um estudo preliminar, já ecaminhado e em posse do município, que atualmente se encontra em fase de planejamento, compatinilização e adequação dos elementos arquitetónicos passíveis de tal demandas e realidades locais. - Ce Gigov 2408/2025 solicitação de complementação. Terrenos definidos e tecnicamente aprovados/ Projetos em desenvolvimento visando licitação Atendimento as pendências para retirada da Cláusula suspensiva. | AY29: Empresas participantes - ART Projetos Construções e Serviços LTDA Consórcio F&R Cultura LP 018 - FCK contruções e Incorporações LTDA / ROBLE Serviços LTDA IFC Engenharia LTDA Aviso de Licitação publicado no DOE 13/02/26 - Abertura 05/05/26 À Licitar. Ofício CE 19/2026 enviado em 02/01/2026 prorrogando abertura da Licitação para 28/02/2026. 19/11/25 - Aguardando dotação orçamentária para licitar. | BA29: OBRA - Projeto Padrão | BB29: =IFERROR(IF(PAC!$AB29="F01 - CAPTAÇÃO DE RECURSO",1,""),"") | BC29: =IFERROR(IF(PAC!$AB29="F02 - LICITAÇÃO",1,""),"") -> 1 | BD29: =IFERROR(IF(PAC!$AB$6:$AB$581="F03 - EXECUÇÃO DO OBJETO",1,""),"") | BE29: =IFERROR(IF(PAC!$AB$6:$AB$581="F04 - CONCLUÍDA",1,""),"") | BF29: =IF(PAC!$V29>0,0,PAC!$Q29) -> 0
A30: =ROW()-5 -> 25 | B30: 2023 | C30: OBRA | D30: PAC SELEÇÕES | E30: Construção do CEU da Cultura | F30: Turismo e Cultura | G30: CEU da Cultura | H30: SECULT | I30: 14 - Gov. Estado - CONDER | J30: Maragogipe | M30: 2066482.2 | O30: 639858.14 | Q30: =SUM(PAC!$M30:$P30) -> 2706340.3 | V30: 3280528.9 | W30: =IF(PAC!$V30>0,PAC!$V30,PAC!$Q30) -> 3280528.9 | X30: ROBLE SERVIÇOS LTDA e FCK CONSTRUÇÕES E INCORPORAÇÕES LTDA | Y30: OGU CONTRAPARTIDA COMPLEMENTAR | AA30: 8 | AB30: F02 - LICITAÇÃO | AC30: 03 - AGUARDANDO ORDEM DE SERVIÇO | AF30: Homologar e Adjudicar Licitação | AI30: *VRPL *AIO *OS *Execução da Obra | AJ30: 005344/2024 42000000344/2023 | AK30: 963563/2024 | AL30: 01 - Retirada Total | AO30: https://governodabahia.plataformatarget.com.br/web/ccd5d90d-154b-43f1-98f0-84059b3670af/home | AP30: https://maps.app.goo.gl/H2bUp8csHK3eCiUP7 | AR30: 46066 | AS30: 46146 | AT30: 46224 | AX30: Notificação de Recurso publicada no DOE 27/06/2026 Ofício CE 46/2026 enviado em 04/02/2026 solicitando nova prorrogação de prazo para abertura de licitação dos CEUS da Cultura. Ofício CE 16/2026 enviado em 01/01/2026 comunicando conclusão da alteração de valores de Repasse nos Termos de Compromisso. Ofício CE 4680/2025 enviado em 17/10/2025 comunicando Celebração de Termo Aditivo (Adequação do valor de repasse - R$ 2.066.482,18 e inclusão dos valores para aquisição de equipamentos e mobiliários - R$ 492.646,42). Valor Total: R$ 2.559.128,60. O município apresentou designação de área, em sua posse, entretando, a poligonal disponibilizada não cabia em dimensões físicas a implantação do projeto dessa forma o terreno foi inviabilizado pela Conder. Foi apresentado a inviabilidade ao município, que em resposta apresentou outra poligonal para implantação. Esta nova poligonal foi alocada em cima de outro equipamento cultural pré-existente, uma praça pública mobiliada. Visita técnica marcada para 19/05/25 Secult, Casa civil. Terreno indicado localizado em Área de Preservação Permanente - APP, margem do Rio Paraguaçu. Terreno indicado e tecnicamente com pendências / Realizada entrega parcial da documentação - pendentes estudos topográficos e geotécnicos. | AY30: Empresas participantes -INO9VARE Enganharia LTDA Consórcio F&R Cultura LP 017 - FCK contruções e Incorporações LTDA / ROBLE Serviços LTDA Aviso de Licitação publicado no DOE 13/02/26 - Abertura 04/05/26 À Licitar. Ofício CE 19/2026 enviado em 02/01/2026 prorrogando abertura da Licitação para 28/02/2026. 19/11/25 - Aguardando dotação orçamentária para licitar. | BA30: OBRA - Projeto Padrão | BB30: =IFERROR(IF(PAC!$AB30="F01 - CAPTAÇÃO DE RECURSO",1,""),"") | BC30: =IFERROR(IF(PAC!$AB30="F02 - LICITAÇÃO",1,""),"") -> 1 | BD30: =IFERROR(IF(PAC!$AB$6:$AB$581="F03 - EXECUÇÃO DO OBJETO",1,""),"") | BE30: =IFERROR(IF(PAC!$AB$6:$AB$581="F04 - CONCLUÍDA",1,""),"") | BF30: =IF(PAC!$V30>0,0,PAC!$Q30) -> 0
A31: =ROW()-5 -> 26 | B31: 2023 | C31: OBRA | D31: PAC SELEÇÕES | E31: Construção do CEU da Cultura | F31: Turismo e Cultura | G31: CEU da Cultura | H31: SECULT | I31: 14 - Gov. Estado - CONDER | J31: Seabra | M31: 2066482.2 | O31: 530259.72 | Q31: =SUM(PAC!$M31:$P31) -> 2596741.9 | V31: 2692126 | W31: =IF(PAC!$V31>0,PAC!$V31,PAC!$Q31) -> 2692126 | X31: CONSÓRCIO TRILHO/FPE - (TRILHO ENGENHARIA LTDA / FÁBIO PERA ARQUITETO LTDA) | Y31: OGU CONTRAPARTIDA COMPLEMENTAR | AA31: 8 | AB31: F03 - EXECUÇÃO DO OBJETO | AC31: 02 - ANDAMENTO | AF31: Emissão do aceite VRPL | AG31: Conder enviar documentação para Caixa para obtenção do VRPL | AI31: *VRPL *AIO *OS *Execução da Obra | AJ31: 005332/2024 42000000044/2023 | AK31: 963493/2024 | AL31: 01 - Retirada Total | AO31: https://governodabahia.plataformatarget.com.br/web/2ecfe66b-89f7-485d-812b-74e5c640bb0e/home | AP31: https://maps.app.goo.gl/YTyCwGwxu7UfZgJK7 | AR31: 46066 | AS31: 46147 | AT31: 46239 | AX31: Ofício CE 46/2026 enviado em 04/02/2026 solicitando nova prorrogação de prazo para abertura de licitação dos CEUS da Cultura Ofício CE 16/2026 enviado em 01/01/2026 comunicando conclusão da alteração de valores de Repasse nos Termos de Compromisso. Ofício CE 4680/2025 enviado em 17/10/2025 comunicando Celebração de Termo Aditivo (Adequação do valor de repasse - R$ 2.066.482,18 e inclusão dos valores para aquisição de equipamentos e mobiliários - R$ 492.646,42). Valor Total: R$ 2.559.128,60. Solicitação de ordenador de despesas 043.4110.2025.0017422-24 enviado para SECULT em 07/10/2025. Terrenos definidos e tecnicamente aprovados/ Projetos em desenvolvimento visando licitação. | AY31: NOTIFICAÇÃO DE RECURSO DA LICITAÇÃO PRESENCIAL Nº 019/26 - SERRA DO RAMALHO, BOM JESUS DA LAPA, MACAÚBAS E SEABRA - CONDER - publicada no DOE em 21/07/2026 Empresas participantes Consórcio TRILHO/FPE ( Trilho engenharia LTDA/ Fábio Pera arquiteto LTDA) e ART projetos construções e serviços LTDA Aviso de Licitação publicado no DOE 13/02/26 - Abertura 05/05/26 À Licitar. Ofício CE 19/2026 enviado em 02/01/2026 prorrogando abertura da Licitação para 28/02/2026. 19/11/25 - Aguardando dotação orçamentária do lote para licitar. SEI: 043.4110.2025.0013222-84. | BA31: OBRA - Projeto Padrão | BB31: =IFERROR(IF(PAC!$AB31="F01 - CAPTAÇÃO DE RECURSO",1,""),"") | BC31: =IFERROR(IF(PAC!$AB31="F02 - LICITAÇÃO",1,""),"") | BD31: =IFERROR(IF(PAC!$AB$6:$AB$581="F03 - EXECUÇÃO DO OBJETO",1,""),"") -> 1 | BE31: =IFERROR(IF(PAC!$AB$6:$AB$581="F04 - CONCLUÍDA",1,""),"") | BF31: =IF(PAC!$V31>0,0,PAC!$Q31) -> 0
A32: =ROW()-5 -> 27 | B32: 2023 | C32: OBRA | D32: PAC SELEÇÕES | E32: Construção do CEU da Cultura | F32: Turismo e Cultura | G32: CEU da Cultura | H32: SECULT | I32: 14 - Gov. Estado - CONDER | J32: Jaguarari | M32: 2066482.2 | O32: 562309.9 | Q32: =SUM(PAC!$M32:$P32) -> 2628792.1 | V32: 2586651.4 | W32: =IF(PAC!$V32>0,PAC!$V32,PAC!$Q32) -> 2586651.4 | X32: ART PROJETOS CONSTRUÇÕES E SERVIÇOS LTDA. | Y32: OGU CONTRAPARTIDA COMPLEMENTAR | AA32: 8 | AB32: F02 - LICITAÇÃO | AC32: 03 - AGUARDANDO ORDEM DE SERVIÇO | AF32: Homologar e Adjudicar Licitação | AI32: *AIO *OS *Execução da Obra | AJ32: 005339/2024 42000000329/2023 | AK32: 963530/2024 | AL32: 01 - Retirada Total | AO32: https://governodabahia.plataformatarget.com.br/web/fe4f6f5a-bdd8-481f-953c-cdd4a2c29890/home | AP32: https://maps.app.goo.gl/LGh54D9sXrk2DnCQ7 | AR32: 46066 | AS32: 46147 | AX32: Ofício CE 46/2026 enviado em 04/02/2026 solicitando nova prorrogação de prazo para abertura de licitação dos CEUS da Cultura. Ofício CE 16/2026 enviado em 01/01/2026 comunicando conclusão da alteração de valores de Repasse nos Termos de Compromisso. Ofício CE 4680/2025 enviado em 17/10/2025 comunicando Celebração de Termo Aditivo (Adequação do valor de repasse - R$ 2.066.482,18 e inclusão dos valores para aquisição de equipamentos e mobiliários - R$ 492.646,42). Valor Total: R$ 2.559.128,60. Solicitação de Ordenador de Despesas 043.4110.2025.0014007-73. Solicitação de Ordenador de Despesas 043.4110.2025.0018290-01 enviado para SECULT em 13/10/2025 duplicado. Aguardando autorização pela Caixa para licitar Aguardando definição de recurso compelementar pela Secult Elaboração de TR e Edital Aguardando autorização pela Caixa para licitar Aguardando definição de recurso compelementar pela Secult Elaboração de TR e Edital | AY32: Empresas participantes - ART Projetos Construções e Serviços LTDA Consórcio F&R Cultura LP 018 - FCK contruções e Incorporações LTDA / ROBLE Serviços LTDA IFC Engenharia LTDA Aviso de Licitação publicado no DOE 13/02/26 - Abertura 05/05/26 À Licitar. Ofício CE 19/2026 enviado em 02/01/2026 prorrogando abertura da Licitação para 28/02/2026. 19/11/25 - Aguardando dotação orçamentária do lote para licitar. SEI:043.4110.2025.0014007-73 | BA32: OBRA - Projeto Padrão | BB32: =IFERROR(IF(PAC!$AB32="F01 - CAPTAÇÃO DE RECURSO",1,""),"") | BC32: =IFERROR(IF(PAC!$AB32="F02 - LICITAÇÃO",1,""),"") -> 1 | BD32: =IFERROR(IF(PAC!$AB$6:$AB$581="F03 - EXECUÇÃO DO OBJETO",1,""),"") | BE32: =IFERROR(IF(PAC!$AB$6:$AB$581="F04 - CONCLUÍDA",1,""),"") | BF32: =IF(PAC!$V32>0,0,PAC!$Q32) -> 0
A33: =ROW()-5 -> 28 | B33: 2023 | C33: OBRA | D33: PAC SELEÇÕES | E33: Construção do CEU da Cultura | F33: Turismo e Cultura | G33: CEU da Cultura | H33: SECULT | I33: 14 - Gov. Estado - CONDER | J33: Pojuca | M33: 2066482.2 | O33: 393920.79 | Q33: =SUM(PAC!$M33:$P33) -> 2460403 | V33: 3206192.6 | W33: =IF(PAC!$V33>0,PAC!$V33,PAC!$Q33) -> 3206192.6 | Y33: OGU CONTRAPARTIDA COMPLEMENTAR | AA33: 8 | AB33: F02 - LICITAÇÃO | AC33: 03 - AGUARDANDO ORDEM DE SERVIÇO | AF33: Abertura das Propostas | AI33: *VRPL *AIO *OS *Execução da Obra | AJ33: 005333/2024 42000000208/2023 | AK33: 963494/2024 | AL33: 01 - Retirada Total | AO33: https://governodabahia.plataformatarget.com.br/web/c29ce066-6778-413f-9e18-23b13b3f1bb0/home | AP33: https://maps.app.goo.gl/is6cTCYAYY9CbnJa7 | AR33: 46066 | AS33: 46148 | AX33: Ofício CE 46/2026 enviado em 04/02/2026 solicitando nova prorrogação de prazo para abertura de licitação dos CEUS da Cultura. Ofício CE 16/2026 enviado em 01/01/2026 comunicando conclusão da alteração de valores de Repasse nos Termos de Compromisso. Ofício CE 4680/2025 enviado em 17/10/2025 comunicando Celebração de Termo Aditivo (Adequação do valor de repasse - R$ 2.066.482,18 e inclusão dos valores para aquisição de equipamentos e mobiliários - R$ 492.646,42). Valor Total: R$ 2.559.128,60. Ce Gigov 2408/2025 solicitação de complementação. Terrenos definidos e tecnicamente aprovados/ Projetos em desenvolvimento visando licitação Atendimento as pendências para retirada da Cláusula suspensiva. Retirada da suspensiva 26/08/25. | AY33: Empresas Participantes -ART Projetos Construções e Serviços LTDA Consórcio F&R Cultura LP 020 - FCK contruções e Incorporações LTDA / ROBLE Serviços LTDA IFC Engenharia LTDA Consórcio Faria Lima - L3 - CEU CULTURA - Contrutora Faria Lima / Leite Engenharia e Consultoria LTDA Aviso de Licitação publicado no DOE 13/02/26 - Abertura 06/05/26 À Licitar. Ofício CE 19/2026 enviado em 02/01/2026 prorrogando abertura da Licitação para 28/02/2026. 19/11/25 - Aguardando dotação orçamentária para licitar. | BA33: OBRA - Projeto Padrão | BB33: =IFERROR(IF(PAC!$AB33="F01 - CAPTAÇÃO DE RECURSO",1,""),"") | BC33: =IFERROR(IF(PAC!$AB33="F02 - LICITAÇÃO",1,""),"") -> 1 | BD33: =IFERROR(IF(PAC!$AB$6:$AB$581="F03 - EXECUÇÃO DO OBJETO",1,""),"") | BE33: =IFERROR(IF(PAC!$AB$6:$AB$581="F04 - CONCLUÍDA",1,""),"") | BF33: =IF(PAC!$V33>0,0,PAC!$Q33) -> 0
A34: =ROW()-5 -> 29 | B34: 2023 | C34: OBRA | D34: PAC SELEÇÕES | E34: Construção do CEU da Cultura | F34: Turismo e Cultura | G34: CEU da Cultura | H34: SECULT | I34: 14 - Gov. Estado - CONDER | J34: Madre de Deus | M34: 2066482.2 | O34: 442576.83 | Q34: =SUM(PAC!$M34:$P34) -> 2509059 | V34: 2729451.9 | W34: =IF(PAC!$V34>0,PAC!$V34,PAC!$Q34) -> 2729451.9 | Y34: OGU CONTRAPARTIDA COMPLEMENTAR | AA34: 8 | AB34: F02 - LICITAÇÃO | AC34: 03 - AGUARDANDO ORDEM DE SERVIÇO | AF34: Homologar e Adjudicar Licitação | AI34: *VRPL *AIO *OS *Execução da Obra | AJ34: 005328/2024 42000000027/2023 | AK34: 963473/2024 | AL34: 01 - Retirada Total | AO34: https://governodabahia.plataformatarget.com.br/web/e76b997d-656e-4853-95a8-1a3e343668b0/home | AP34: https://maps.app.goo.gl/HSokUzJjA81KJSPQ6 | AR34: 46066 | AS34: 46148 | AX34: Ofício CE 46/2026 enviado em 04/02/2026 solicitando nova prorrogação de prazo para abertura de licitação dos CEUS da Cultura. Ofício CE 16/2026 enviado em 01/01/2026 comunicando conclusão da alteração de valores de Repasse nos Termos de Compromisso. Ofício CE 4680/2025 enviado em 17/10/2025 comunicando Celebração de Termo Aditivo (Adequação do valor de repasse - R$ 2.066.482,18 e inclusão dos valores para aquisição de equipamentos e mobiliários - R$ 492.646,42). Valor Total: R$ 2.559.128,60. Terrenos definidos e tecnicamente aprovados/ Projetos aprovados possíveis de licitação. | AY34: Empresas Participantes -ART Projetos Construções e Serviços LTDA Consórcio F&R Cultura LP 020 - FCK contruções e Incorporações LTDA / ROBLE Serviços LTDA IFC Engenharia LTDA Consórcio Faria Lima - L3 - CEU CULTURA - Contrutora Faria Lima / Leite Engenharia e Consultoria LTDA Aviso de Licitação publicado no DOE 13/02/26 - Abertura 06/05/26 À Licitar. Ofício CE 19/2026 enviado em 02/01/2026 prorrogando abertura da Licitação para 28/02/2026. 19/11/25 - Aguardando dotação orçamentária do lote para licitar. SEI:043.4110.2025.0013212-11. | BA34: OBRA - Projeto Padrão | BB34: =IFERROR(IF(PAC!$AB34="F01 - CAPTAÇÃO DE RECURSO",1,""),"") | BC34: =IFERROR(IF(PAC!$AB34="F02 - LICITAÇÃO",1,""),"") -> 1 | BD34: =IFERROR(IF(PAC!$AB$6:$AB$581="F03 - EXECUÇÃO DO OBJETO",1,""),"") | BE34: =IFERROR(IF(PAC!$AB$6:$AB$581="F04 - CONCLUÍDA",1,""),"") | BF34: =IF(PAC!$V34>0,0,PAC!$Q34) -> 0
A35: =ROW()-5 -> 30 | B35: 2023 | C35: OBRA | D35: PAC SELEÇÕES | E35: Construção do CEU da Cultura | F35: Turismo e Cultura | G35: CEU da Cultura | H35: SECULT | I35: 14 - Gov. Estado - CONDER | J35: Serra do Ramalho | M35: 2066482.2 | O35: 287101.96 | Q35: =SUM(PAC!$M35:$P35) -> 2353584.1 | V35: 2533097.4 | W35: =IF(PAC!$V35>0,PAC!$V35,PAC!$Q35) -> 2533097.4 | X35: CONSÓRCIO TRILHO/FPE - (TRILHO ENGENHARIA LTDA / FÁBIO PERA ARQUITETO LTDA) | Y35: OGU CONTRAPARTIDA COMPLEMENTAR | AA35: 8 | AB35: F03 - EXECUÇÃO DO OBJETO | AC35: 02 - ANDAMENTO | AF35: Emissão do aceite VRPL | AG35: Conder enviar documentação para Caixa para obtenção do VRPL | AI35: *VRPL *AIO *OS *Execução da Obra | AJ35: 005340/2024 42000000333/2023 | AK35: 963531/2024 | AL35: 01 - Retirada Total | AO35: https://governodabahia.plataformatarget.com.br/web/9c4e5296-0482-45d9-a890-6c6b64bfe9ab/home | AP35: https://maps.app.goo.gl/xJtkr4nZ9cMFaS288 | AR35: 46066 | AS35: 46147 | AT35: 46239 | AX35: 07/10/26 - SERVIÇOS CONCLUÍDOS: Instalação de placa de obra. SERVIÇO À INICIAR: Instalação de Tapume metálico (PREVISÃO: 19/10/2026); Serviços Preliminares; Terraplenagem ; Elaboração de Projetos; Fundações; Superestrutura; Cobertura; Paredes e painéis; Esquadrias; Sistemas hidráulicos, Sanitários e de combate a incêndio(HSI); Sistema elétrico e sistema de voz e dados; Sistemas de ar condicionado, ventilação e exaustão; Revestimentos primários; Acabamentos (revestimento para teto, parede e piso); Acabamentos (hidrossanitários); Acabamentos (elétricos, voz, dados e tv); Pintura; Urbanização e paisagismo; Desmobilização de canteiro e Limpeza final. Obs.: A empresa está em processo de elaboração dos projetos executivos, previsão para iniciar a obra após a aprovação. Ofício CE 46/2026 enviado em 04/02/2026 solicitando nova prorrogação de prazo para abertura de licitação dos CEUS da Cultura. Ofício CE 16/2026 enviado em 01/01/2026 comunicando conclusão da alteração de valores de Repasse nos Termos de Compromisso. Ofício CE 4680/2025 enviado em 17/10/2025 comunicando Celebração de Termo Aditivo (Adequação do valor de repasse - R$ 2.066.482,18 e inclusão dos valores para aquisição de equipamentos e mobiliários - R$ 492.646,42). Valor Total: R$ 2.559.128,60. Solicitação de ordenador de despesas 043.4110.2025.0017422-24 enviado para SECULT em 07/10/2025. Terrenos definidos e tecnicamente aprovados/ Projetos aprovados possíveis de licitação. | AY35: NOTIFICAÇÃO DE RECURSO DA LICITAÇÃO PRESENCIAL Nº 019/26 - SERRA DO RAMALHO, BOM JESUS DA LAPA, MACAÚBAS E SEABRA - CONDER - publicada no DOE em 21/07/2026 Empresas participantes Consórcio TRILHO/FPE ( Trilho engenharia LTDA/ Fábio Pera arquiteto LTDA) e ART projetos construções e serviços LTDA Aviso de Licitação publicado no DOE 13/02/26 - Abertura 05/05/26 À Licitar. Ofício CE 19/2026 enviado em 02/01/2026 prorrogando abertura da Licitação para 28/02/2026. 19/11/25 - Aguardando dotação orçamentária do lote para licitar. SEI:043.4110.2025.0013225-27. | BA35: OBRA - Projeto Padrão | BB35: =IFERROR(IF(PAC!$AB35="F01 - CAPTAÇÃO DE RECURSO",1,""),"") | BC35: =IFERROR(IF(PAC!$AB35="F02 - LICITAÇÃO",1,""),"") | BD35: =IFERROR(IF(PAC!$AB$6:$AB$581="F03 - EXECUÇÃO DO OBJETO",1,""),"") -> 1 | BE35: =IFERROR(IF(PAC!$AB$6:$AB$581="F04 - CONCLUÍDA",1,""),"") | BF35: =IF(PAC!$V35>0,0,PAC!$Q35) -> 0
A36: =ROW()-5 -> 31 | B36: 2023 | C36: OBRA | D36: PAC SELEÇÕES | E36: Construção do CEU da Cultura | F36: Turismo e Cultura | G36: CEU da Cultura | H36: SECULT | I36: 14 - Gov. Estado - CONDER | J36: São Desidério | M36: 2066482.2 | O36: 604349.88 | Q36: =SUM(PAC!$M36:$P36) -> 2670832.1 | V36: 2480183.1 | W36: =IF(PAC!$V36>0,PAC!$V36,PAC!$Q36) -> 2480183.1 | X36: ART Projetos Construções e Serviços LTDA | Y36: OGU CONTRAPARTIDA COMPLEMENTAR | AA36: 8 | AB36: F02 - LICITAÇÃO | AC36: 02 - ANDAMENTO | AF36: Enviar documentos para obtenção do VRPL | AG36: Conder enviar documentação para Caixa para obtenção do VRPL | AI36: *VRPL *AIO *OS *Execução da Obra | AJ36: 005345/2024 42000000346/2023 | AK36: 963565/2024 | AL36: 01 - Retirada Total | AO36: https://governodabahia.plataformatarget.com.br/web/1af130b7-7731-441a-b0e6-f57a9be4d9be/home | AP36: https://maps.app.goo.gl/8jEgQFPwCvkqnedUA | AR36: 46066 | AS36: 46148 | AT36: 46185 | AU36: 46198 | AV36: 46563 | AX36: Percentual Físico: 5,36% Homologação publicada no DOE dia 12/06/2026 Ofício CE 46/2026 enviado em 04/02/2026 solicitando nova prorrogação de prazo para abertura de licitação dos CEUS da Cultura. Ofício CE 16/2026 enviado em 01/01/2026 comunicando conclusão da alteração de valores de Repasse nos Termos de Compromisso. Ofício CE 4680/2025 enviado em 17/10/2025 comunicando Celebração de Termo Aditivo (Adequação do valor de repasse - R$ 2.066.482,18 e inclusão dos valores para aquisição de equipamentos e mobiliários - R$ 492.646,42). Valor Total: R$ 2.559.128,60. Terrenos definidos e tecnicamente aprovados/ Projetos em desenvolvimento visando licitação. | AY36: Empresa Vencedora - ART Projetos Construções e Serviços LTDA Aviso de Licitação publicado no DOE 13/02/26 - Abertura 06/05/26 À Licitar. Ofício CE 19/2026 enviado em 02/01/2026 prorrogando abertura da Licitação para 28/02/2026. 19/11/25 - Aguardando dotação orçamentária para licitar. | BA36: OBRA - Projeto Padrão | BB36: =IFERROR(IF(PAC!$AB36="F01 - CAPTAÇÃO DE RECURSO",1,""),"") | BC36: =IFERROR(IF(PAC!$AB36="F02 - LICITAÇÃO",1,""),"") -> 1 | BD36: =IFERROR(IF(PAC!$AB$6:$AB$581="F03 - EXECUÇÃO DO OBJETO",1,""),"") | BE36: =IFERROR(IF(PAC!$AB$6:$AB$581="F04 - CONCLUÍDA",1,""),"") | BF36: =IF(PAC!$V36>0,0,PAC!$Q36) -> 0
A37: =ROW()-5 -> 32 | B37: 2023 | C37: OBRA | D37: PAC SELEÇÕES | E37: Construção do CEU da Cultura | F37: Turismo e Cultura | G37: CEU da Cultura | H37: SECULT | I37: 14 - Gov. Estado - CONDER | J37: Jequié | M37: 2066482.2 | O37: 436764 | Q37: =SUM(PAC!$M37:$P37) -> 2503246.2 | V37: 2391335.2 | W37: =IF(PAC!$V37>0,PAC!$V37,PAC!$Q37) -> 2391335.2 | X37: INO9VARE ENGENHARIA LTDA | Y37: OGU CONTRAPARTIDA COMPLEMENTAR | AA37: 8 | AB37: F02 - LICITAÇÃO | AC37: 02 - ANDAMENTO | AF37: Execução da Obra | AG37: PARALISAÇÃO DOS SERVIÇOS DO CONTRATO Nº 071/2026 NO DIA 09/09/26 POR PRAZO INDETERMINADO. | AI37: *VRPL *AIO *OS *Execução da Obra | AJ37: 005346/2024 42000000366/2023 | AK37: 963566/2024 | AL37: 01 - Retirada Total | AO37: https://governodabahia.plataformatarget.com.br/web/2d78a10d-10f4-4c98-a631-cefde5b9fd01/home | AP37: https://maps.app.goo.gl/JaskRbHVYxWxcEET7 | AR37: 46066 | AS37: 46146 | AT37: 46188 | AU37: 46191 | AV37: 46563 | AX37: Homoloção publicado no DOE 15/06/2026 Ofício CE 46/2026 enviado em 04/02/2026 solicitando nova prorrogação de prazo para abertura de licitação dos CEUS da Cultura. Ofício CE 16/2026 enviado em 01/01/2026 comunicando conclusão da alteração de valores de Repasse nos Termos de Compromisso. Ofício CE 4680/2025 enviado em 17/10/2025 comunicando Celebração de Termo Aditivo (Adequação do valor de repasse - R$ 2.066.482,18 e inclusão dos valores para aquisição de equipamentos e mobiliários - R$ 492.646,42). Valor Total: R$ 2.559.128,60. Terreno indicado apresenta solo do tipo rochoso – valor estimado da implantação R$4.725.157,39. Terreno indicado e tecnicamente com pendências / Projetos em desenvolvimento. | AY37: Empresa vencedora- INO9VARE Enganharia LTDA Aviso de Licitação publicado no DOE 13/02/26 - Abertura: 04/05/2026 À Licitar. Ofício CE 19/2026 enviado em 02/01/2026 prorrogando abertura da Licitação para 28/02/2026. 19/11/25 - Aguardando dotação orçamentária para licitar. SEI: 043.4110.2025.0020786-46 | BA37: OBRA - Projeto Padrão | BB37: =IFERROR(IF(PAC!$AB37="F01 - CAPTAÇÃO DE RECURSO",1,""),"") | BC37: =IFERROR(IF(PAC!$AB37="F02 - LICITAÇÃO",1,""),"") -> 1 | BD37: =IFERROR(IF(PAC!$AB$6:$AB$581="F03 - EXECUÇÃO DO OBJETO",1,""),"") | BE37: =IFERROR(IF(PAC!$AB$6:$AB$581="F04 - CONCLUÍDA",1,""),"") | BF37: =IF(PAC!$V37>0,0,PAC!$Q37) -> 0
A38: =ROW()-5 -> 33 | B38: 2023 | C38: OBRA | D38: PAC SELEÇÕES | E38: Construção do CEU da Cultura | F38: Turismo e Cultura | G38: CEU da Cultura | H38: SECULT | I38: 14 - Gov. Estado - CONDER | J38: Teixeira de Freitas | M38: 2066482.2 | O38: 523724.77 | Q38: =SUM(PAC!$M38:$P38) -> 2590207 | V38: 2696324 | W38: =IF(PAC!$V38>0,PAC!$V38,PAC!$Q38) -> 2696324 | X38: INO9VARE ENGENHARIA LTDA | Y38: OGU CONTRAPARTIDA COMPLEMENTAR | AA38: 8 | AB38: F02 - LICITAÇÃO | AC38: 02 - ANDAMENTO | AF38: Execução da Obra | AG38: PARALISAÇÃO DOS SERVIÇOS DO CONTRATO Nº 071/2026 NO DIA 09/09/26 POR PRAZO INDETERMINADO. | AI38: *VRPL *AIO *OS *Execução da Obra | AJ38: 005330/2024 42000000032/2023 | AK38: 963477/2024 | AL38: 01 - Retirada Total | AO38: https://governodabahia.plataformatarget.com.br/web/8fa7b8ed-4b2d-443d-9f93-d23046529deb/home | AP38: https://maps.app.goo.gl/b2ntTaR9Q2o61pWN8 | AR38: 46066 | AS38: 46146 | AT38: 46188 | AU38: 46191 | AV38: 46563 | AX38: Homoloção publicado no DOE 15/06/2026 Ofício CE 46/2026 enviado em 04/02/2026 solicitando nova prorrogação de prazo para abertura de licitação dos CEUS da Cultura Ofício CE 16/2026 enviado em 01/01/2026 comunicando conclusão da alteração de valores de Repasse nos Termos de Compromisso. Ofício CE 4680/2025 enviado em 17/10/2025 comunicando Celebração de Termo Aditivo (Adequação do valor de repasse - R$ 2.066.482,18 e inclusão dos valores para aquisição de equipamentos e mobiliários - R$ 492.646,42). Valor Total: R$ 2.559.128,60. A Conder elaborou um estudo preliminar, já ecaminhado e em posse do município, que atualmente se encontra em fase de planejamento, compatinilização e adequação dos elementos arquitetónicos passíveis de tal demandas e realidades locais. O terreno se localiza próximo de uma creche, posto de saúde e da futura rodoviária da cidade. Terreno possui matrícula e escritura. Terrenos definidos e tecnicamente aprovados/ Projetos em desenvolvimento visando licitação. | AY38: Empresa Vencedora - INO9VARE Enganharia LTDA Aviso de Licitação publicado no DOE 13/02/26 - Abertura: 04/05/2026 À Licitar. Ofício CE 19/2026 enviado em 02/01/2026 prorrogando abertura da Licitação para 28/02/2026. 19/11/25 - Aguardando dotação orçamentária para licitar. SEI: 043.4110.2025.0020786-46 | BA38: OBRA - Projeto Padrão | BB38: =IFERROR(IF(PAC!$AB38="F01 - CAPTAÇÃO DE RECURSO",1,""),"") | BC38: =IFERROR(IF(PAC!$AB38="F02 - LICITAÇÃO",1,""),"") -> 1 | BD38: =IFERROR(IF(PAC!$AB$6:$AB$581="F03 - EXECUÇÃO DO OBJETO",1,""),"") | BE38: =IFERROR(IF(PAC!$AB$6:$AB$581="F04 - CONCLUÍDA",1,""),"") | BF38: =IF(PAC!$V38>0,0,PAC!$Q38) -> 0
A39: =ROW()-5 -> 34 | B39: 2023 | C39: OBRA | D39: PAC SELEÇÕES | E39: Construção do CEU da Cultura | F39: Turismo e Cultura | G39: CEU da Cultura | H39: SECULT | I39: 14 - Gov. Estado - CONDER | J39: Vera Cruz | M39: 2559128.6 | Q39: =SUM(PAC!$M39:$P39) -> 2559128.6 | W39: =IF(PAC!$V39>0,PAC!$V39,PAC!$Q39) -> 2559128.6 | Y39: OGU CONTRAPARTIDA COMPLEMENTAR | AA39: 8 | AB39: F01 - CAPTAÇÃO DE RECURSO | AC39: 05 - À LICITAR | AF39: Enviar documentos para atendimento à Cláusula Suspensiva | AG39: Secult atender as diligências da Clasula Suspensiva para Caixa | AI39: *Elaboração de TR e Edital *Publicação da Licitação *VRPL *AIO *OS *Execução da Obra | AJ39: 058030/2025 42000000075/2024 | AK39: 993775 | AL39: 03 - Cláusula Vigente | AM39: Titularidade de área, Projeto básico,Licença Ambiental Prévia e Plano de Sustentabilidade | AN39: 46380 | BB39: =IFERROR(IF(PAC!$AB39="F01 - CAPTAÇÃO DE RECURSO",1,""),"") -> 1 | BC39: =IFERROR(IF(PAC!$AB39="F02 - LICITAÇÃO",1,""),"") | BD39: =IFERROR(IF(PAC!$AB$6:$AB$581="F03 - EXECUÇÃO DO OBJETO",1,""),"") | BE39: =IFERROR(IF(PAC!$AB$6:$AB$581="F04 - CONCLUÍDA",1,""),"") | BF39: =IF(PAC!$V39>0,0,PAC!$Q39) -> 2559128.6
A40: =ROW()-5 -> 35 | B40: 2023 | C40: OBRA | D40: PAC SELEÇÕES | E40: Construção do CEU da Cultura | F40: Turismo e Cultura | G40: CEU da Cultura | H40: SECULT | I40: 14 - Gov. Estado - CONDER | J40: Paratinga | M40: 2559128.6 | Q40: =SUM(PAC!$M40:$P40) -> 2559128.6 | W40: =IF(PAC!$V40>0,PAC!$V40,PAC!$Q40) -> 2559128.6 | Y40: OGU CONTRAPARTIDA COMPLEMENTAR | AA40: 8 | AB40: F01 - CAPTAÇÃO DE RECURSO | AC40: 05 - À LICITAR | AF40: Enviar documentos para atendimento à Cláusula Suspensiva | AG40: Secult atender as diligências da Clasula Suspensiva para Caixa | AI40: *Elaboração de TR e Edital *Publicação da Licitação *VRPL *AIO *OS *Execução da Obra | AJ40: 58032/2025 42000000345/2023 | AK40: 993772 | AL40: 03 - Cláusula Vigente | AM40: Titularidade de área, Projeto básico,Licença Ambiental Prévia e Plano de Sustentabilidade | AN40: 46380 | BB40: =IFERROR(IF(PAC!$AB40="F01 - CAPTAÇÃO DE RECURSO",1,""),"") -> 1 | BC40: =IFERROR(IF(PAC!$AB40="F02 - LICITAÇÃO",1,""),"") | BD40: =IFERROR(IF(PAC!$AB$6:$AB$581="F03 - EXECUÇÃO DO OBJETO",1,""),"") | BE40: =IFERROR(IF(PAC!$AB$6:$AB$581="F04 - CONCLUÍDA",1,""),"") | BF40: =IF(PAC!$V40>0,0,PAC!$Q40) -> 2559128.6
A41: =ROW()-5 -> 36 | B41: 2023 | C41: OBRA | D41: PAC SELEÇÕES | E41: Construção do CEU da Cultura | F41: Turismo e Cultura | G41: CEU da Cultura | H41: SECULT | I41: 14 - Gov. Estado - CONDER | J41: Luís Eduardo Magalhães | M41: 2066482.2 | O41: 314302.13 | Q41: =SUM(PAC!$M41:$P41) -> 2380784.3 | V41: 2316592.2 | W41: =IF(PAC!$V41>0,PAC!$V41,PAC!$Q41) -> 2316592.2 | X41: ART Projetos Construções e Serviços LTDA | Y41: OGU CONTRAPARTIDA COMPLEMENTAR | AA41: 8 | AB41: F02 - LICITAÇÃO | AC41: 02 - ANDAMENTO | AF41: Enviar documentos para obtenção do VRPL | AG41: Conder enviar documentação para Caixa para obtenção do VRPL | AI41: *VRPL *AIO *OS *Execução da Obra | AJ41: 005335/2024 42000000251/2023 | AK41: 963497/2024 | AL41: 01 - Retirada Total | AO41: https://governodabahia.plataformatarget.com.br/web/0a735f32-80e9-49b3-b7d2-32347ce24a55/home | AP41: https://maps.app.goo.gl/QWeULVaLQfYN6dEE9 | AR41: 46066 | AS41: 46148 | AT41: 46185 | AU41: 46198 | AV41: 46563 | AX41: Percentual Físico: 5,36% Homologação publicada no DOE dia 12/06/2026 Ofício CE 46/2026 enviado em 04/02/2026 solicitando nova prorrogação de prazo para abertura de licitação dos CEUS da Cultura. Ofício CE 16/2026 enviado em 01/01/2026 comunicando conclusão da alteração de valores de Repasse nos Termos de Compromisso. Ofício CE 4680/2025 enviado em 17/10/2025 comunicando Celebração de Termo Aditivo (Adequação do valor de repasse - R$ 2.066.482,18 e inclusão dos valores para aquisição de equipamentos e mobiliários - R$ 492.646,42). Valor Total: R$ 2.559.128,60. Terrenos definidos e tecnicamente aprovados/ Projetos em desenvolvimento visando licitação. | AY41: Empresa Vencedora - ART Projetos Construções e Serviços LTDA Aviso de Licitação publicado no DOE 13/02/26 - Abertura 06/05/26 À Licitar. Ofício CE 19/2026 enviado em 02/01/2026 prorrogando abertura da Licitação para 28/02/2026. 19/11/25 - Aguardando dotação orçamentária para licitar. | BA41: OBRA - Projeto Padrão | BB41: =IFERROR(IF(PAC!$AB41="F01 - CAPTAÇÃO DE RECURSO",1,""),"") | BC41: =IFERROR(IF(PAC!$AB41="F02 - LICITAÇÃO",1,""),"") -> 1 | BD41: =IFERROR(IF(PAC!$AB$6:$AB$581="F03 - EXECUÇÃO DO OBJETO",1,""),"") | BE41: =IFERROR(IF(PAC!$AB$6:$AB$581="F04 - CONCLUÍDA",1,""),"") | BF41: =IF(PAC!$V41>0,0,PAC!$Q41) -> 0
A42: =ROW()-5 -> 37 | B42: 2023 | C42: OBRA | D42: PAC SELEÇÕES | E42: Construção do CEU da Cultura | F42: Turismo e Cultura | G42: CEU da Cultura | H42: SECULT | I42: 14 - Gov. Estado - CONDER | J42: Salvador | M42: 1912158.3 | O42: 1807956.1 | Q42: =SUM(PAC!$M42:$P42) -> 3720114.5 | V42: 3875772.8 | W42: =IF(PAC!$V42>0,PAC!$V42,PAC!$Q42) -> 3875772.8 | X42: Consórcio Faria Lima - L3 - CEU (Construtora Fria Lima/ Leite Engenharia e Consultoria Ltda) | Y42: OGU CONTRAPARTIDA COMPLEMENTAR | AA42: 8 | AB42: F03 - EXECUÇÃO DO OBJETO | AC42: 02 - ANDAMENTO | AD42: 46455 | AE42: 10.14 | AF42: Execução da Obra | AG42: Acompanhar os serviços e emissão de Alvará | AJ42: 005347/2024 42000000396/2023 | AK42: 963636/2024 | AL42: 01 - Retirada Total | AO42: https://governodabahia.plataformatarget.com.br/web/86a5325a-a633-427d-aca1-7e08a89240da/home | AP42: https://maps.app.goo.gl/HsCrMu5sZBLZKUZw8 | AR42: 45903 | AS42: 45971 | AT42: 45995 | AU42: 46029 | AV42: 46455 | AW42: 46455 | AX42: Serviços preliminares de limpeza do terreno iniciados em 28/04/2026. Em andamento fechamento da obra com tapume (75% executado). Ofício CE 16/2026 enviado em 01/01/2026 comunicando conclusão da alteração de valores de Repasse nos Termos de Compromisso. Ofício CE 4680/2025 enviado em 17/10/2025 comunicando Celebração de Termo Aditivo (Adequação do valor de repasse - R$ 2.066.482,18 e inclusão dos valores para aquisição de equipamentos e mobiliários - R$ 492.646,42). Valor Total: R$ 2.559.128,60. Publicado contrato no DOE em 05/12/2025. Homologação publicado no DOE em 02/12/2025. Aviso de Licitação Semi-Integrada publicado no DOE em 03/09/2025 (LP - 057/25). Edital disponível em 05/09/2025. Abertura de Propostas realizada em: 10/11/2025. Única Licitante participando: Consórcio Faria Lima - L3 - CEU (Construtora Fria Lima/ Leite Engenharia e Consultoria Ltda). Ofício CE nº 2281/2025 - GIGOV/AS emitido em 11/06/2025 com Aceite de projeto, retirada da Cláusula Suspensiva e autorização para o Processo Licitatório. Terrenos definidos e tecnicamente aprovados/ Projetos aprovados possíveis de licitação. | AY42: AIO emitida de forma indireta, a partir da conclusão de um instrumento contratual pelo usuário em 22/05/26 VRPL emitido 20/05/26. OS emitida em 07/01/2026 e início da execução em 09/01/2026 (Projetos). Empresa Contratada: Consórcio Faria Lima - L3 - CEU (Construtora Fria Lima/ Leite Engenharia e Consultoria Ltda). | BA42: OBRA - Projeto Padrão | BB42: =IFERROR(IF(PAC!$AB42="F01 - CAPTAÇÃO DE RECURSO",1,""),"") | BC42: =IFERROR(IF(PAC!$AB42="F02 - LICITAÇÃO",1,""),"") | BD42: =IFERROR(IF(PAC!$AB$6:$AB$581="F03 - EXECUÇÃO DO OBJETO",1,""),"") -> 1 | BE42: =IFERROR(IF(PAC!$AB$6:$AB$581="F04 - CONCLUÍDA",1,""),"") | BF42: =IF(PAC!$V42>0,0,PAC!$Q42) -> 0
A43: =ROW()-5 -> 38 | B43: 2023 | C43: OBRA | D43: PAC SELEÇÕES | E43: Construção e implantação de Centro Comunitário pela Vida – CONVIVE, no município de Juazeiro, Estado da Bahia. | F43: Turismo e Cultura | G43: Convive | H43: SEADES | I43: 14 - Gov. Estado - CONDER | J43: Juazeiro | M43: 11440559 | N43: 139742.41 | O43: 1915931 | Q43: =SUM(PAC!$M43:$P43) -> 13496232 | R43: 10947985 | S43: 139742.41 | T43: 1412523.9 | V43: 12500251 | W43: =IF(PAC!$V43>0,PAC!$V43,PAC!$Q43) -> 12500251 | X43: CONSÓRCIO CONVIVE JUAZEIRO - FCK / SC ARQUITETURA | Y43: OGU CONTRAPARTIDA COMPLEMENTAR | AA43: 12 | AB43: F03 - EXECUÇÃO DO OBJETO | AC43: 02 - ANDAMENTO | AD43: 46429 | AE43: 57 | AF43: Execução da Obra | AG43: - Polo 13/10/26: Serviços em execução: - Elaboração / revisão dos projetos executivos; - Subestação – Instalação de transformador; - Auditório – Execução de mestras (piso); - Vestiário – Reboco interno; - Implantação muros e fechamento - Fundação e alvenaria (muro da poligonal), chapisco e reboco; - Ensino – Limpeza de obra; - Quadra poliesportiva – Telhamento; - Assistência – Polimento do piso de alta resistência e estucagem (módulo 3), concretagem de piso de alta resistência (granilite), levante de alvenaria (módulo2), infra de elétrica; - Piscina – Instalação de skimmers. (11/11/26) | AH43: 46429 | AI43: - Conclusão do projeto executivo - Execução da obra. | AJ43: 026498/2024 (30000000080/2024) | AK43: 970115/2024 | AL43: 01 - Retirada Total | AO43: https://governodabahia.plataformatarget.com.br/web/069363b5-ba10-415c-8da0-fe4b53815bff/home | AP43: https://maps.app.goo.gl/gce3549Hm2G82exy5 | AR43: 45822 | AS43: 45897 | AT43: 45953 | AU43: 45972 | AV43: 46337 | AW43: 46429 | AX43: DOE 24/10/25 - Contrato Publicado 17/10/25 - Contrato Nº 095/2025 assinado em 23/10/25. DOE 16/10/25 - Homologação, vencedora FCK / SC ARQUITETURA. Valor Global: R$12.360.508,59 DOE 15/10/25 - Publicação do julgamento 13/10/25 - Aditivo de valor (placa fotovoltaica) publicado. 24/09/25 - CE GIGOV/SA 4153/2025 - Incorporação de Nota de Empenho no valor de R$ 3.500.000,00. DOE 27/09/25 - FARIA LIMA / GLOBO, FCK / SC, PEJOTA / FÁBIO PERA e ART / JCA, interpuseram recursos contra a decisão da Comissão. 18/09/25 - 2ª Ata de reunião: 1ª Classificada Consórcio CONVIVE Juazeiro (FCK/SC Arquitetura), nota final: 9,58 Valor Global: R$ 12.360.508,59 2ª Classificada Consórcio Centro Comunitário pela Vida (Pejota / Fábio Pera Arquiteto LTDA), nota final: 9,25. Valor Global: R$ 11.554.829,39 3ª Classificada Consórcio Faria Lima - Globo - CCV, nota final: 9,17. Valor Global: R$ 12.308.405,22 DOU 24/06/25 - Oficializa inclusão da CONDER ente executor. 10/06/25 - SEADES encaminha Ofício nº 555/2025, à CONDER para assinatura do termo de oficialização do executor. 10/06/25 - CAIXA encaminha termo para oficialização do ente executor para assinatura. 04/06/25 - Conforme SEADES, a CAIXA aprovou a documentação para oficialização da CONDER como executor. Prazo dado pela CAIXA para abertura da conta: 13/06/25. 28/05/25 - Conforme SEADES, expectativa de publicação da licitação: 30/06/25. 20/05/25 - Ofício encaminhado à CAIXA, informando o número da conta. 06/05/25 - Documentação assinada pelo Governador e encaminhada à ALBA, através do ofício 0014/2025/GG, para apresentação do novo equipamento, visando informar que o Estado assumiu formalmente o compromisso de garantir a execução do objeto pactuado. 15/05/25 - SEADES encaminha solicitação do ente executor (CONDER) à CAIXA. - 15/05/25 - Conforme SEADES, Acordo de Cooperação ainda pendente. Documento relevante no âmbito Estadual. - 28/04/25 - CAIXA (comunicado 36/2024) autoriza o processo licitatório. Encaminha termo de aditivo de supressão no valor de R$ 5.056.333,81. - 24/04/25 - SEADES encaminha Ofício nº 282/2025 à CASA CIVIL - "Solicitação de comunicação à Assembleia Legislativa da Bahia." Aguardando encaminhamento da COAPL para o GABGOV. - 24/04/25 - CAIXA informa a retirada da Cláusula Suspensiva. - 17/04/25 - Em atendimento à Cláusula Suspensiva, a SEADES encaminha o material solicitado à CAIXA. - 22/04/25 - Conforme SEADES, sinalizado pela CONDER uma complementação máxima no valor de R$ 785.000,00 (5% do valor apoiado). Ainda em análise. - 09/04/25 - Terreno vistoriado pela CAIXA. - 08/04/25 - A CAIXA sinaliza pendências na relação de documentos, cláusula suspensiva, vigência 31/05/25. - 01/04/25 - Projeto básico analisado pela Conder sem necessidade de adequações (piscina será construída, conforme proposta apresentada pelo Ministério). Planilha orçamentária inserida no TransfereGov, em 01/04/25, já em análise pela Caixa. Vistoria técnica da Caixa ao terreno prevista para 09/04/25. - DOU 24/12/24 - Informa que o TC não terá contrapartida. - 20/01/25 - Declaração de anuência concedida e encaminhada à SEADES. - 10/01/25 - SEADES encaminha o ofício nº 018/2025, à CONDER, solicitando declaração de anuência para cadastro no TransfereGov. - DOU 24/12/24 - Contrato publicado, vigência 28/04/28. - 20/12/24 - TC assinado e protocolado na CAIXA; - 17/12/24 - Ofício nº 3646/2024/GIGOV/SA encaminhado pela CAIXA com a Minuta do TC 970115/2024, em anexo para assinatura do Governador/SEADES; - 13/12/24 - Projeto básico encaminhado à SEADES/CONDER (DINEP); - 04/12/24 - Conforme parecer técnico no TGov, o MJ aprovou a proposta elaborada pela SEADES; - 15/10/24 - Conforme SEADES/CONDER, em resposta à CAIXA, os projetos serão apresentados em 17/02/25, com possibilidade de antecipar o prazo; - 01/10/24 - SEADES confirma CONDER como ente executor da obra incluindo cadastro do CNPJ no TransfereGOV. Pendentes aprovação da proposta apresentada e entrega do projeto padrão/orçamento de referência pelo MJ; - Conforme SEADES, formalização da proposta concluída e encaminhada no dia 06/09/24. Nova proposta cadastrada pela SEADES nº 026498/2024 no TransfereGov; - Conforme Plano de Trabalho início previsto 20/12/24 e término previsto 28/04/28. | AY43: 16/09/25 - Em reunião com a Madatária e a Casa Civil/PR ficou definido que o Governo do Estado deverá formalizar, através de Ofício ao MJ, pleito de recurso para contratação de equipamento fotovoltaico, visando substituir o uso de recurso próprio. Em relatos feitos pela SEADES e a CONDER, o MJ incluiu a fotovoltaica (não prevista no projeto inicial do Convive) após a publicação do aviso de licitação, e em tratativa conjunta mantiveram a licitação com a possibilidade de fazer um aditivo complementando o serviço, porém com uso de recursos próprios inicialmente para posteriomente pleitear os recursos do MJ destinados ao equipamento. Essa formalização deverá ser encaminhada ao MJ até 19/09/25 com justificativa consistente para substituição do recurso. 16/09/25 - Em reunião com a Mandatária e a Casa Civil/PR, ficou alinhado a emissão do VRPL para o dia 22/10/25. 16/09/25 - Conforme RT da Comissão de licitação. O Consórcio ART Projeto/JCA Engenharia foi desclassificado. Nova reunião marcada para o dia 18/09/25. 28/08/25 - Propostas técnicas apresentadas. Licitantes: - Consórcio (Construtora Faria Lima LTDA / Globo Engenharia LTDA) - Consórcio (FCK Construações e Incorporações LTDA / SC Arquitetura e Consultoria LTDA) - Consórcio (Pejota Construções LTDA / Fábio Pera Arquiteto LTDA) - Consórcio (ART Projetos Construções LTDA / JCA Engenharia e Arquitetura DOU 16/06/25 e DOE 14/06/25 - Aviso de licitação publicado, abertura prevista 28/08/25. | BA43: OBRA - Projeto Padrão | BB43: =IFERROR(IF(PAC!$AB43="F01 - CAPTAÇÃO DE RECURSO",1,""),"") | BC43: =IFERROR(IF(PAC!$AB43="F02 - LICITAÇÃO",1,""),"") | BD43: =IFERROR(IF(PAC!$AB$6:$AB$581="F03 - EXECUÇÃO DO OBJETO",1,""),"") -> 1 | BE43: =IFERROR(IF(PAC!$AB$6:$AB$581="F04 - CONCLUÍDA",1,""),"") | BF43: =IF(PAC!$V43>0,0,PAC!$Q43) -> 0
A44: =ROW()-5 -> 39 | B44: 2023 | C44: OBRA | D44: PAC SELEÇÕES | E44: OBRAS DE MACRODRENAGEM NO CÓRREGO PREGO NO BAIRRO DE DOM AVELAR, NA CIDADE DE SALVADOR - BAHIA - Sistema de canais de macrodrenagem na região dos bairros de Pirajá, Castelo Branco, Vila Canaria, Dom Avelar, Águas Claras, Av. 29 de Março e proximidades da Nova Rodoviária de Salvador para contenção de enchentes. | F44: Prevenção a Desastres Naturais | G44: Drenagem Urbana | H44: SEDUR | I44: 14 - Gov. Estado - CONDER | J44: Salvador | L44: 29598227 | M44: 29598227 | Q44: =SUM(PAC!$M44:$P44) -> 29598227 | V44: 42741860 | W44: =IF(PAC!$V44>0,PAC!$V44,PAC!$Q44) -> 42741860 | X44: CONSÓRCIO DOM AVELAR , PEJOTA CONSTRUÇÕES LTDA. IDEAL CONSTRUCAO E PAVIMENTACAO LTDA | Y44: OGU | AA44: 20 | AB44: F03 - EXECUÇÃO DO OBJETO | AC44: 02 - ANDAMENTO | AD44: 46718 | AJ44: 24845/2024 56000001031/2023 | AK44: 969064/2024 | AL44: 01 - Retirada Total | AO44: https://governodabahia.plataformatarget.com.br/web/189a2781-155b-472c-9c6d-01d0b10616b2/home | AP44: https://maps.app.goo.gl/XCs3zNJWeSWuGANd8 | AR44: 45811 | AS44: 45884 | AT44: 45880 | AU44: 46106 | AV44: 46718 | AW44: 46718 | AX44: CE GIGOV/SA 6099/2026 - Desbloqueio - BM 02 - Social - Etapa 2 Encontram-se em andamento as atividades de implantação do canteiro de obras, incluindo a instalação do canteiro destinado à equipe de fiscalização. Processo 2026.001.006448/INEMA/LIC-06448 no INEMA para de Licença Ambiental Unificada, Outorga e ASV, permanece com o status “aguardando distribuição” CE GIGOV/SA 1592/2026 - Enviado dia 20/03/26 - Informamos a pendência para o desbloqueio no valor de R$ 621.669,05. CE GIGOV SA 1536_2026 - Autorização de Início de Objeto_AIO recepcionado 18/03 Aguardando a AIO - Secr Executiva assinar e enviar para a matriz Caixa. CE GIGOV/SA 629/2026 - Enviado dia 03/02/26 - Aceitação da Verificação do Processo Licitatório do Social. REITERAÇÃO CE GIGOV/SA 5542/2025 - Enviado dia 27/01/26 - Pendência Verificação do Processo Licitatório do Social. CE GIGOV/SA 332/2026 - Pendência Para Solicitação da AIO- LICITAÇÃO PRESENCIAL Nº 035/25 - TC OGU 969064/2024. CAIXA solicita retificação da declaração de atendimento à legislação vigente, inserida no TGOV CE GIGOV/SA 208/2026 - Enviado dia 14/01/2026 - Pendência Para Aprovação. CE GIGOV/SA 208/2026 Pendência Para Aprovação - Licitação Presencial Nº 035/25 - Operação 1098381-91 DOE - 30/10 Resultado Finalda LP035/25 e Homologação, Adjudicação e Convocação para assinatura do Contrato Licitante vencedor - Consórcio Dom Avelar (PEJOTA Construções LTDA/ IDEAL Construção e Pavimentação LTDA Valor Global R$ 42.741.860,13 Recepcionado 13/06/25 - CE GIGOV/SA 2330/2025 - Aprovação do PTS. Autoriz. Iinicio de Licitação Mcidades 02/06/25 Assinatura e publicação do termo de compromisso publicado no DOU - 19/11/2024 Recepcionado 19/03 OF GIGOV solicitando da CONDER ajustes no projeto e Orçamento. Recepcionado dia 15/01/25 o Ofício nº 119 / 2025 / GIGOV/SA - Resposta do MCidades sobre Licenciamento Ambiental e Titularidade de Área; Cronograma cadastrado no TRANSFEREGOV - Prazo de execução - 20 meses, conclusão Prevista 21/12/26. Clausula Suspensiva: Apresentação dos itens (Anteprojeto, Projeto Básico, TR, Comprovação de propriedade do imóvel, Licenciamento Ambiental, Declaração de Sustentabilidade e PTS) até 08/07/25 Publicada no DOE 05/11 LEI Nº 14.784 DE 04 DE NOVEMBRO DE 2024 Autoriza o Poder Executivo a contratar operação de crédito interno junto à Caixa Econômica Federal - CEF. Na formalização se solicitou a unificação da Proposta 1031; Todo Material foi incluído na plataforma TGOV; Em fase de formalização, anterior ao TC; Ministério tem prazo de 30 dias para devolver a caixa - 13/10/24; CAIXA retornar ao proponente até 17/10 solicitando ou não complementações; A modalidade de Licitação adotada será Integrada, todas em um Termo de Compromisso com cinco metas. | AY44: DOE - 06/11 Resumo de Contrato 103/2025 Licitante vencedor - Consórcio Dom Avelar (PEJOTA Construções LTDA/ IDEAL Construção e Pavimentação LTDA Valor R$ 42.741.860,13 AIL Ministério das Cidades: 02/06/25 | BA44: Anteprojeto | BB44: =IFERROR(IF(PAC!$AB44="F01 - CAPTAÇÃO DE RECURSO",1,""),"") | BC44: =IFERROR(IF(PAC!$AB44="F02 - LICITAÇÃO",1,""),"") | BD44: =IFERROR(IF(PAC!$AB$6:$AB$581="F03 - EXECUÇÃO DO OBJETO",1,""),"") -> 1 | BE44: =IFERROR(IF(PAC!$AB$6:$AB$581="F04 - CONCLUÍDA",1,""),"") | BF44: =IF(PAC!$V44>0,0,PAC!$Q44) -> 0
A45: =ROW()-5 -> 40 | B45: 2023 | C45: OBRA | D45: PAC SELEÇÕES | E45: OBRAS DE MACRODRENAGEM E COMPLEMENTAÇÃO DA MACRODRENAGEM DA RUA NILO PEÇANHA (BAIXA DO FISCAL), NO BAIRRO DE URUGUAI, NA CIDADE DE SALVADOR - BAHIA | F45: Prevenção a Desastres Naturais | G45: Drenagem Urbana | H45: SEDUR | I45: 14 - Gov. Estado - CONDER | J45: Salvador | L45: 32671590 | M45: 62990873 | Q45: =SUM(PAC!$M45:$P45) -> 62990873 | V45: 53239507 | W45: =IF(PAC!$V45>0,PAC!$V45,PAC!$Q45) -> 53239507 | X45: Consórcio Macrodrenagem CBS Construtora Bahiana de Saneamento Ltda / Klao Engenharia S/A | Y45: OGU | AA45: 18 | AB45: F03 - EXECUÇÃO DO OBJETO | AC45: 02 - ANDAMENTO | AD45: 46449 | AE45: 24.49 | AJ45: 24845/2024 56000001031/2023 | AK45: 969064/2024 | AL45: 01 - Retirada Total | AO45: https://governodabahia.plataformatarget.com.br/web/a12df5fe-97ee-4721-9751-24e415d256c4/home | AP45: https://maps.app.goo.gl/hurhvtucjW5ooWFT8 | AR45: 45730 | AS45: 45804 | AT45: 45857 | AU45: 45901 | AV45: 46409 | AW45: 46491 | AX45: CE GIGOV SA 5709 2026 - Desbloqueio - BM 07 - Etapa 1 - Caixa comunica o desbloqueio de parcela CE GIGOV SA 5712 2026 - Crédito de Recursos Financeiros – Orçamento Geral da União - OBTV - Estado da Bahia CE GIGOV SA 5709 2026 - Desbloqueio Parcial de Parcela - BM 07 - Etapa 1 - COMPATIBILIDADE - TC OGU 969064/2024 - Operação 1098381-91 - Macrodrenagem em Salvador. CE GIGOVSA 4993 2026 - Desbloqueio de Parcela - BM 05 - Social CE GIGOVSA 4985 2026 - Ateste de Medição e Pendência Para Desbloqueio - BM 06 - Social CE GIGOVSA 4930 2026 - Condicionante Para Desbloqueio - BM 06 - Etapa 1 CE GIGOVSA 4584 2026 - Ateste de Medição e Pendência Para Desbloqueio - BM 05 - Social. Caixa acata 5 relatório BM Social CE GIGOVSA 3181-2026 - Crédito de Recursos Financeiros – Orçamento Geral da União CE GIGOVSA 3183-2026 - Crédito de Recursos Financeiros CE GIGOVSA 3015_2026 - Desbloqueio de Parcela - BM 02 - Etapa 1 Recepcionado 20/05 CE GIGOV/SA 3015/2026 - Desbloqueio de Parcela - BM 02 Recepcionado 19/05 CE GIGOVSA 2997_2026 - Ateste de Medição e Pendência Para Desbloqueio - BM 02 - Social O PRMC será apresentado tão logo seja concluída a etapa de caracterização dos imóveis e definição do quantitativo de reassentamentos previstos. Isto é, após conclusão do projeto executivo pela empresa contratada. CE GIGOVSA 5639 2026 - Condicionante Para Desbloqueio - BM 07 - Etapa 1 - COMPATIBILIDADE CE GIGOVSA 5536 2026 - Ateste de Medição e Desbloqueio do BM 07 do Social CE GIGOV/SA 1689/2026 - Enviado 26/03/26 - Referente ao Plano de Reassentamento e Medidas Compensatórias (PRMC) da operação em epígrafe, será posterior a licitação. CE GIGOV/SA 1592/2026 - Pendência Para Desbloqueio - BM 02. Caixa solicita inclusão de documento no TGOV CE GIGOV/SA 1592/2026 - Enviado dia 20/03/26 - Informamos a pendência para o desbloqueio no valor de R$ 621.669,05. Recepcionado dia 03/02/26 CE GIGOV/SA 538/2026 - Solicita informações acerca da situação da execução do objeto e dos motivos da não apresentação dos boletins de medição - Objeto sem evolução há mais de 90 dias CE GIGOV/SA 4606/2025 - Autorização de Início de Objeto – AIO – Etapa 1 . A plataforma TGOV emitiu o AIO automático em 13/10/2025. CE GIGOV/SA 4515/2025 - Enviado dia 10/10/25 Solicitação de Autorização para Início do Objeto - AIO. CE GIGOV/SA 4182/2025 - Enviado dia 23/09/2025 -Aceite da Verificação da Licitação de Obra/projeto da Etapa 01 e Solicitação de AIO ao MCidades. Projeto e Obra = R$ 53.239.506,77 Trabalho Social = R$ 666.812,85 Totalizando o valor de Repasse de R$ 53.906.319,62. CE GIGOV/SA 4139/2025 -Enviado dia 19/09/25 - Pendências de Documentação da VRPL de obra/projeto. Recepcionado CE GIGOV/SA 3954/2025 Pendências de Documentação da VRPL de obra/projeto da Etapa 01 Autorização de Inicio de Licitação concedida 10/03/25 Emissão de SPA (Sintese de Projeto Aprovada) no Tgov 07/02/2025 Recepcionado Of Gigov com despacho do Ministério das Cidades concedendo AIL; Recepcionado dia 15/01/25 o Ofício nº 119 / 2025 / GIGOV/SA - Resposta do MCidades sobre Licenciamento Ambiental e Titularidade de Área; Cronograma cadastrado no TRANSFEREGOV - Prazo de execução - 18 meses, conclusão Prevista 05/10/26. Clausula Suspensiva: Apresentação dos itens (Anteprojeto, Projeto Básico, TR, Comprovação de propriedade do imóvel, Licenciamento Ambiental, Declaração de Sustentabilidade e PTS) até 08/07/25 Titularidade do Terreno - Decreto Desapropriação em trâmite na Casa Civil SEI 043.4098.2024.0016016-23 Publicada no DOE 05/11 LEI Nº 14.784 DE 04 DE NOVEMBRO DE 2024 Autoriza o Poder Executivo a contratar operação de crédito interno junto à Caixa Econômica Federal - CEF. Em fase de formalização, anterior ao TC; Ministério tem prazo de 30 dias para devolver a caixa - 13/10/24; CAIXA retornar ao proponente até 17/10 solicitando ou não complementações; A modalidade de Licitação adotada será Integrada, todas em um Termo de Compromisso com cinco metas. | AY45: AIO emitida no TGOV 13/10 CT 068/2025 - Resumo do contrato publicado no DOE dia 19/07/2025. Empresa Vencedora: Consórcio Macrodrenagem (CBS Construtora Bahiana de Saneamento Ltda / Klao Engenharia Ltda). Valor R$: 53.239.506,78. | BA45: Anteprojeto | BB45: =IFERROR(IF(PAC!$AB45="F01 - CAPTAÇÃO DE RECURSO",1,""),"") | BC45: =IFERROR(IF(PAC!$AB45="F02 - LICITAÇÃO",1,""),"") | BD45: =IFERROR(IF(PAC!$AB$6:$AB$581="F03 - EXECUÇÃO DO OBJETO",1,""),"") -> 1 | BE45: =IFERROR(IF(PAC!$AB$6:$AB$581="F04 - CONCLUÍDA",1,""),"") | BF45: =IF(PAC!$V45>0,0,PAC!$Q45) -> 0
A46: =ROW()-5 -> 41 | B46: 2023 | C46: OBRA | D46: PAC SELEÇÕES | E46: OBRA DE DRENAGEM URBANA | F46: Prevenção a Desastres Naturais | G46: Drenagem Urbana | H46: SEDUR | I46: 14 - Gov. Estado - CONDER | J46: Itororó | K46: 34701704 | P46: 34701704 | Q46: =SUM(PAC!$M46:$P46) -> 34701704 | W46: =IF(PAC!$V46>0,PAC!$V46,PAC!$Q46) -> 34701704 | Y46: FINANCIAMENTO | Z46: FGTS | AA46: 36 | AB46: F01 - CAPTAÇÃO DE RECURSO | AC46: 05 - À LICITAR | AF46: Análise de compatibilidade do projeto pela Caixa; | AG46: CONDER reunindo documentações complementares solicitadas pela Caixa para posterior submissão para continuidade da análise. | AI46: - Elaboração de TR e edital para licitar; - Previsão de publicação do aviso de licitação; - Contratação do objeto licitado; - Emissão de OS; - Atendimento às condicionantes da cláusula resolutiva para 1° desembolso; - Monitorar execução do objeto; | AJ46: 56000001897/2023 | AK46: CF Financiamento 0639469-97/2025 | AO46: https://governodabahia.plataformatarget.com.br/web/5d575d0c-fff6-4c4b-bff7-5e9569535645/home | AX46: Projeto de engenharia aprovado CE 5057/2026, de 13/08/2026. Aguardando comprovação de lançamento do Edital de Licitação, prazo: 12/10/2026. Alteração Contratual de inclusão de Agente Promotor - Aguardando devolução do Aditivo assinado. Alteração Contratual de Meta Física - Em tramitação no Comitê da Superintendência Regional. Alteração Contratual de Prazo de primeiro desembolso / prazo total de desembolso - recebida solicitação em 17/08, em análise técnica. CE GIGOVSA 2019-2026 - Apontamentos da análise preliminar - Etapa Macrodrenagem em Itororó Recepcionado CE GIGOV/SA 1684/2026 dia 25/03 - Orientações para continuidade do processo (alteração contratual) - CF Financiamento 0639469-97/2025 Macrodrenagem em diversos municípios do Estado da Bahia CE GIGOV/SA 0219/2026 Alteração contratual - CT 0639469-97/2025 Macrodrenagem na Bahia - macrodrenagem nos municípios de Ubaíra e Itororó de maneira mais abrangente. Ofício nº 001/2026 – SEDUR/GAB/SGT, de 06/01/2026 contendo justificativa técnica para ampliação de escopo das intervenções de macrodrenagem nos municípios de Ubaíra e Itororó/BA e a supressão das intervenções de macrodrenagem nos Municípios Ilhéus e Ipiaú/BA. Recepcionado 16/06 CE GIGOV/SA 2334/2025 - A SNSA (Ministério das Cidades), gestora do contrato 0639469-97, não concordou em dispensar a apresentação de documentação de titularidade e o licenciamento ambiental, conforme pleiteado. CE GIGOV/AS 1556/2025 enviado dia 08/05/2025 solicitando providências quanto a inserção de documentos no SADIPEM para tramitação de PVL (Pedido de Verificação de Limites e Condições). SEPLAN comunica dia 07/04 que está em elaboração da Minuta do Contrato. Em fase de formalização, anterior ao TC; Prev de entrega da documentação via Tgov - Fev 2025 Modelo de lic. - Semi-integrada Licença Ambiental - será delegada a empresa contratada; DUP - A solicitar após revisão da poligonal; Em fase de formalização, anterior ao TC; Ministério tem prazo de 30 dias para devolver a caixa - 13/10/24; CAIXA retornar ao proponente até 17/10 solicitando ou não complementações; Contratação definida pela SUQUALI - A ser definida; - Cada meta será licitada individualmente - A prestação de contas será por Contrato de Repasse/Termo de Compromisso Recepcionado OF-GIGOV 2723/2024 que trata das informações relativas a contratação de financiamento FGTS para propostas do NOVO PAC - 26/09/2024 - A composição do Investimento inclui Repasse + Contrapartida Estadual de 5% Lei Autorizativa PLs 25.482 e 25.483 Fonte de recurso: FGTS | AY46: Aviso de LP 092/26 publicado no DOE 12/09/2026 Previsão de abertura 26/11/2026 Contratação da operação de crédito. Projeto em Fase final de Análise pela CAIXA. | BA46: ANTEPROJETO | BB46: =IFERROR(IF(PAC!$AB46="F01 - CAPTAÇÃO DE RECURSO",1,""),"") -> 1 | BC46: =IFERROR(IF(PAC!$AB46="F02 - LICITAÇÃO",1,""),"") | BD46: =IFERROR(IF(PAC!$AB$6:$AB$581="F03 - EXECUÇÃO DO OBJETO",1,""),"") | BE46: =IFERROR(IF(PAC!$AB$6:$AB$581="F04 - CONCLUÍDA",1,""),"") | BF46: =IF(PAC!$V46>0,0,PAC!$Q46) -> 34701704
A47: =ROW()-5 -> 42 | B47: 2023 | C47: OBRA | D47: PAC SELEÇÕES | E47: Obra de drenagem profunda na sede da cidade | F47: Prevenção a Desastres Naturais | G47: Drenagem Urbana | H47: SEDUR | I47: 14 - Gov. Estado - CONDER | J47: Ubaíra | K47: 46411180 | P47: 46411180 | Q47: =SUM(PAC!$M47:$P47) -> 46411180 | W47: =IF(PAC!$V47>0,PAC!$V47,PAC!$Q47) -> 46411180 | Y47: FINANCIAMENTO | Z47: FGTS | AA47: 36 | AB47: F01 - CAPTAÇÃO DE RECURSO | AC47: 05 - À LICITAR | AF47: Análise de compatibilidade do projeto pela Caixa; | AG47: CONDER reunindo documentações complementares solicitadas pela Caixa para posterior submissão para continuidade da análise. | AI47: - Elaboração de TR e edital para licitar; - Previsão de publicação do aviso de licitação; - Contratação do objeto licitado; - Emissão de OS; - Atendimento às condicionantes da cláusula resolutiva para 1° desembolso; - Monitorar execução do objeto; | AJ47: 56000001897/2023 | AK47: CF Financiamento 0639469-97/2025 | AO47: https://governodabahia.plataformatarget.com.br/web/585bfc0f-a140-488d-b6ac-b212a1ba9f55/home | AX47: Alteração Contratual de inclusão de Agente Promotor - Aguardando devolução do Aditivo assinado. Alteração Contratual de Meta Física - Em tramitação no Comitê da Superintendência Regional. Alteração Contratual de Prazo de primeiro desembolso / prazo total de desembolso - recebida solicitação em 17/08, em análise técnica. Recepcionado CE GIGOV/SA 1684/2026 dia 25/03 - Orientações para continuidade do processo (alteração contratual) - CF Financiamento 0639469-97/2025 Macrodrenagem em diversos municípios do Estado da Bahia CE GIGOV/SA 0219/2026 Alteração contratual - CT 0639469-97/2025 Macrodrenagem na Bahia - macrodrenagem nos municípios de Ubaíra e Itororó de maneira mais abrangente. Ofício nº 001/2026 – SEDUR/GAB/SGT, de 06/01/2026 contendo justificativa técnica para ampliação de escopo das intervenções de macrodrenagem nos municípios de Ubaíra e Itororó/BA e a supressão das intervenções de macrodrenagem nos Municípios Ilhéus e Ipiaú/BA. Recepcionado 16/06 CE GIGOV/SA 2334/2025 - A SNSA (Ministério das Cidades), gestora do contrato 0639469-97, não concordou em dispensar a apresentação de documentação de titularidade e o licenciamento ambiental, conforme pleiteado. SEPLAN comunica dia 07/04 que está em elaboração da Minuta do Contrato. Em fase de formalização, anterior ao TC; Prev de entrega da documentação via Tgov - Fev 2025 Modelo de lic. - Semi-integrada Licença Ambiental - será delegada a empresa contratada; DUP - A solicitar após revisão da poligonal; Ministério tem prazo de 30 dias para devolver a caixa - 13/10/24; CAIXA retornar ao proponente até 17/10 solicitando ou não complementações; Contratação definida pela SUQUALI -a ser definida - Cada meta será licitada individualmente - A prestação de contas será por Contrato de Repasse/Termo de Compromisso Recepcionado OF-GIGOV 2723/2024 que trata das informações relativas a contratação de financiamento FGTS para propostas do NOVO PAC - 26/09/2024 - A composição do Investimento inclui Repasse + Contrapartida Estadual de 5% Lei Autorizativa PLs 25.482 e 25.483 Fonte de recurso: FGTS | AY47: Contratação da operação de crédito. Projeto em Fase final de Análise pela CAIXA. | BA47: ANTEPROJETO | BB47: =IFERROR(IF(PAC!$AB47="F01 - CAPTAÇÃO DE RECURSO",1,""),"") -> 1 | BC47: =IFERROR(IF(PAC!$AB47="F02 - LICITAÇÃO",1,""),"") | BD47: =IFERROR(IF(PAC!$AB$6:$AB$581="F03 - EXECUÇÃO DO OBJETO",1,""),"") | BE47: =IFERROR(IF(PAC!$AB$6:$AB$581="F04 - CONCLUÍDA",1,""),"") | BF47: =IF(PAC!$V47>0,0,PAC!$Q47) -> 46411180
A48: =ROW()-5 -> 43 | B48: 2023 | C48: OBRA | D48: PAC SELEÇÕES | E48: EXECUÇÃO DA OBRA DE MACRODRENAGEM DE CANAL PARA O RIO GONGOJI, NO MUNICÍPIO DE DÁRIO MEIRA - BAHIA | F48: Prevenção a Desastres Naturais | G48: Drenagem Urbana | H48: SEDUR | I48: 14 - Gov. Estado - CONDER | J48: Dário Meira | L48: 19115211 | M48: 19115211 | Q48: =SUM(PAC!$M48:$P48) -> 19115211 | V48: 16698772 | W48: =IF(PAC!$V48>0,PAC!$V48,PAC!$Q48) -> 16698772 | X48: COESA CONSTRUÇÕES E MONTAGENS SA | Y48: OGU | AA48: 15 | AB48: F03 - EXECUÇÃO DO OBJETO | AC48: 02 - ANDAMENTO | AD48: 46455 | AE48: 28.44 | AJ48: 024835/2024 56000000251/2023 | AK48: 969063/2024 | AL48: 01 - Retirada Total | AO48: https://governodabahia.plataformatarget.com.br/web/adcdca1d-d538-4bf5-9ab6-0258e83c4539/home | AP48: https://maps.app.goo.gl/1NaMUrQnWD6b9xW16 | AR48: 45759 | AS48: 45841 | AT48: 45886 | AU48: 46000 | AV48: 46455 | AW48: 46455 | AX48: CE GIGOV SA 5655 2026 - Crédito de Recursos Financeiros – Orçamento Geral da União CE GIGOV SA 5495 2026 - Ateste de Medição do BM 02 até o BM 06 CE GIGOVSA 5058/2026 - Desbloqueio de Parcela - BM 01- RAT CE GIGOVSA 5068 2026 - Desbloqueio de Parcela - BM 04 CE GIGOVSA 5065 2026 - Crédito de Recursos - OBTV CE GIGOV/SA 4290/2026 - Desbloqueio de Parcela - BM 04 - TC OGU 969063/2024 CE GIGOV/SA 4265/2026 - Condicionante Para Desbloqueio CE GIGOV SA 4086 2026 Estado da Bahia CAIXA TC OGU MCIDADES 969063 2024 Operação 1098379 59 Ofício de Crédito de Recursos OBTV - Notificamos o crédito de recursos financeiros, sob bloqueio. CE GIGOV/SA 3737/2026 - Condicionante Para Desbloqueio - BM 04 CAixa solicita documentação para desbloqueio de valor Quanto a Dário Meira, o projeto executivo já foi aprovado pela Caixa na primeira medição. A Ordem de Serviço (O.S.) foi emitida em 09/12/2025. Referente às desapropriações, as áreas 03 e 05 já foram negociadas. As áreas 01, 02 e 04 estão atualmente na CODES para análise dos apontamentos do PROJUR. CE GIGOVSA 3179-2026 - Desbloqueio de Parcela - BM 03 CE GIGOVSA 3180-2026 - Crédito de Recursos Financeiros – Orçamento Geral da União Recepcionado CE GIGOV SA 2863 2026 - Desbloqueio de Parcela - BM 02 CE GIGOVSA 2486_2026 - Pendência Para Desbloqueio - BM 02 - TC OGU 9690632024 CE GIGOV/SA 1481/2026 Enviado dia 17/03/26 - Solicita comprovação de início de obra e registro de BM. Obra com Barracão estaqueameto e topografia concluída, porém o efetivo inicio das obras está vinculado a desapropriação de 5 áreas. Houve avanço nas tratativas para desapropriação de uma das áreas com o autorizo para execução de sondagem. Há a expectativa de elaboração do projeto executivo e inico de obras civis com medição até 31/03. CE GIGOV/SA 969/2026 - Documentação para início de obra - TC OGU 969063/2024 CAIXA solicita envio de documentação para caracterização do início dos serviços. CE GIGOV/SA 445/2026 -Enviado dia 27/01/26 - Solicita disponibilização da Ordem de Serviço. CE GIGOV/SA 5636/2025 - recepcionado 03/12 - Estado da Bahia - CAIXA - TC OGU MCIDADES 969063/2024 - Operação 1098379-59 - Ofício de Autorização de Início do Objeto (AIO) DUP - 24.155 publicado no DOE 02/12/2025,Altera o Decreto nº 23.353, de 10 de janeiro de 2025, na forma que indica. utilidade pública, para fins de constituição de servidão administrativa, a área de terra medindo 97.645,18m², situada às margens do Rio Gongoji, no Município de Dário Meira - Bahia VRPL emitido 01/12/2025 CE GIGOV/SA 5459/2025 - Enviado dia 26/11/25 - Análise Preliminar da proposta de alteração do Traçado. CE GIGOV/SA 5439/2025 - Enviado dia 25/11/25 - Solicita comprovação de abertura do processo licitatório. Documentos Orçamentários Enviado dia 13/10/25 – Conclusão automática da SPA pelo sistema realizada com sucesso. Recepcionado dia 08/04 CE GIGOV/SA 1070/2025 - Autorização do Processo Licitatório. Recepcionado 27/02/25 CE GIGOV/SA 431/2025 1 A SEDUR protocolou documentação complementar referente à análise de engenharia 2 Recebedor deve realizar as seguintes inserções na aba anexos do Projeto Básico do TransfereGov: Matriz de risco; Laudo Técnico de Especialista caracterizando o Município de Dário Meira como de alto a muito alto grau de riscos de inundação e enchentes; Realizar ajustes no QCI; CE GIGOVSA 4986 2026 - Ofício de Crédito de Recursos - OBTV - Estado da Bahia CE GIGOVSA 4888 2026 - QCI para verificação de conformidade CE GIGOV/SA 4764/2026 - Condicionante Para Desbloqueio - BM 04. Caixa solicita complementações. Recepcionado OF GIGOV da Caixa com a informação de que para a retirada da Clausula Suspensiva é necessário que a CONDER apresente o Projeto de Trabalho Social 2º Versão no Transferegov e PO com as devidas assinaturas. Recepcionado dia 15/01/25 o Ofício nº 119 / 2025 / GIGOV/SA - Resposta do MCidades sobre Licenciamento Ambiental e Titularidade de Área; Cronograma cadastrado no TRANSFEREGOV - Prazo de execução - 11 meses, conclusão Prevista 05/08/25. Clausula Suspensiva: Apresentação dos itens (Anteprojeto, Projeto Básico, TR, Comprovação de propriedade do imóvel, Licenciamento Ambiental, Declaração de Sustentabilidade e PTS) até 08/07/25 Prefeitura em negociação com o proprietário do terrno para emissão de Termo de Cessão de área para construção da Faixa de servidão para manutenção do Canal. Lic Ambiental - Em fase de solicitação pela Prefeitura do Município. Publicada no DOE 05/11 LEI Nº 14.784 DE 04 DE NOVEMBRO DE 2024 Autoriza o Poder Executivo a contratar operação de crédito interno junto à Caixa Econômica Federal - CEF. Recepcionado Of 3109/2024 GIGOV/SA - solicitando complemteação de informações e documentação. Em fase de formalização, anterior ao TC; Ministério tem prazo de 30 dias para devolver a caixa - 13/10/24; CAIXA retornar ao proponente até 17/10 solicitando ou não complementações; Contratação definida pela SUQUALI - Semi Integrada - Cada meta será licitada individualmente - A prestação de contas será por Contrato de Repasse/Termo de Compromisso Nº da proposta Novo PAC - Seleção 56000000251/2023 | AY48: OS Assinada dia 09/12/25 AIO emitida 03/12 LP 026/25 - Resumo de Contrato publicado no DOE 12/08 Ctr.: 075/2025 Empresa Vencedora: COESA CONSTRUÇÕES E MONTAGENS SA Valor Contratado: R$16.698.771,58 | BA48: Anteprojeto | BB48: =IFERROR(IF(PAC!$AB48="F01 - CAPTAÇÃO DE RECURSO",1,""),"") | BC48: =IFERROR(IF(PAC!$AB48="F02 - LICITAÇÃO",1,""),"") | BD48: =IFERROR(IF(PAC!$AB$6:$AB$581="F03 - EXECUÇÃO DO OBJETO",1,""),"") -> 1 | BE48: =IFERROR(IF(PAC!$AB$6:$AB$581="F04 - CONCLUÍDA",1,""),"") | BF48: =IF(PAC!$V48>0,0,PAC!$Q48) -> 0
A49: =ROW()-5 -> 44 | B49: 2023 | C49: OBRA | D49: PAC ORIGINAL | E49: Drenagem Urbana - Bairros Bonfim Boa Viagem e Massaranduba | F49: Prevenção a Desastres Naturais | G49: Drenagem Urbana | H49: SEDUR | I49: 14 - Gov. Estado - CONDER | J49: Salvador | M49: 78622205 | Q49: =SUM(PAC!$M49:$P49) -> 78622205 | V49: 94971709 | W49: =IF(PAC!$V49>0,PAC!$V49,PAC!$Q49) -> 94971709 | X49: CBS CONSTRUTORA BAIANA DE SANEAMENTO LTDA | Y49: OGU | AA49: 30 | AB49: F03 - EXECUÇÃO DO OBJETO | AC49: 02 - ANDAMENTO | AD49: 46302 | AE49: 84.15 | AK49: 0459669-83/2015 | AL49: 01 - Retirada Total | AO49: https://governodabahia.plataformatarget.com.br/web/05f27b4a-15a6-485a-949b-1d46c52a6162/home | AP49: https://maps.app.goo.gl/KQKy9qS4cttDp9PA7 | AR49: 45160 | AS49: 45184 | AT49: 45210 | AU49: 45300 | AV49: 46200 | AW49: 46302 | AX49: CE GIGOV SA 6110 2026 -Desbloqueio de Parcela RETIFICAÇÃO: CE GIGOV SA 5963 2026 - Crédito de Recursos - Estado da Bahia CE GIGOV SA 5753 2026 - Pendência Para o Desbloqueio de Parcela do Social - Junho 2026 - TC 0459669-83 2015 Drenagem Bonfim Boa Viagem Massaranduba CE GIGOV/SA 5751/2026 - Ateste de Medição até o BM 31 e Pendência para o Desbloqueio - TC PAC 0459669-83 2015 - DRENAGEM BONFIM MASSARANDUBA Aditivo de 90 dias de prazo em trâmite CE GIGOV SA 5653 2026 Crédito de Recursos Financeiros Orçamento Geral da União CE GIGOV SA 5561 2026 - Pendência Para o Desbloqueio de Parcela do Social CE GIGOV/SA 5323/2026 - Termo Aditivo ao Termo de Compromisso 304 dias CE GIGOV/SA 5251/2026 - Crédito de Recursos - Estado da Bahia - CAIXA - TC PAC 0459669-83/2015 Há uma pendência de desapropriação de duas unidades habitacionais nas quais foi judicializado pelos proprietários o processo de desapropriação. CE GIGOV SA 4358 2026 - Crédito de Recursos - Estado da Bahia CAIXA notifica o crédito de recursos financeiros, sob bloqueio, em 14/07/2026, no valor de R$ 2.522.350,13 CE GIGOV/SA 4360/2026 - Desbloqueio de Parcela do Social - Mar/2026 CE GIGOV SA 4359 2026 - Desbloqueio Parcial do BM 27 e 28 Complemento + BM 29 - CAIXA comunica o desbl parcial no valor de R$ 2.484.206,67 conforme CE GIGOV/SA 4263/2026. CE GIGOV/SA 4263/2026 - Pendência Para Desbloqueio do BM 27e 28 ( Complemento) + BM 29 - TC 0459669-83/2015 Drenagem Bonfim/Boa ENC: CE GIGOV SA 3270 2026 - Inconsistência solicitação desbloqueio RRE BM 27 e 28 CE GIGOV/SA 4244/2026 - Crédito de Recursos Financeiros – Orçamento Geral da União Recepcionado 14/05 CE GIGOV/SA 2883/2026 - Pendência Para Desbloqueio ( BM 27) - Caixa solicita relatório fotográfico para proceder com o desbloqueio CE GIGOV/SA 2764/2026 - Desbloqueio do Social CE GIGOV/SA 1630/2026 - Crédito de Recursos CE GIGOV/SA 1214/2026 - Informa desbloqueio do saldo do BM 23 CE GIGOV/SA 1160/2026 - Solicita correções no BM CE GIGOV/SA 1854/2026 - Ateste de Medição ( BM 22 a 26) e Desbloqueio Parcial ( BM 24 a 26) - TC 0459669-83/2015 Drenagem Bonfim/Boa Viagem/Massaranduba CE GIGOV/SA 1826/2026 - Termo Aditivo CTEF nº 119/2023 - TC PAC 0459669-83/2015 - DRENAGEM BONFIM MASSARANDUBA CE GIGOV/SA 1790/2026 - Crédito de Recursos - Estado da Bahia - CAIXA - TC PAC 0459669-83/2015 CE GIGOV/SA 1214/2026 - Enviado dia 04/03/26 - Comunicamos o desbloqueio complementar no valor de R$ 437.323,08. CE GIGOV/SA 1036/2026 - Enviado dia 24/02/26 - Informamos a pendência para o desbloqueio do valor de repasse referente ao relatório de outubro/2025, encaminhado por meio do OF 099/2026, no valor de R$ 28.036,78. CE GIGOV/SA 1006/2026 -Enviado dia 23/02/26 - Ofício de Crédito de Recursos. Notificamos a V.Exa. o crédito de recursos financeiros, sob bloqueio, em 19/02/2026, no valor de R$ 1.744.597,56. CE GIGOV/SA 888/2026 - Enviado dia 12/02/2026 - Informa desbloqueio parcial p/ compatibilidade no valor de R$ 987.472,69. Recepcionado dia 03/02 CE GIGOV/SA 700/2026 - Informa desbloqueio complementar p/ compatibilidade BM 22 - Etapa 02 (Lotes 01, 02, 03 e 04) CE GIGOV/SA 3025/2025 enviado dia 25/07/2025 - Notificado a V.Exa. do crédito de recursos financeiros, sob bloqueio, em 23/07/2025, no valor de R$ 2.226.905,18 Reprogramação de serviços em trâmite. | AY49: Termo Aditivo ao Termo de Compromisso 304 dias Monitorar a execução da obra - Conclusão prevista: Jul/2026; | BB49: =IFERROR(IF(PAC!$AB49="F01 - CAPTAÇÃO DE RECURSO",1,""),"") | BC49: =IFERROR(IF(PAC!$AB49="F02 - LICITAÇÃO",1,""),"") | BD49: =IFERROR(IF(PAC!$AB$6:$AB$581="F03 - EXECUÇÃO DO OBJETO",1,""),"") -> 1 | BE49: =IFERROR(IF(PAC!$AB$6:$AB$581="F04 - CONCLUÍDA",1,""),"") | BF49: =IF(PAC!$V49>0,0,PAC!$Q49) -> 0
A50: =ROW()-5 -> 45 | B50: 2023 | C50: OBRA | D50: PAC SELEÇÕES | E50: CONTRATAÇÃO INTEGRADA DE EMPRESA ESPECIALIZADA PARA DESENVOLVIMENTO DE PROJETOS BASICOS E EXECUTIVOS E EXECUÇÃO DE OBRAS DE MACRODRENAGEM DO CANAL DE BATE FACHO, NO BAIRRO DE PITUAÇU, NA CIDADE DE SALVADOR-BA. | F50: Prevenção a Desastres Naturais | G50: Drenagem Urbana | H50: SEDUR | I50: 14 - Gov. Estado - CONDER | J50: Salvador | L50: 9086276.2 | M50: 13449629 | Q50: =SUM(PAC!$M50:$P50) -> 13449629 | V50: 9660258.6 | W50: =IF(PAC!$V50>0,PAC!$V50,PAC!$Q50) -> 9660258.6 | X50: Pejota Construções LTDA | Y50: OGU | AA50: 12 | AB50: F03 - EXECUÇÃO DO OBJETO | AC50: 02 - ANDAMENTO | AD50: 46522 | AE50: 8.05 | AH50: 46522 | AJ50: 24845/2024 56000001031/2023 | AK50: 969064/2024 | AL50: 01 - Retirada Total | AO50: https://governodabahia.plataformatarget.com.br/web/ddae084d-f628-45fa-b4e1-428313f24101/home | AP50: https://maps.app.goo.gl/VsKANwEPjmNe5Fhr5 | AR50: 45906 | AS50: 45975 | AT50: 46042 | AU50: 46157 | AV50: 46522 | AW50: 46522 | AX50: CE GIGOV SA 4101 2026 Verificação de Resultado de Processo Licitatório Trabalho Social Etapa 3 Bate Facho TC OGU 969064 2024 - Caixa solicita complementação de documentação CE GIGOVSA 2830_2026 - Autorização de Início de Objeto – AIO – Etapa 3 ( Bate Facho) Caixa informa da AIO CE GIGOV/SA 1592/2026 - Enviado dia 20/03/26 - Informamos a pendência para o desbloqueio no valor de R$ 621.669,05. CE GIGOV/SA 1413/2026 - Caixa informa o aceite VRPL. Solicita envio do processo no TGOV CE GIGOV/SA 1413/2026 - Enviado dia 13/03/26 - Verificação do Resultado do Processo Licitatório. Aceito nesta VRPL. Valor R$ 9.660.258,59. Recepcionado CE GIGOV/SA 420/2026 - Solicitado a inclusão na plataforma TGOV documentação de inicio ou conclusão de cocumentos que comprovem a realização da Licitação da Etapa 3. Dando um prazo limite de prorrogação de mais 60 dias. CE GIGOV/SA 5262/2025 -Enviado dia 18/11/25 - Análise da 1ª versão da reprogramação do PTS. Recepcionado o CE GIGOV/SA 3620/2025 - Aceite de Projeto do Tomador/Proponente CE GIGOV/SA 2879/2025 enviado dia 17/07/2025 - Pendências da Análise. Recepcionado 23/06/25 CE GIGOV/SA 2429/2025 Operação 1098381-91 - Meta BATE FACHO CAIXA Encaminha Relatório de Pendencias/esclarecimentos necessários para finalização da análise.(Revisões e complementações na documentação apresentada) CE GIGOV/SA 1978/2025 - Laudo de Análise de Instrumento de Planejamento Social; 19/05 A CONDER informou que o anteprojeto está finalizado e está em análise pela CAIXA. As Complementações e retificações que a CAIXA havia solicitado para que se fizesse no Orçamento foram feitas e encaminhadas desde o dia 30/04/2025. A CONDER tem insistido para que a análise ocorra de maneira célere. Porém o Status atual é análise da Documentação pela CAIXA. Recepcionado dia 03/04/25 CE GIGOV/SA 998/2025 - Análise Preliminar - Caixa solicita correções/ complementações. Recepcionado dia 15/01/25 o Ofício nº 119 / 2025 / GIGOV/SA - Resposta do MCidades sobre Licenciamento Ambiental e Titularidade de Área; Cronograma cadastrado no TRANSFEREGOV - Prazo de execução - 12 meses, conclusão Prevista 08/04/26. Clausula Suspensiva: Apresentação dos itens (Anteprojeto, Projeto Básico, TR, Comprovação de propriedade do imóvel, Licenciamento Ambiental, Declaração de Sustentabilidade e PTS) até 08/07/25 Publicada no DOE 05/11 LEI Nº 14.784 DE 04 DE NOVEMBRO DE 2024 Autoriza o Poder Executivo a contratar operação de crédito interno junto à Caixa Econômica Federal - CEF. Em fase de formalização, anterior ao TC; Ministério tem prazo de 30 dias para devolver a caixa - 13/10/24; CAIXA retornar ao proponente até 17/10 solicitando ou não complementações; A modalidade de Licitação adotada será Integrada, todas em um Termo de Compromisso com cinco metas. | AY50: Resumo DO CT 010/2026 - Macrodrenagem Bate Facho - DOE 21/01 Homologação, Adjudicação e Convocação para assinatura do Contrato - LP 058/25 - publicado no DOE 15/01 - Licitante Vencedor Pejota Construções LTDA. | BA50: Anteprojeto | BB50: =IFERROR(IF(PAC!$AB50="F01 - CAPTAÇÃO DE RECURSO",1,""),"") | BC50: =IFERROR(IF(PAC!$AB50="F02 - LICITAÇÃO",1,""),"") | BD50: =IFERROR(IF(PAC!$AB$6:$AB$581="F03 - EXECUÇÃO DO OBJETO",1,""),"") -> 1 | BE50: =IFERROR(IF(PAC!$AB$6:$AB$581="F04 - CONCLUÍDA",1,""),"") | BF50: =IF(PAC!$V50>0,0,PAC!$Q50) -> 0
A51: =ROW()-5 -> 46 | B51: 2023 | C51: PROJETO | D51: PAC SELEÇÕES | E51: Contratação de empresa de engenharia para elaboração de projeto básico de macrodrenagem, no município de Aratuípe BA | F51: Prevenção a Desastres Naturais | G51: Drenagem Urbana | H51: SEDUR | I51: 14 - Gov. Estado - CONDER | J51: Aratuípe | L51: 16525798 | M51: 826290 | Q51: =SUM(PAC!$M51:$P51) -> 826290 | V51: 671333.89 | W51: =IF(PAC!$V51>0,PAC!$V51,PAC!$Q51) -> 671333.89 | X51: HIGESA ENGENHARIA LTDA | Y51: OGU | AA51: 4 | AB51: F03 - EXECUÇÃO DO OBJETO | AC51: 02 - ANDAMENTO | AD51: 46304 | AE51: 29.2 | AJ51: 25094/2024 56000004587/2023 | AK51: 969146/2024 | AL51: 01 - Retirada Total | AO51: https://governodabahia.plataformatarget.com.br/web/ad4b6407-ea23-44e9-be91-479a93c6e88f/home | AR51: 46056 | AS51: 46129 | AT51: 46157 | AU51: 46182 | AV51: 46304 | AW51: 46349 | AX51: Ofício 0485 2026 GIGOV SA - Crédito de Recursos Financeiros – Orçamento Geral da União CE GIGOVSA 6112 2026 - Estado da Bahia - Incorporação de Nota de Empenho CE GIGOV SA 5947 2026 - Crédito de Recursos - OBTV - Estado da Bahia - CAIXA - TC OGU 969146 CE GIGOV SA 5787 2026 - Estado da Bahia TC 969146 2024 Regime Simplificado – Caixa informa Desbloqueio de Recursos CE GIGOV SA 4025 2026 - Enviado dia 01/07/26 -Caixa informa que os recursos discriminados abaixo foram integralmente desbloqueados nesta data no Transferegov, conforme os procedimentos aplicáveis às operações enquadradas no Regime Simplificado. Recepcionado 08/06/26 CE GIGOV/SA 3392/2026 - Requisitos para Autorização de Início de Objeto Automática no TransfereGov Aviso de licitação presencial publicado no DOE 03/02/26 - LP 007/26 previsão de abertura 17/04/26. CE GIGOV/SA 439/2026 - Enviado dia 27/01/26 - Em atendimento, informamos que o prazo para publicação do edital de licitação foi prorrogado e deverá ocorrer até a data limite de 21/03/2026. CE GIGOV/SA 360/2026 - Solicitação de Prorrogação de Prazo para Abertura de Processo Licitatório - Oficio nº 01/2026 - SEDUR - TC OGU 969146/2024. CAIXA aponta que não emitirá novas consideraçõessobre o pedido de prorrogação de prazos para licitação. REITERAÇÃO: CE GIGOV/SA 5442/2025 - TC MCIDADES 969146/2024 - Solicita comprovação de abertura do processo licitatório RETIFICADO: CE GIGOV/SA 5442/2025 - Enviado dia 16/12/25 - Solicita comprovação de abertura do processo licitatório. CE GIGOV/SA 5428/2025 - Enviado dia 25/11/25 Orientações para Continuidade do Processo - Regime Simplificado. CE GIGOV/SA 5442/2025 - Enviado dia 25/11/25 - Solicita comprovação de abertura do processo licitatório. E-mail enviado dia 25/11/25 -Conclusão automática da SPA. Meta em análise para revisão do escopo e republicação do edital. DOE 05/08/25 - Informada a Revogação LP 038/25 Conder informou dia 28/05 que a meta do vale do Saboeiro foi substituida por projeto de macrodrenagem na San Martins. Cronograma cadastrado no TRANSFEREGOV - Prazo de execução - 33 meses, conclusão Prevista 30/09/27. Apresentação do item da Clausula Suspensiva: TR até 08/07/25 Publicada no DOE 05/11 LEI Nº 14.784 DE 04 DE NOVEMBRO DE 2024 Autoriza o Poder Executivo a contratar operação de crédito interno junto à Caixa Econômica Federal - CEF. Em fase de formalização, anterior ao TC; Ministério tem prazo de 30 dias para devolver a caixa - 13/10/24; CAIXA retornar ao proponente até 17/10 solicitando ou não complementações; Foi proposto R$ 16.525.797,61, mas foi selecionado R$ 826.289,88 A modalidade de Licitação adotada será Integrada, todas em um Termo de Compromisso com cinco metas. N da proposta seleção PAC 56000004587/2023 | AY51: Resultado final, homologação, adjudicação e convocação para assinatura do contrato publicado no DOE 11/05/2026 Aviso de licitação presencial publicado no DOE 03/02/26 - LP 007/26 previsão de abertura 17/04/26. | BA51: Estudo Preliminar | BB51: =IFERROR(IF(PAC!$AB51="F01 - CAPTAÇÃO DE RECURSO",1,""),"") | BC51: =IFERROR(IF(PAC!$AB51="F02 - LICITAÇÃO",1,""),"") | BD51: =IFERROR(IF(PAC!$AB$6:$AB$581="F03 - EXECUÇÃO DO OBJETO",1,""),"") -> 1 | BE51: =IFERROR(IF(PAC!$AB$6:$AB$581="F04 - CONCLUÍDA",1,""),"") | BF51: =IF(PAC!$V51>0,0,PAC!$Q51) -> 0
A52: =ROW()-5 -> 47 | B52: 2025 | C52: OBRA | D52: PAC SELEÇÕES | E52: MACRODRENAGEM - CANDEIAS: desenvolvimento de Projeto de canalização de talvegue tributário referente aos dois canais de drenagem da cidade de Candeias: Canal 01: drena a porção central da cidade; Canal 02: drena o bairro Santo Antônio | F52: Prevenção a Desastres Naturais | G52: Drenagem Urbana | H52: SEDUR | I52: 14 - Gov. Estado - CONDER | J52: Candeias | K52: 46159224 | P52: 46187620 | Q52: =SUM(PAC!$M52:$P52) -> 46187620 | W52: =IF(PAC!$V52>0,PAC!$V52,PAC!$Q52) -> 46187620 | Y52: FINANCIAMENTO | Z52: FGTS | AA52: 36 | AB52: F01 - CAPTAÇÃO DE RECURSO | AC52: 05 - À LICITAR | AF52: Publicação de Lei Autorizativa | AG52: Definição do Estado quanto a publicação da Lei Autorizativa | AH52: 46325 | AI52: Apresentação da documentação administrativa para contratação de operações (SEPLAN/Secretarias) Publicação de Lei Autorizativa Validação da proposta pelo Agente Financeiro Contratação da Operação de Crédito Envio do projeto para avaliação de compatibilidade pela Caixa; Análise de compatibilidade do projeto pela Caixa; Atendimento às condicionantes da cláusula resolutiva para 1° desembolso | AJ52: 56000001616/2025 56011/2025 | AO52: https://governodabahia.plataformatarget.com.br/web/24f98c53-1b0e-458b-9ce7-f91d836209cd/home | BA52: Anteprojeto | BB52: =IFERROR(IF(PAC!$AB52="F01 - CAPTAÇÃO DE RECURSO",1,""),"") -> 1 | BC52: =IFERROR(IF(PAC!$AB52="F02 - LICITAÇÃO",1,""),"") | BD52: =IFERROR(IF(PAC!$AB$6:$AB$581="F03 - EXECUÇÃO DO OBJETO",1,""),"") | BE52: =IFERROR(IF(PAC!$AB$6:$AB$581="F04 - CONCLUÍDA",1,""),"") | BF52: =IF(PAC!$V52>0,0,PAC!$Q52) -> 46187620
A53: =ROW()-5 -> 48 | B53: 2025 | C53: OBRA | D53: PAC SELEÇÕES | E53: Contratação integrada de empresa especializada para elaboração dos projetos básico e executivos e a execução da obra da 2ª etapa do fechamento do canal do malhado(etapa Nelson Schawn) no município de Ilhéus estado da Bahia. | F53: Prevenção a Desastres Naturais | G53: Drenagem Urbana | H53: SEDUR | I53: 14 - Gov. Estado - CONDER | J53: Ilhéus | L53: 22800367 | M53: 22800367 | Q53: =SUM(PAC!$M53:$P53) -> 22800367 | W53: =IF(PAC!$V53>0,PAC!$V53,PAC!$Q53) -> 22800367 | Y53: OGU | AA53: 36 | AB53: F02 - LICITAÇÃO | AC53: 04 - LICITAÇÃO /CONTRATAÇÃO | AF53: Abertura das Propostas | AG53: CONDER proceder com a abertura de propostas | AH53: 46323 | AI53: - Enviar projetos para análise qualitativa pela Mandatária - Enviar documentos para atendimento à Cláusula Suspensiva - Realizar Visita Técnica pela Mandatária ao local da Obra - Elaboração TR e Edital - Publicar Aviso da Licitação - Abertura das Propostas - Homologar e Adjudicar Licitação - Publicar Contrato de Execução - Enviar documentos para obtenção do VRPL - Emissão de AIO - Emissão de Alvará - Emitir Ordem de Serviço | AJ53: 56000001616/2025 56011/2025 | AK53: 986129 | AL53: 01 - Retirada Total | AO53: https://governodabahia.plataformatarget.com.br/web/49fc86a9-f2e7-42ca-bee7-cce992ffe2da/home | AR53: 46223 | AS53: 46293 | AT53: 46341 | AX53: REITIFICAÇÃO CE GIGOVSA 47862026 - Prazo para apresentação do resultado do processo licitatório da Etapa 1 Ipiaú - 30 de outubro Ilhéus CE GIGOV SA 4852 2026 - Apontamentos da análise da 2ª versão do PTS - Etapa 2 Ilhéus RETIFICAÇÃO CE GIGOVSA 47862026 - Prazo para apresentação do resultado do processo licitatório da Etapa 2 Ilhéus - 19 de Novembro. CE GIGOV/SA 4015/2026 - Incorporação de Nota de Empenho - CAIXA informa a incorporação dos dados orçamentários e financeiros de recursos. CE GIGOV/SA 4149/2026 - CAIXA informa por meio de correspondência prazo para aprovação de projeto e valores propostos e obtenção do LAE - Etapa 02 CE GIGOV/SA 2816/2026 - Prorrogação do prazo para atendimento da condição suspensiva Ministério das Cidades autorizou a prorrogação do prazo de cumprimento da condição suspensiva para as operações de Drenagem contratadas em dezembro/2025, abrangendo o Termo de Compromisso referenciado. Tal medida contempla as Etapas 02 a 09 (Ilhéus; Itororó; Juazeiro 01; Juazeiro 02; Ubaíra; Santo Amaro; Dário Meira (2ª etapa); Medeiros Neto). Novo prazo 29/07/2026 CE GIGOV/SA 2978/2026 - Apontamentos da análise técnica – Etapa 2 (Macrodrenagem em Ilhéus) - Caixa solicita ajustes e complementações na documentação técnica Recepcionado dia 07/03 CE GIGOVSA 2651_2026 - Apontamentos da análise técnica Etapa Ilhéus Caixa solicita ajustes e complementações na documentação enviada. CE GIGOVSA 1574/2026 - Enviado dia 20/03/26 - Apontamentos da análise preliminar. CE GIGOVSA 901/2026 - Enviado dia 12/02/26 - Apontamentos da análise preliminar. CE GIGOV/SA 0309/2026 Etapa 01 - Ilhéus: análise preliminar 02 - TC 986129/2025. A CONDER protocolou Ofício 176/2025 CONDER/DIURB/SUEQUI, encaminhando documentação complementar referente ao anteprojeto da Etapa de Macrodrenagem no Município de Ilhéus. Após análise, a CAIXA solicita complementações. | AY53: AVISO DE LP - 076/26 - MACRODRENAGEM - DOE 20/07/26 - CONDER abertura 28/09/26 CONDER protocolou Ofício 176/2025 CONDER/DIURB/SUEQUI, encaminhando documentação complementar referente ao anteprojeto´, para análise qualitativa da CAIXA. | BA53: Anteprojeto | BB53: =IFERROR(IF(PAC!$AB53="F01 - CAPTAÇÃO DE RECURSO",1,""),"") | BC53: =IFERROR(IF(PAC!$AB53="F02 - LICITAÇÃO",1,""),"") -> 1 | BD53: =IFERROR(IF(PAC!$AB$6:$AB$581="F03 - EXECUÇÃO DO OBJETO",1,""),"") | BE53: =IFERROR(IF(PAC!$AB$6:$AB$581="F04 - CONCLUÍDA",1,""),"") | BF53: =IF(PAC!$V53>0,0,PAC!$Q53) -> 22800367
A54: =ROW()-5 -> 49 | B54: 2025 | C54: OBRA | D54: PAC SELEÇÕES | E54: MACRODRENAGEM CAM 15 – RUA DA HARMONIA PERNAMBUÉS, SALVADOR/BA | F54: Prevenção a Desastres Naturais | G54: Drenagem Urbana | H54: SEDUR | I54: 14 - Gov. Estado - CONDER | J54: Salvador | K54: 13324752 | P54: 13324752 | Q54: =SUM(PAC!$M54:$P54) -> 13324752 | W54: =IF(PAC!$V54>0,PAC!$V54,PAC!$Q54) -> 13324752 | Y54: FINANCIAMENTO | Z54: FGTS | AA54: 36 | AB54: F01 - CAPTAÇÃO DE RECURSO | AC54: 05 - À LICITAR | AF54: Publicação de Lei Autorizativa | AG54: Definição do Estado quanto a publicação da Lei Autorizativa | AH54: 46325 | AI54: Apresentação da documentação administrativa para contratação de operações (SEPLAN/Secretarias) Publicação de Lei Autorizativa Validação da proposta pelo Agente Financeiro Contratação da Operação de Crédito Envio do projeto para avaliação de compatibilidade pela Caixa; Análise de compatibilidade do projeto pela Caixa; Atendimento às condicionantes da cláusula resolutiva para 1° desembolso | AJ54: 56000001639/2025 56014/2025 | AO54: https://governodabahia.plataformatarget.com.br/web/97cbfe37-dc59-4556-b532-44aa8b7974ad/home | BA54: Anteprojeto | BB54: =IFERROR(IF(PAC!$AB54="F01 - CAPTAÇÃO DE RECURSO",1,""),"") -> 1 | BC54: =IFERROR(IF(PAC!$AB54="F02 - LICITAÇÃO",1,""),"") | BD54: =IFERROR(IF(PAC!$AB$6:$AB$581="F03 - EXECUÇÃO DO OBJETO",1,""),"") | BE54: =IFERROR(IF(PAC!$AB$6:$AB$581="F04 - CONCLUÍDA",1,""),"") | BF54: =IF(PAC!$V54>0,0,PAC!$Q54) -> 13324752
A55: =ROW()-5 -> 50 | B55: 2025 | C55: OBRA | D55: PAC SELEÇÕES | E55: Grupo 2 - MACRODRENAGEM 2º ETAPA DA EXECUÇÃO NO RIO GONGOJI - Intervenção para área urbana de Dário Meira, por onde passa o Riacho do Meio e tem como objetivo sanar os problemas causados pelos alagamentos em períodos de chuva. | F55: Prevenção a Desastres Naturais | G55: Drenagem Urbana | H55: SEDUR | I55: 14 - Gov. Estado - CONDER | J55: Dário Meira | L55: 16957483 | M55: 16957483 | Q55: =SUM(PAC!$M55:$P55) -> 16957483 | W55: =IF(PAC!$V55>0,PAC!$V55,PAC!$Q55) -> 16957483 | Y55: OGU | AA55: 36 | AB55: F01 - CAPTAÇÃO DE RECURSO | AC55: 05 - À LICITAR | AF55: Enviar projetos para análise Qualitativa pela Mandatária | AI55: - Enviar projetos para análise qualitativa pela Mandatária - Enviar documentos para atendimento à Cláusula Suspensiva - Realizar Visita Técnica pela Mandatária ao local da Obra - Elaboração TR e Edital - Publicar Aviso da Licitação - Abertura das Propostas - Homologar e Adjudicar Licitação - Publicar Contrato de Execução - Enviar documentos para obtenção do VRPL - Emissão de AIO - Emissão de Alvará - Emitir Ordem de Serviço | AJ55: 56000001639/2025 56011/2025 | AK55: 986129 | AL55: 03 - Cláusula Vigente | AM55: Titularidade de àrea, PB, Licença Ambiental préviae Declaração sobre sustentabilidade do objeto, Anteprojeto ou TR Conj Art 12, inc. I ou III, "a", da Port conjuntiva MGI/MF/CGU nº3224 | AN55: 46751 | AO55: https://governodabahia.plataformatarget.com.br/web/96d86e64-1a8f-4b02-b626-c6ee50993abd/home | AX55: CE GIGOVSA 6231 2026 - DESBLOQUEIO DE GLOSA CE GIGOV SA 6107 2026 - Desbloqueio de Parcela do Social - BM 02- RATS CE GIGOV SA 5966 2026 - Crédito de Recursos - OBTV - Estado da Bahia CE GIGOV SA 5899 2026 - Pendência Para o Desbloqueio do BM - Caixa informa que pagamentos referentes ao BM 05 e BM 06 serão desbloqueados após o equacionamento da glosa apontada CE GIGOV/SA 5685/2026 - Resultado da análise da documentação CONDER enviou dia 17/08 documentação técnica com ajustes e complementações para prosseguimento na análise da CAIXA CE GIGOV/SA 4015/2026 - Incorporação de Nota de Empenho - CAIXA informa a incorporação dos dados orçamentários e financeiros de recursos. CE GIGOV/SA 2816/2026 - Prorrogação do prazo para atendimento da condição suspensiva Ministério das Cidades autorizou a prorrogação do prazo de cumprimento da condição suspensiva para as operações de Drenagem contratadas em dezembro/2025, abrangendo o Termo de Compromisso referenciado. Tal medida contempla as Etapas 02 a 09 (Ilhéus; Itororó; Juazeiro 01; Juazeiro 02; Ubaíra; Santo Amaro; Dário Meira (2ª etapa); Medeiros Neto). Novo prazo 29/07/2026 Recepcionado 08/05 CE GIGOV/SA 2730/2026 - Apontamentos da análise técnica (Macrodrenagem Dário Meira/BA - Riacho do Meio) - Caixa solicita complementações CE GIGOV/SA 2815/2026 - Prorrogação do prazo para atendimento da condição suspensiva - TC 986128/2025 Macrodrenagem G1 Informamos que o Ministério das Cidades autorizou a prorrogação do prazo de cumprimento da condição suspensiva para as operações de Drenagem contratadas em dezembro/2025, abrangendo o Termo de Compromisso referenciado. Novo prazo 29/07/2026 | BA55: Anteprojeto | BB55: =IFERROR(IF(PAC!$AB55="F01 - CAPTAÇÃO DE RECURSO",1,""),"") -> 1 | BC55: =IFERROR(IF(PAC!$AB55="F02 - LICITAÇÃO",1,""),"") | BD55: =IFERROR(IF(PAC!$AB$6:$AB$581="F03 - EXECUÇÃO DO OBJETO",1,""),"") | BE55: =IFERROR(IF(PAC!$AB$6:$AB$581="F04 - CONCLUÍDA",1,""),"") | BF55: =IF(PAC!$V55>0,0,PAC!$Q55) -> 16957483
A56: =ROW()-5 -> 51 | B56: 2025 | C56: OBRA | D56: PAC SELEÇÕES | E56: MACRODRENAGEM ENTORNO DO MERCADO MUNICIPAL E RUA LEOCÁDIO SANTANA – PAU BRASIL | F56: Prevenção a Desastres Naturais | G56: Drenagem Urbana | H56: SEDUR | I56: 14 - Gov. Estado - CONDER | J56: Pau-Brasil | K56: 10187655 | P56: 10187655 | Q56: =SUM(PAC!$M56:$P56) -> 10187655 | W56: =IF(PAC!$V56>0,PAC!$V56,PAC!$Q56) -> 10187655 | Y56: FINANCIAMENTO | Z56: FGTS | AA56: 36 | AB56: F01 - CAPTAÇÃO DE RECURSO | AC56: 05 - À LICITAR | AF56: Publicação de Lei Autorizativa | AG56: Definição do Estado quanto a publicação da Lei Autorizativa | AH56: 46325 | AI56: Apresentação da documentação administrativa para contratação de operações (SEPLAN/Secretarias) Publicação de Lei Autorizativa Validação da proposta pelo Agente Financeiro Contratação da Operação de Crédito Envio do projeto para avaliação de compatibilidade pela Caixa; Análise de compatibilidade do projeto pela Caixa; Atendimento às condicionantes da cláusula resolutiva para 1° desembolso | AJ56: 56000001639/2025 56014/2025 | AO56: https://governodabahia.plataformatarget.com.br/web/7fd5d305-5466-4e17-911a-4b0aed1b2df3/home | BA56: Anteprojeto | BB56: =IFERROR(IF(PAC!$AB56="F01 - CAPTAÇÃO DE RECURSO",1,""),"") -> 1 | BC56: =IFERROR(IF(PAC!$AB56="F02 - LICITAÇÃO",1,""),"") | BD56: =IFERROR(IF(PAC!$AB$6:$AB$581="F03 - EXECUÇÃO DO OBJETO",1,""),"") | BE56: =IFERROR(IF(PAC!$AB$6:$AB$581="F04 - CONCLUÍDA",1,""),"") | BF56: =IF(PAC!$V56>0,0,PAC!$Q56) -> 10187655
A57: =ROW()-5 -> 52 | B57: 2025 | C57: OBRA | D57: PAC SELEÇÕES | E57: Grupo 2 - MACRODRENAGEM PARA REQUALIFICAÇÃO DO TRECHO URBANO DO RIO ITANHÉM EM MEDEIROS NETO/BA E ATENUAÇÃO DAS INUNDAÇÕES - Obra em duas etapas - Fase 1 - 1.050 m no rio Itanhém (parcial) Fase 2 - 1.205 m ao longo do eixo principal do rio Itanhém (parcial); 552,7 m ao longo do eixo secundário do rio Itanhém (contorno da ilha - total) | F57: Prevenção a Desastres Naturais | G57: Drenagem Urbana | H57: SEDUR | I57: 14 - Gov. Estado - CONDER | J57: Medeiros Neto | L57: 76285208 | M57: 76285208 | Q57: =SUM(PAC!$M57:$P57) -> 76285208 | W57: =IF(PAC!$V57>0,PAC!$V57,PAC!$Q57) -> 76285208 | Y57: OGU | AA57: 36 | AB57: F01 - CAPTAÇÃO DE RECURSO | AC57: 05 - À LICITAR | AF57: Enviar projetos para análise Qualitativa pela Mandatária | AG57: Meta possivelmente não será executada. Em tratativas para remanejamento do recurso para construção de uma barragem. | AI57: - Enviar projetos para análise qualitativa pela Mandatária - Enviar documentos para atendimento à Cláusula Suspensiva - Realizar Visita Técnica pela Mandatária ao local da Obra - Elaboração TR e Edital - Publicar Aviso da Licitação - Abertura das Propostas - Homologar e Adjudicar Licitação - Publicar Contrato de Execução - Enviar documentos para obtenção do VRPL - Emissão de AIO - Emissão de Alvará - Emitir Ordem de Serviço | AJ57: 56000001639/2025 56011/2025 | AK57: 986129 | AL57: 03 - Cláusula Vigente | AM57: Titularidade de àrea, PB, Licença Ambiental préviae Declaração sobre sustentabilidade do objeto, Anteprojeto ou TR Conj Art 12, inc. I ou III, "a", da Port conjuntiva MGI/MF/CGU nº3224 | AN57: 46751 | AO57: https://governodabahia.plataformatarget.com.br/web/6159fbc7-d0a3-46fa-9f16-0ddeaee8b6e6/home | AX57: CE GIGOV/SA 4015/2026 - Incorporação de Nota de Empenho - CAIXA informa a incorporação dos dados orçamentários e financeiros de recursos. Meta possivelmente não será executada. Em tratativas para remanejamento do recurso para a CERB executar a barragem de Medeiros Neto localizada na Bacia de contribuição do rio Alcobaça (ou rio Itanhém) 25 a 30 km a montante da sede de Medeiros Neto, com objetivo de atender múltiplos usos, incluindo abastecimento humano, atividades produtivas e regularização de vazões do rio. Posteriormente buscar-se-á captar recurso para execução da macrodrenagem na cidade. CE GIGOV/SA 2816/2026 - Prorrogação do prazo para atendimento da condição suspensiva Ministério das Cidades autorizou a prorrogação do prazo de cumprimento da condição suspensiva para as operações de Drenagem contratadas em dezembro/2025, abrangendo o Termo de Compromisso referenciado. Tal medida contempla as Etapas 02 a 09 (Ilhéus; Itororó; Juazeiro 01; Juazeiro 02; Ubaíra; Santo Amaro; Dário Meira (2ª etapa); Medeiros Neto). Novo prazo 29/07/2026 | BA57: Anteprojeto | BB57: =IFERROR(IF(PAC!$AB57="F01 - CAPTAÇÃO DE RECURSO",1,""),"") -> 1 | BC57: =IFERROR(IF(PAC!$AB57="F02 - LICITAÇÃO",1,""),"") | BD57: =IFERROR(IF(PAC!$AB$6:$AB$581="F03 - EXECUÇÃO DO OBJETO",1,""),"") | BE57: =IFERROR(IF(PAC!$AB$6:$AB$581="F04 - CONCLUÍDA",1,""),"") | BF57: =IF(PAC!$V57>0,0,PAC!$Q57) -> 76285208
A58: =ROW()-5 -> 53 | B58: 2025 | C58: OBRA | D58: PAC SELEÇÕES | E58: Contratação de empresa especializada para elaboração dos projetos básico e executivo e a execução da obra de Macrodrenagem de Bacias no Município de Ipiaú. Grupo 2 - MACRODRENAGEM 5 BACIAS (Bacias Euclides Neto, Nova Conquista, Getúlio Vargas, 02 de dezembro e Aparecida) | F58: Prevenção a Desastres Naturais | G58: Drenagem Urbana | H58: SEDUR | I58: 14 - Gov. Estado - CONDER | J58: Ipiaú | L58: 40878223 | M58: 40878223 | Q58: =SUM(PAC!$M58:$P58) -> 40878223 | W58: =IF(PAC!$V58>0,PAC!$V58,PAC!$Q58) -> 40878223 | Y58: OGU | AA58: 36 | AB58: F02 - LICITAÇÃO | AC58: 04 - LICITAÇÃO /CONTRATAÇÃO | AD58: 46336 | AF58: Abertura das Propostas | AG58: CONDER Republicou edital de licitação 17/07/26. Previsão de abertura 25/09/26. | AH58: 46320 | AI58: - Abertura das Propostas - Homologar e Adjudicar Licitação - Publicar Contrato de Execução - Enviar documentos para obtenção do VRPL - Emissão de AIO - Emissão de Alvará - Emitir Ordem de Serviço | AJ58: 56000001616/2025 56011/2025 | AK58: 986129 | AL58: 01 - Retirada Total | AO58: https://governodabahia.plataformatarget.com.br/web/67899e11-1f85-4e44-89c6-ed44b9904141/home | AQ58: FINANCIAMENTO | AR58: 46094 | AS58: 46168 | AT58: 46213 | AX58: REITIFICAÇÃO CE GIGOVSA 4786 2026 - Prazo para apresentação do resultado do processo licitatório da Etapa 1 Ipiaú - 30 de outubro Ilhéus CE GIGOV SA 4852 2026 - Apontamentos da análise da 2ª versão do PTS - Etapa 2 Ilhéus RETIFICAÇÃO CE GIGOVSA 47862026 - Prazo para apresentação do resultado do processo licitatório da Etapa 2 Ilhéus - 19 de Novembro. CE GIGOV/SA 4015/2026 - Incorporação de Nota de Empenho - CAIXA informa a incorporação dos dados orçamentários e financeiros de recursos. CE GIGOV/SA 2815/2026 - Prorrogação do prazo para atendimento da condição suspensiva - TC 986128/2025 Macrodrenagem G1 Informamos que o Ministério das Cidades autorizou a prorrogação do prazo de cumprimento da condição suspensiva para as operações de Drenagem contratadas em dezembro/2025, abrangendo o Termo de Compromisso referenciado. Novo prazo 29/07/2026 Informamos que o Ministério das Cidades autorizou a prorrogação do prazo de cumprimento da condição suspensiva para as operações de Drenagem contratadas em dezembro/2025, abrangendo o Termo de Compromisso referenciado. Novo prazo 29/07/2026 | AY58: CONDER Republicou edital de licitação 17/07/26. Previsão de abertura 25/09/26. CONDER publicou resultado de Licitação Deserta - LP 026/26 - DOE 10/06/26 Aviso de Licitação presencial publicado no DOE 13/03/26 - LP 026/26 Abertura 26/05/26 | BA58: Anteprojeto | BB58: =IFERROR(IF(PAC!$AB58="F01 - CAPTAÇÃO DE RECURSO",1,""),"") | BC58: =IFERROR(IF(PAC!$AB58="F02 - LICITAÇÃO",1,""),"") -> 1 | BD58: =IFERROR(IF(PAC!$AB$6:$AB$581="F03 - EXECUÇÃO DO OBJETO",1,""),"") | BE58: =IFERROR(IF(PAC!$AB$6:$AB$581="F04 - CONCLUÍDA",1,""),"") | BF58: =IF(PAC!$V58>0,0,PAC!$Q58) -> 40878223
A59: =ROW()-5 -> 54 | B59: 2025 | C59: OBRA | D59: PAC SELEÇÕES | E59: Canal projetado em concreto com 3,50m de altura e 5,00m de largura, partindo da lagoa transpassando a Rua Beira Rio e Rua Beira Rio I, até o lançamento no Rio São Francisco. Construção de uma lagoa artificial que funcionará como Bacia de Detenção. | F59: Prevenção a Desastres Naturais | G59: Drenagem Urbana | H59: SEDUR | I59: 14 - Gov. Estado - CONDER | J59: Bom Jesus da Lapa | K59: 8717773.3 | P59: 8717773.3 | Q59: =SUM(PAC!$M59:$P59) -> 8717773.3 | W59: =IF(PAC!$V59>0,PAC!$V59,PAC!$Q59) -> 8717773.3 | Y59: FINANCIAMENTO | Z59: FGTS | AA59: 36 | AB59: F01 - CAPTAÇÃO DE RECURSO | AC59: 05 - À LICITAR | AF59: Publicação de Lei Autorizativa | AG59: Definição do Estado quanto a publicação da Lei Autorizativa | AH59: 46325 | AI59: Apresentação da documentação administrativa para contratação de operações (SEPLAN/Secretarias) Publicação de Lei Autorizativa Validação da proposta pelo Agente Financeiro Contratação da Operação de Crédito Envio do projeto para avaliação de compatibilidade pela Caixa; Análise de compatibilidade do projeto pela Caixa; Atendimento às condicionantes da cláusula resolutiva para 1° desembolso | AJ59: 56000001639/2025 56014/2025 | AO59: https://governodabahia.plataformatarget.com.br/web/fd115da4-f175-4911-ab0c-f866fa99dc93/home | BA59: Anteprojeto | BB59: =IFERROR(IF(PAC!$AB59="F01 - CAPTAÇÃO DE RECURSO",1,""),"") -> 1 | BC59: =IFERROR(IF(PAC!$AB59="F02 - LICITAÇÃO",1,""),"") | BD59: =IFERROR(IF(PAC!$AB$6:$AB$581="F03 - EXECUÇÃO DO OBJETO",1,""),"") | BE59: =IFERROR(IF(PAC!$AB$6:$AB$581="F04 - CONCLUÍDA",1,""),"") | BF59: =IF(PAC!$V59>0,0,PAC!$Q59) -> 8717773.3
A60: =ROW()-5 -> 55 | B60: 2025 | C60: OBRA | D60: PAC SELEÇÕES | E60: Contratação de empresa especializada para desenvolvimento de projetos e execução de obras de Macrodrenagem Pluvial na área urbana de Vitória da Conquista no estado da Bahia | F60: Prevenção a Desastres Naturais | G60: Drenagem Urbana | H60: SEDUR | I60: 14 - Gov. Estado - CONDER | J60: Vitória da Conquista | L60: 30747336 | M60: 30747336 | Q60: =SUM(PAC!$M60:$P60) -> 30747336 | W60: =IF(PAC!$V60>0,PAC!$V60,PAC!$Q60) -> 30747336 | Y60: OGU | AA60: 36 | AB60: F02 - LICITAÇÃO | AC60: 04 - LICITAÇÃO /CONTRATAÇÃO | AI60: - Abertura das Propostas - Homologar e Adjudicar Licitação - Publicar Contrato de Execução - Enviar documentos para obtenção do VRPL - Emissão de AIO - Emissão de Alvará - Emitir Ordem de Serviço | AJ60: 56000001639/2025 55977/2025 | AK60: 986128/2025 | AL60: 01 - Retirada Total | AO60: https://governodabahia.plataformatarget.com.br/web/e77ec5ca-826c-4385-9606-dca2d9891624/home | AR60: 46282 | AS60: 46357 | AT60: 46419 | AX60: CE GIGOV SA 6140/2026 - Apontamentos técnicos DUP N 24.798 de 08/09/26 - publicado no DOE 09/09. At= 66.562,75 m². CE GIGOV/SA 5353/2026 Etapa 01: retirada de suspensivas e orientações para licitação - TC 986128/2025 Macrodrenagem G1 CE GIGOV SA 5340 2026 - Apontamentos da análise técnica - Etapa 3 (Canal de Vitória da Conquista/BA) - TC 986128/2025 Macrodrenagem G1 Caixa solicita apontamentos. CONDER enviou dia 18/08 documentação técnica com ajustes e complementações para prosseguimento na análise da CAIXA CE GIGOV SA 5018 2026 - Apontamentos da análise técnica - Etapa 3 Caixa solicita complementações. CE GIGOV/SA 4509/2026 - Apontamentos da análise técnica (Etapa Canal de Vitória da Conquista/BA)- TC 986128/2025 Macrodrenagem G1. Recepcionado CE GIGOV SA 3691 2026 Macrodrenagem de Vitória da Conquista, com indicativo de que a documentação não seria analisada. CE GIGOVSA 3039-2026 - Apontamentos da análise técnica Apontamentos da análise técnica - Etapa Canal de Vitória da Conquista CE GIGOV/SA 2815/2026 - Prorrogação do prazo para atendimento da condição suspensiva - TC 986128/2025 Macrodrenagem G1 Informamos que o Ministério das Cidades autorizou a prorrogação do prazo de cumprimento da condição suspensiva para as operações de Drenagem contratadas em dezembro/2025, abrangendo o Termo de Compromisso referenciado. Novo prazo 29/07/2026 ALTERAÇÃO: CE GIGOV/SA 5688/2025 Aceite de Plano de Trabalho, empenho e abertura da conta vinculada, foi celebrado nesta data o Termo de Compromisso supracitado, com valor de investimento de R$ 91.975.203,37 (composto exclusivamente de repasse) e vigência de 36 meses (término em 04/12/28). | AY60: AVISO DE LP 097/26 - MACRODRENAGEM - DOE 17/09/26 TC celebrado - 04/12/2025 Plano de Trabalho, empenho e abertura da conta vinculada | BA60: Anteprojeto | BB60: =IFERROR(IF(PAC!$AB60="F01 - CAPTAÇÃO DE RECURSO",1,""),"") | BC60: =IFERROR(IF(PAC!$AB60="F02 - LICITAÇÃO",1,""),"") -> 1 | BD60: =IFERROR(IF(PAC!$AB$6:$AB$581="F03 - EXECUÇÃO DO OBJETO",1,""),"") | BE60: =IFERROR(IF(PAC!$AB$6:$AB$581="F04 - CONCLUÍDA",1,""),"") | BF60: =IF(PAC!$V60>0,0,PAC!$Q60) -> 30747336
A61: =ROW()-5 -> 56 | B61: 2025 | C61: OBRA | D61: PAC SELEÇÕES | E61: Elaboração de Projeto Básico e Projeto Executivo, e Execução de Obras de infraestrutura para sistemas de drenagem urbano sustentável e de manejo de águas pluviais, – Obra em duas etapas | F61: Prevenção a Desastres Naturais | G61: Drenagem Urbana | H61: SEDUR | I61: 14 - Gov. Estado - CONDER | J61: Porto Seguro | K61: 60585666 | P61: 60585666 | Q61: =SUM(PAC!$M61:$P61) -> 60585666 | W61: =IF(PAC!$V61>0,PAC!$V61,PAC!$Q61) -> 60585666 | Y61: FINANCIAMENTO | Z61: FGTS | AA61: 36 | AB61: F01 - CAPTAÇÃO DE RECURSO | AC61: 05 - À LICITAR | AF61: Publicação de Lei Autorizativa | AG61: Apontamentos da análise técnica - Etapa Canal de Vitória da Conquista | AH61: 46325 | AI61: Apresentação da documentação administrativa para contratação de operações (SEPLAN/Secretarias) Publicação de Lei Autorizativa Validação da proposta pelo Agente Financeiro Contratação da Operação de Crédito Envio do projeto para avaliação de compatibilidade pela Caixa; Análise de compatibilidade do projeto pela Caixa; Atendimento às condicionantes da cláusula resolutiva para 1° desembolso | AJ61: 56000001639/2025 56014/2025 | AO61: https://governodabahia.plataformatarget.com.br/web/8789c347-5419-4119-ade7-594045c773e3/home | BA61: Anteprojeto | BB61: =IFERROR(IF(PAC!$AB61="F01 - CAPTAÇÃO DE RECURSO",1,""),"") -> 1 | BC61: =IFERROR(IF(PAC!$AB61="F02 - LICITAÇÃO",1,""),"") | BD61: =IFERROR(IF(PAC!$AB$6:$AB$581="F03 - EXECUÇÃO DO OBJETO",1,""),"") | BE61: =IFERROR(IF(PAC!$AB$6:$AB$581="F04 - CONCLUÍDA",1,""),"") | BF61: =IF(PAC!$V61>0,0,PAC!$Q61) -> 60585666
A62: =ROW()-5 -> 57 | B62: 2025 | C62: OBRA | D62: PAC SELEÇÕES | E62: ITAPETINGA (PARTE 01 e PARTE 02) - Canal do Bairro Camacã e Canal do bairro residencial Moacyr Moura | F62: Prevenção a Desastres Naturais | G62: Drenagem Urbana | H62: SEDUR | I62: 14 - Gov. Estado - CONDER | J62: Itapetinga | K62: 31866594 | P62: 30303921 | Q62: =SUM(PAC!$M62:$P62) -> 30303921 | W62: =IF(PAC!$V62>0,PAC!$V62,PAC!$Q62) -> 30303921 | Y62: FINANCIAMENTO | Z62: FGTS | AA62: 36 | AB62: F01 - CAPTAÇÃO DE RECURSO | AC62: 05 - À LICITAR | AF62: Publicação de Lei Autorizativa | AG62: Definição do Estado quanto a publicação da Lei Autorizativa | AH62: 46325 | AI62: Apresentação da documentação administrativa para contratação de operações (SEPLAN/Secretarias) Publicação de Lei Autorizativa Validação da proposta pelo Agente Financeiro Contratação da Operação de Crédito Envio do projeto para avaliação de compatibilidade pela Caixa; Análise de compatibilidade do projeto pela Caixa; Atendimento às condicionantes da cláusula resolutiva para 1° desembolso | AJ62: 56000001639/2025 56014/2025 | AO62: https://governodabahia.plataformatarget.com.br/web/011338d0-7995-41e5-9d57-bef9a18d5a12/home | BA62: Anteprojeto | BB62: =IFERROR(IF(PAC!$AB62="F01 - CAPTAÇÃO DE RECURSO",1,""),"") -> 1 | BC62: =IFERROR(IF(PAC!$AB62="F02 - LICITAÇÃO",1,""),"") | BD62: =IFERROR(IF(PAC!$AB$6:$AB$581="F03 - EXECUÇÃO DO OBJETO",1,""),"") | BE62: =IFERROR(IF(PAC!$AB$6:$AB$581="F04 - CONCLUÍDA",1,""),"") | BF62: =IF(PAC!$V62>0,0,PAC!$Q62) -> 30303921
A63: =ROW()-5 -> 58 | B63: 2025 | C63: OBRA | D63: PAC SELEÇÕES | E63: MACRODRENAGEM DISTRITO DE COROA VERMELHA – STA CRUZ DE CABRÁLIA | F63: Prevenção a Desastres Naturais | G63: Drenagem Urbana | H63: SEDUR | I63: 14 - Gov. Estado - CONDER | J63: Santa Cruz Cabrália | K63: 2541652.8 | P63: 2541652.8 | Q63: =SUM(PAC!$M63:$P63) -> 2541652.8 | W63: =IF(PAC!$V63>0,PAC!$V63,PAC!$Q63) -> 2541652.8 | Y63: FINANCIAMENTO | Z63: FGTS | AA63: 36 | AB63: F01 - CAPTAÇÃO DE RECURSO | AC63: 05 - À LICITAR | AF63: Publicação de Lei Autorizativa | AG63: Definição do Estado quanto a publicação da Lei Autorizativa | AH63: 46325 | AI63: Apresentação da documentação administrativa para contratação de operações (SEPLAN/Secretarias) Publicação de Lei Autorizativa Validação da proposta pelo Agente Financeiro Contratação da Operação de Crédito Envio do projeto para avaliação de compatibilidade pela Caixa; Análise de compatibilidade do projeto pela Caixa; Atendimento às condicionantes da cláusula resolutiva para 1° desembolso | AJ63: 56000001639/2025 56014/2025 | AO63: https://governodabahia.plataformatarget.com.br/web/ad95b41d-4575-40fa-992b-4bea8a5cde23/home | BA63: Anteprojeto | BB63: =IFERROR(IF(PAC!$AB63="F01 - CAPTAÇÃO DE RECURSO",1,""),"") -> 1 | BC63: =IFERROR(IF(PAC!$AB63="F02 - LICITAÇÃO",1,""),"") | BD63: =IFERROR(IF(PAC!$AB$6:$AB$581="F03 - EXECUÇÃO DO OBJETO",1,""),"") | BE63: =IFERROR(IF(PAC!$AB$6:$AB$581="F04 - CONCLUÍDA",1,""),"") | BF63: =IF(PAC!$V63>0,0,PAC!$Q63) -> 2541652.8
A64: =ROW()-5 -> 59 | B64: 2025 | C64: OBRA | D64: PAC SELEÇÕES | E64: Contratação de empresa especializada para desenvolvimento de projetos básicos e executivos e execução de obras de macrodrenagem na Rua Nilo Peçanha no município de Salvador/BA | F64: Prevenção a Desastres Naturais | G64: Drenagem Urbana | H64: SEDUR | I64: 14 - Gov. Estado - CONDER | J64: Salvador | L64: 56440521 | M64: 56440521 | Q64: =SUM(PAC!$M64:$P64) -> 56440521 | W64: =IF(PAC!$V64>0,PAC!$V64,PAC!$Q64) -> 56440521 | Y64: OGU | AA64: 36 | AB64: F01 - CAPTAÇÃO DE RECURSO | AC64: 05 - À LICITAR | AF64: Enviar projetos para análise Qualitativa pela Mandatária | AG64: Documentação técnica da proposta enviada pela CONDER 29/05/26, em proceso de análise qualitativa na CAIXA. | AI64: - Enviar documentos para atendimento à Cláusula Suspensiva - Realizar Visita Técnica pela Mandatária ao local da Obra - Elaboração TR e Edital - Publicar Aviso da Licitação - Abertura das Propostas - Homologar e Adjudicar Licitação - Publicar Contrato de Execução - Enviar documentos para obtenção do VRPL - Emissão de AIO - Emissão de Alvará - Emitir Ordem de Serviço | AJ64: 56000000899/2025 55977/2025 | AK64: 986128/2025 | AL64: 01 - Retirada Total | AO64: https://governodabahia.plataformatarget.com.br/web/ee7526fa-228f-42ac-9680-bddbc53bfaa0/home | AR64: 46281 | AS64: 46356 | AT64: 46417 | AX64: Ofício nº 0490 / 2026 / GIGOV/SA - Crédito de Recursos Financeiros – Orçamento Geral da União CE GIGOV SA 5945 2026 - Crédito de Recursos - OBTV CE GIGOV SA 5944 2026 - Crédito de Recursos - OBTV CE GIGOV SA 5604 2026 Etapa 02 retirada de suspensivas e orientações para licitação Decreto de desapropriação N 24.736 em favor da CONDER destinada a implantação da macrodrenagem na Rua Nilo Peçanha. Publicado no DOE 19/08/26. CE GIGOVSA 3807_2026 - MACRODRENAGEM CALÇADA/NILO PEÇANHA (PENDÊNCIAS DE ENGENHARA) - Caixa Solicita complementação documental e revisãos nos projetos apresentados. CE GIGOV/SA 2815/2026 - Prorrogação do prazo para atendimento da condição suspensiva - TC 986128/2025 Macrodrenagem G1 Informamos que o Ministério das Cidades autorizou a prorrogação do prazo de cumprimento da condição suspensiva para as operações de Drenagem contratadas em dezembro/2025, abrangendo o Termo de Compromisso referenciado. Novo prazo 29/07/2026. CE GIGOV/SA 2791/2026 - Apontamentos da análise preliminar (Etapa Calçada/Rua Nilo Peçanha) - TC 986128/2025 Macrodrenagem G1 Caixa solicita complementações ALTERAÇÃO: CE GIGOV/SA 5688/2025 Aceite de Plano de Trabalho, empenho e abertura da conta vinculada, foi celebrado nesta data o Termo de Compromisso supracitado, com valor de investimento de R$ 91.975.203,37 (composto exclusivamente de repasse) e vigência de 36 meses (término em 04/12/28). | AY64: AVISO DE LP 095/26 - MACRODRENAGEM - DOE 16/09/26 TC celebrado - 04/12/2025 Plano de Trabalho, empenho e abertura da conta vinculada | BA64: Anteprojeto | BB64: =IFERROR(IF(PAC!$AB64="F01 - CAPTAÇÃO DE RECURSO",1,""),"") -> 1 | BC64: =IFERROR(IF(PAC!$AB64="F02 - LICITAÇÃO",1,""),"") | BD64: =IFERROR(IF(PAC!$AB$6:$AB$581="F03 - EXECUÇÃO DO OBJETO",1,""),"") | BE64: =IFERROR(IF(PAC!$AB$6:$AB$581="F04 - CONCLUÍDA",1,""),"") | BF64: =IF(PAC!$V64>0,0,PAC!$Q64) -> 56440521
A65: =ROW()-5 -> 60 | B65: 2025 | C65: OBRA | D65: PAC SELEÇÕES | E65: Grupo 2 - Macrodrenagem para requalificação do trecho urbano do Rio Colonia (Obra em quattro etapas) | F65: Prevenção a Desastres Naturais | G65: Drenagem Urbana | H65: SEDUR | I65: 14 - Gov. Estado - CONDER | J65: Itororó | L65: 7322475.8 | M65: 7322475.8 | Q65: =SUM(PAC!$M65:$P65) -> 7322475.8 | W65: =IF(PAC!$V65>0,PAC!$V65,PAC!$Q65) -> 7322475.8 | Y65: OGU | AA65: 36 | AB65: F01 - CAPTAÇÃO DE RECURSO | AC65: 05 - À LICITAR | AF65: Enviar projetos para análise Qualitativa pela Mandatária | AG65: Documentação técnica da proposta enviada pela CONDER 27/05/26, em proceso de análise qualitativa na CAIXA. | AI65: Formalização da Proposta no TGOV e Envio do Plano de Trabalho | AJ65: 56000001616/2025 56011/2025 | AK65: 986129 | AL65: 03 - Cláusula Vigente | AM65: Anteprojeto, Titularidade de àrea, PB, Licença Ambiental prévia e Declaração sobre sustentabilidade do objeto, Anteprojeto ou TR Conj Art 12, inc. I ou III, "a", da Port conjuntiva MGI/MF/CGU nº3224 | AN65: 46751 | AO65: https://governodabahia.plataformatarget.com.br/web/93be3a9f-a6ac-4012-9dee-aba5e0f89698/home | AX65: CE GIGOV/SA 6065/2026 - Prorrogação da Suspensiva - Apostilamento - TC OGU 986129/2025 - Operação 1106722-41 - Macrodrenagem G2 (Ipiau; Ilhéus; Itororó; Santo Amaro; Juazeiro; Ubaíra; Dário Meira; Medeiros Neto;) CE GIGOV SA 6086 2026 - Comunicação de Publicação do Edital de Licitação da Etapa 3 – Itororó Projeto de engenharia aprovado CE 5057/2026, de 13/08/2026. Aguardando comprovação de lançamento do Edital de Licitação, prazo: 12/10/2026. CE GIGOV/SA 5057/2026 - Aceite de projeto e valores propostos CE GIGOV/SA 5004/2026 - Apontamentos para a finalização da análise técnica - G2. Caixa solicita ajustes e complementações. CE GIGOV/SA 4015/2026 - Incorporação de Nota de Empenho - CAIXA informa a incorporação dos dados orçamentários e financeiros de recursos. CE GIGOVSA 901/2026 - Enviado dia 12/02/26 - Apontamentos da análise preliminar. CE GIGOV/SA 2816/2026 - Prorrogação do prazo para atendimento da condição suspensiva Ministério das Cidades autorizou a prorrogação do prazo de cumprimento da condição suspensiva para as operações de Drenagem contratadas em dezembro/2025, abrangendo o Termo de Compromisso referenciado. Tal medida contempla as Etapas 02 a 09 (Ilhéus; Itororó; Juazeiro 01; Juazeiro 02; Ubaíra; Santo Amaro; Dário Meira (2ª etapa); Medeiros Neto). Novo prazo 29/07/2026 | AY65: CAIXA analisar a proposta | BA65: Anteprojeto | BB65: =IFERROR(IF(PAC!$AB65="F01 - CAPTAÇÃO DE RECURSO",1,""),"") -> 1 | BC65: =IFERROR(IF(PAC!$AB65="F02 - LICITAÇÃO",1,""),"") | BD65: =IFERROR(IF(PAC!$AB$6:$AB$581="F03 - EXECUÇÃO DO OBJETO",1,""),"") | BE65: =IFERROR(IF(PAC!$AB$6:$AB$581="F04 - CONCLUÍDA",1,""),"") | BF65: =IF(PAC!$V65>0,0,PAC!$Q65) -> 7322475.8
A66: =ROW()-5 -> 61 | B66: 2025 | C66: OBRA | D66: PAC SELEÇÕES | E66: Grupo 2 - MACRODRENAGEM NOS CANAIS RIACHO DO MALHADA E RIACHO DO MULUNGU – JUAZEIRO ETAPA 2 | F66: Prevenção a Desastres Naturais | G66: Drenagem Urbana | H66: SEDUR | I66: 14 - Gov. Estado - CONDER | J66: Juazeiro | L66: 49896527 | M66: 49896527 | Q66: =SUM(PAC!$M66:$P66) -> 49896527 | W66: =IF(PAC!$V66>0,PAC!$V66,PAC!$Q66) -> 49896527 | Y66: OGU | AA66: 36 | AB66: F01 - CAPTAÇÃO DE RECURSO | AC66: 05 - À LICITAR | AF66: Enviar projetos para análise Qualitativa pela Mandatária | AG66: CONDER enviou dia 24/07 documentação técnica com ajustes e complementações para prosseguimento na análise da CAIXA. | AI66: - Enviar projetos para análise qualitativa pela Mandatária - Enviar documentos para atendimento à Cláusula Suspensiva - Realizar Visita Técnica pela Mandatária ao local da Obra - Elaboração TR e Edital - Publicar Aviso da Licitação - Abertura das Propostas - Homologar e Adjudicar Licitação - Publicar Contrato de Execução - Enviar documentos para obtenção do VRPL - Emissão de AIO - Emissão de Alvará - Emitir Ordem de Serviço | AJ66: 56000001616/2025 56011/2025 | AK66: 986129 | AL66: 03 - Cláusula Vigente | AM66: Titularidade de àrea, PB, Licença Ambiental préviae Declaração sobre sustentabilidade do objeto, Anteprojeto ou TR Conj Art 12, inc. I ou III, "a", da Port conjuntiva MGI/MF/CGU nº3224 | AN66: 46751 | AO66: https://governodabahia.plataformatarget.com.br/web/7a42068a-7f30-4c4c-9d3c-2ec828209821/home | AX66: CE GIGOV/SA 5533/2026 - Pendências para elaboração do Laudo de Análise de Engenharia da Etapa 7 - Caixa solicita complementações. CE GIGOV/SA 4054/2026 - Apontamentos da análise técnica Caixa fez apontamentos e solicitou correções na documentação encaminhada pela CONDER. CE GIGOV/SA 4015/2026 - Incorporação de Nota de Empenho - CAIXA informa a incorporação dos dados orçamentários e financeiros de recursos. CE GIGOVSA 2514/2026 - Apontamentos da análise técnica - Etapa 7 Macrodrenagem nos Riachos Malhada e Mulungu em Juazeiro BA - TC 986129_2025 CE GIGOV/SA 2816/2026 - Prorrogação do prazo para atendimento da condição suspensiva Ministério das Cidades autorizou a prorrogação do prazo de cumprimento da condição suspensiva para as operações de Drenagem contratadas em dezembro/2025, abrangendo o Termo de Compromisso referenciado. Tal medida contempla as Etapas 02 a 09 (Ilhéus; Itororó; Juazeiro 01; Juazeiro 02; Ubaíra; Santo Amaro; Dário Meira (2ª etapa); Medeiros Neto). Novo prazo 29/07/2026 | BA66: Anteprojeto | BB66: =IFERROR(IF(PAC!$AB66="F01 - CAPTAÇÃO DE RECURSO",1,""),"") -> 1 | BC66: =IFERROR(IF(PAC!$AB66="F02 - LICITAÇÃO",1,""),"") | BD66: =IFERROR(IF(PAC!$AB$6:$AB$581="F03 - EXECUÇÃO DO OBJETO",1,""),"") | BE66: =IFERROR(IF(PAC!$AB$6:$AB$581="F04 - CONCLUÍDA",1,""),"") | BF66: =IF(PAC!$V66>0,0,PAC!$Q66) -> 49896527
A67: =ROW()-5 -> 62 | B67: 2025 | C67: OBRA | D67: PAC SELEÇÕES | E67: Grupo 2 - MACRODRENAGEM ENTORNO DO CAMPO E HOSPITAL REGIONAL | F67: Prevenção a Desastres Naturais | G67: Drenagem Urbana | H67: SEDUR | I67: 14 - Gov. Estado - CONDER | J67: Juazeiro | L67: 10880381 | M67: 10880381 | Q67: =SUM(PAC!$M67:$P67) -> 10880381 | W67: =IF(PAC!$V67>0,PAC!$V67,PAC!$Q67) -> 10880381 | Y67: OGU | AA67: 36 | AB67: F01 - CAPTAÇÃO DE RECURSO | AC67: 05 - À LICITAR | AF67: Enviar projetos para análise Qualitativa pela Mandatária | AG67: CONDER enviou dia 18/08 documentação técnica com ajustes e complementações para prosseguimento na análise da CAIXA | AI67: - Enviar projetos para análise qualitativa pela Mandatária - Enviar documentos para atendimento à Cláusula Suspensiva - Realizar Visita Técnica pela Mandatária ao local da Obra - Elaboração TR e Edital - Publicar Aviso da Licitação - Abertura das Propostas - Homologar e Adjudicar Licitação - Publicar Contrato de Execução - Enviar documentos para obtenção do VRPL - Emissão de AIO - Emissão de Alvará - Emitir Ordem de Serviço | AJ67: 56000001616/2025 56011/2025 | AK67: 986129 | AL67: 03 - Cláusula Vigente | AM67: Titularidade de àrea, PB, Licença Ambiental préviae Declaração sobre sustentabilidade do objeto, Anteprojeto ou TR Conj Art 12, inc. I ou III, "a", da Port conjuntiva MGI/MF/CGU nº3224 | AN67: 46751 | AO67: https://governodabahia.plataformatarget.com.br/web/8d425b99-fdfb-4123-b92d-b527348e280f/home | AX67: CE GIGOV SA 6016 2026 - Análise técnica de Engenharia - Caixa lista apontamentos para conclusão da análise técnica. CE GIGOV SA 5791 2026 - Pendências para a conclusão da análise e a retirada da condição suspensiva — Caixa solicita documentações complementares (QCI, memoria de cálculo, etc.) CE GIGOV SA 5481 2026 - Análise técnica de Engenharia Etapa 6 Macrodrenagem G2 Juazeiro CE GIGOV/SA 4054/2026 - Apontamentos da análise técnica Caixa fez apontamentos e solicitou correções na documentação encaminhada pela CONDER. CE GIGOV/SA 4015/2026 - Incorporação de Nota de Empenho - CAIXA informa a incorporação dos dados orçamentários e financeiros de recursos. Recepcionado dia 06/05 CE GIGOVSA 2653_2026 - Apontamentos da análise técnica - Macrodrenagem do entorno do Campo da Liga e Hospital Regional em Juazeiro/BA CEF Solicita Ajustes e/ou complementos na documentação inserida na plataforma TGOV para continuidade do processo de análise documental. CE GIGOV/SA 2816/2026 - Prorrogação do prazo para atendimento da condição suspensiva Ministério das Cidades autorizou a prorrogação do prazo de cumprimento da condição suspensiva para as operações de Drenagem contratadas em dezembro/2025, abrangendo o Termo de Compromisso referenciado. Tal medida contempla as Etapas 02 a 09 (Ilhéus; Itororó; Juazeiro 01; Juazeiro 02; Ubaíra; Santo Amaro; Dário Meira (2ª etapa); Medeiros Neto). Novo prazo 29/07/2026 | BA67: Anteprojeto | BB67: =IFERROR(IF(PAC!$AB67="F01 - CAPTAÇÃO DE RECURSO",1,""),"") -> 1 | BC67: =IFERROR(IF(PAC!$AB67="F02 - LICITAÇÃO",1,""),"") | BD67: =IFERROR(IF(PAC!$AB$6:$AB$581="F03 - EXECUÇÃO DO OBJETO",1,""),"") | BE67: =IFERROR(IF(PAC!$AB$6:$AB$581="F04 - CONCLUÍDA",1,""),"") | BF67: =IF(PAC!$V67>0,0,PAC!$Q67) -> 10880381
A68: =ROW()-5 -> 63 | B68: 2025 | C68: OBRA | D68: PAC SELEÇÕES | E68: Contratação integrada de empresa especializada para elaboração dos projetos básico e executivo e a execução da obra de macrodrenagem na BA-420 no município de Santo Amaro, estado da Bahia. | F68: Prevenção a Desastres Naturais | G68: Drenagem Urbana | H68: SEDUR | I68: 14 - Gov. Estado - CONDER | J68: Santo Amaro | L68: 11729544 | M68: 11729432 | Q68: =SUM(PAC!$M68:$P68) -> 11729432 | W68: =IF(PAC!$V68>0,PAC!$V68,PAC!$Q68) -> 11729432 | Y68: OGU | AA68: 36 | AB68: F02 - LICITAÇÃO | AC68: 04 - LICITAÇÃO /CONTRATAÇÃO | AI68: - Enviar projetos para análise qualitativa pela Mandatária - Enviar documentos para atendimento à Cláusula Suspensiva - Realizar Visita Técnica pela Mandatária ao local da Obra - Elaboração TR e Edital - Publicar Aviso da Licitação - Abertura das Propostas - Homologar e Adjudicar Licitação - Publicar Contrato de Execução - Enviar documentos para obtenção do VRPL - Emissão de AIO - Emissão de Alvará - Emitir Ordem de Serviço | AJ68: 56000000899/2025 56011/2025 | AK68: 986129 | AL68: 01 - Retirada Total | AO68: https://governodabahia.plataformatarget.com.br/web/7362145a-bc2b-4968-af86-51e07893b0ea/home | AP68: https://maps.app.goo.gl/kXm1E1tyB4Zrp66F7 | AR68: 46261 | AS68: 46336 | AT68: 46380 | AX68: Aviso de Licitação publicadono DOE 27/08/26. Aguardando comprovação de lançamento do Edital de Licitação, prazo: 21/09/2026. CE GIGOVSA 4547 2026 - Aceite de projeto e valores propostos - Etapa 04Macrodrenagem de Santo Amaro. LAE 11 e PA 697/2026 e retirada das suspensivas. CE GIGOV/SA 4015/2026 - Incorporação de Nota de Empenho - CAIXA informa a incorporação dos dados orçamentários e financeiros de recursos. CE GIGOV/SA 2816/2026 - Prorrogação do prazo para atendimento da condição suspensiva Ministério das Cidades autorizou a prorrogação do prazo de cumprimento da condição suspensiva para as operações de Drenagem contratadas em dezembro/2025, abrangendo o Termo de Compromisso referenciado. Tal medida contempla as Etapas 02 a 09 (Ilhéus; Itororó; Juazeiro 01; Juazeiro 02; Ubaíra; Santo Amaro; Dário Meira (2ª etapa); Medeiros Neto). Novo prazo 29/07/2026 REITERAÇÃO: CE GIGOVSA 1973/2026 - Apontamentos da análise preliminar - Etapa Macrodrenagem em Santo Amaro - TC 986129/2025 Macrodrenagem G2 CE GIGOVSA 1973/2026 - Apontamentos da análise preliminar - Etapa Macrodrenagem em Santo Amaro - TC 986129/2025 Macrodrenagem | AY68: AVISO DE LP 086/26 - MACRODRENAGEM - DOE 27/08/26 | BA68: Anteprojeto | BB68: =IFERROR(IF(PAC!$AB68="F01 - CAPTAÇÃO DE RECURSO",1,""),"") | BC68: =IFERROR(IF(PAC!$AB68="F02 - LICITAÇÃO",1,""),"") -> 1 | BD68: =IFERROR(IF(PAC!$AB$6:$AB$581="F03 - EXECUÇÃO DO OBJETO",1,""),"") | BE68: =IFERROR(IF(PAC!$AB$6:$AB$581="F04 - CONCLUÍDA",1,""),"") | BF68: =IF(PAC!$V68>0,0,PAC!$Q68) -> 11729432
A69: =ROW()-5 -> 64 | B69: 2025 | C69: OBRA | D69: PAC SELEÇÕES | E69: MACRODRENAGEM SEDE E DISTRITO DE IPIAPORÃ | F69: Prevenção a Desastres Naturais | G69: Drenagem Urbana | H69: SEDUR | I69: 14 - Gov. Estado - CONDER | J69: Mundo Novo | K69: 12214360 | P69: 12214360 | Q69: =SUM(PAC!$M69:$P69) -> 12214360 | W69: =IF(PAC!$V69>0,PAC!$V69,PAC!$Q69) -> 12214360 | Y69: FINANCIAMENTO | Z69: FGTS | AA69: 36 | AB69: F01 - CAPTAÇÃO DE RECURSO | AC69: 05 - À LICITAR | AF69: Publicação de Lei Autorizativa | AG69: Definição do Estado quanto a publicação da Lei Autorizativa | AH69: 46325 | AI69: Apresentação da documentação administrativa para contratação de operações (SEPLAN/Secretarias) Publicação de Lei Autorizativa Validação da proposta pelo Agente Financeiro Contratação da Operação de Crédito Envio do projeto para avaliação de compatibilidade pela Caixa; Análise de compatibilidade do projeto pela Caixa; Atendimento às condicionantes da cláusula resolutiva para 1° desembolso | AJ69: 56000001616/2025 56011/2025 | AO69: https://governodabahia.plataformatarget.com.br/web/43a2271d-f063-418c-87f5-719176f9471d/home | BA69: Anteprojeto | BB69: =IFERROR(IF(PAC!$AB69="F01 - CAPTAÇÃO DE RECURSO",1,""),"") -> 1 | BC69: =IFERROR(IF(PAC!$AB69="F02 - LICITAÇÃO",1,""),"") | BD69: =IFERROR(IF(PAC!$AB$6:$AB$581="F03 - EXECUÇÃO DO OBJETO",1,""),"") | BE69: =IFERROR(IF(PAC!$AB$6:$AB$581="F04 - CONCLUÍDA",1,""),"") | BF69: =IF(PAC!$V69>0,0,PAC!$Q69) -> 12214360
A70: =ROW()-5 -> 65 | B70: 2025 | C70: OBRA | D70: PAC SELEÇÕES | E70: MACRODRENAGEM DO CANAL VIEIRA PASSOS E NOVA CONSTITUINTE | F70: Prevenção a Desastres Naturais | G70: Drenagem Urbana | H70: SEDUR | I70: 14 - Gov. Estado - CONDER | J70: Salvador | K70: 2183497.3 | P70: 2183497.3 | Q70: =SUM(PAC!$M70:$P70) -> 2183497.3 | W70: =IF(PAC!$V70>0,PAC!$V70,PAC!$Q70) -> 2183497.3 | Y70: FINANCIAMENTO | Z70: FGTS | AA70: 36 | AB70: F01 - CAPTAÇÃO DE RECURSO | AC70: 05 - À LICITAR | AF70: Publicação de Lei Autorizativa | AG70: Definição do Estado quanto a publicação da Lei Autorizativa | AH70: 46325 | AI70: Apresentação da documentação administrativa para contratação de operações (SEPLAN/Secretarias) Publicação de Lei Autorizativa Validação da proposta pelo Agente Financeiro Contratação da Operação de Crédito Envio do projeto para avaliação de compatibilidade pela Caixa; Análise de compatibilidade do projeto pela Caixa; Atendimento às condicionantes da cláusula resolutiva para 1° desembolso | AJ70: 56000001616/2025 56011/2025 | AO70: https://governodabahia.plataformatarget.com.br/web/0079c93e-4f03-4f21-8338-5eaa31b399b9/home | BA70: Anteprojeto | BB70: =IFERROR(IF(PAC!$AB70="F01 - CAPTAÇÃO DE RECURSO",1,""),"") -> 1 | BC70: =IFERROR(IF(PAC!$AB70="F02 - LICITAÇÃO",1,""),"") | BD70: =IFERROR(IF(PAC!$AB$6:$AB$581="F03 - EXECUÇÃO DO OBJETO",1,""),"") | BE70: =IFERROR(IF(PAC!$AB$6:$AB$581="F04 - CONCLUÍDA",1,""),"") | BF70: =IF(PAC!$V70>0,0,PAC!$Q70) -> 2183497.3
A71: =ROW()-5 -> 66 | B71: 2025 | C71: OBRA | D71: PAC SELEÇÕES | E71: MACRODRENAGEM CANAL TIMBALADA CABULA | F71: Prevenção a Desastres Naturais | G71: Drenagem Urbana | H71: SEDUR | I71: 14 - Gov. Estado - CONDER | J71: Salvador | K71: 6616162.4 | P71: 6616162.4 | Q71: =SUM(PAC!$M71:$P71) -> 6616162.4 | W71: =IF(PAC!$V71>0,PAC!$V71,PAC!$Q71) -> 6616162.4 | Y71: FINANCIAMENTO | Z71: FGTS | AA71: 36 | AB71: F01 - CAPTAÇÃO DE RECURSO | AC71: 05 - À LICITAR | AF71: Publicação de Lei Autorizativa | AG71: Definição do Estado quanto a publicação da Lei Autorizativa | AH71: 46325 | AI71: Apresentação da documentação administrativa para contratação de operações (SEPLAN/Secretarias) Publicação de Lei Autorizativa Validação da proposta pelo Agente Financeiro Contratação da Operação de Crédito Envio do projeto para avaliação de compatibilidade pela Caixa; Análise de compatibilidade do projeto pela Caixa; Atendimento às condicionantes da cláusula resolutiva para 1° desembolso | AJ71: 56000001616/2025 56011/2025 | AO71: https://governodabahia.plataformatarget.com.br/web/8964b1a5-3d69-48ea-bb80-d90677e13834/home | BA71: Anteprojeto | BB71: =IFERROR(IF(PAC!$AB71="F01 - CAPTAÇÃO DE RECURSO",1,""),"") -> 1 | BC71: =IFERROR(IF(PAC!$AB71="F02 - LICITAÇÃO",1,""),"") | BD71: =IFERROR(IF(PAC!$AB$6:$AB$581="F03 - EXECUÇÃO DO OBJETO",1,""),"") | BE71: =IFERROR(IF(PAC!$AB$6:$AB$581="F04 - CONCLUÍDA",1,""),"") | BF71: =IF(PAC!$V71>0,0,PAC!$Q71) -> 6616162.4
A72: =ROW()-5 -> 67 | B72: 2025 | C72: OBRA | D72: PAC SELEÇÕES | E72: Contratação de empresa especializada para desenvolvimento de projetos básicos e executivos e execução de obras do sistema de drenagem da Avenida Luis Tarquinio na cidade de Salvador | F72: Prevenção a Desastres Naturais | G72: Drenagem Urbana | H72: SEDUR | I72: 14 - Gov. Estado - CONDER | J72: Salvador | L72: 4787346.4 | M72: 4787346.4 | Q72: =SUM(PAC!$M72:$P72) -> 4787346.4 | W72: =IF(PAC!$V72>0,PAC!$V72,PAC!$Q72) -> 4787346.4 | Y72: OGU | AA72: 36 | AB72: F02 - LICITAÇÃO | AC72: 04 - LICITAÇÃO /CONTRATAÇÃO | AI72: - Abertura das Propostas - Homologar e Adjudicar Licitação - Publicar Contrato de Execução - Enviar documentos para obtenção do VRPL - Emissão de AIO - Emissão de Alvará - Emitir Ordem de Serviço | AJ72: 56000001616/2025 55977/2025 | AK72: 986128/2025 | AL72: 01 - Retirada Total | AO72: https://governodabahia.plataformatarget.com.br/web/f1fffe89-40d8-4c20-bcd6-d3295c91c163/home | AR72: 46281 | AS72: 46356 | AT72: 46417 | AX72: Documentação aprovada anexada no TGOV. Aguardando emissão do LAE pela CAIXA CE GIGOV/SA 3443/2026 Macrodrenagem Av. Luiz Tarquínio - TC 986128/2025 Macrodrenagem G1 - Caixa solicita complementações Recepcionado 25/05 CE GIGOVSA 3100_2026 - Apontamentos da análise técnica Etapa Luiz Tarquínio-Irmã Dulce CE GIGOV/SA 2815/2026 - Prorrogação do prazo para atendimento da condição suspensiva - TC 986128/2025 Macrodrenagem G1 Informamos que o Ministério das Cidades autorizou a prorrogação do prazo de cumprimento da condição suspensiva para as operações de Drenagem contratadas em dezembro/2025, abrangendo o Termo de Compromisso referenciado. Novo prazo 29/07/2026. Recepcionado CE GIGOVSA 1000/2026 - Apontamentos da análise preliminar - Etapa 03 (Luiz Tarquinio/Irmã Dulce) ALTERAÇÃO: CE GIGOV/SA 5688/2025 Aceite de Plano de Trabalho, empenho e abertura da conta vinculada, foi celebrado nesta data o Termo de Compromisso supracitado, com valor de investimento de R$ 91.975.203,37 (composto exclusivamente de repasse) e vigência de 36 meses (término em 04/12/28). | AY72: AVISO DE LP 096/26 - DRENAGEM - DOE 16/09/26 TC celebrado - 04/12/2025 Plano de Trabalho, empenho e abertura da conta vinculada | BA72: Anteprojeto | BB72: =IFERROR(IF(PAC!$AB72="F01 - CAPTAÇÃO DE RECURSO",1,""),"") | BC72: =IFERROR(IF(PAC!$AB72="F02 - LICITAÇÃO",1,""),"") -> 1 | BD72: =IFERROR(IF(PAC!$AB$6:$AB$581="F03 - EXECUÇÃO DO OBJETO",1,""),"") | BE72: =IFERROR(IF(PAC!$AB$6:$AB$581="F04 - CONCLUÍDA",1,""),"") | BF72: =IF(PAC!$V72>0,0,PAC!$Q72) -> 4787346.4
A73: =ROW()-5 -> 68 | B73: 2025 | C73: OBRA | D73: PAC SELEÇÕES | E73: Grupo 2 - Requalificação do Trecho Urbano do Rio Jiquiriçá e Atenuação das Inundações em Ubaíra/BA | F73: Prevenção a Desastres Naturais | G73: Drenagem Urbana | H73: SEDUR | I73: 14 - Gov. Estado - CONDER | J73: Ubaíra | L73: 8601356.1 | M73: 8601356.1 | Q73: =SUM(PAC!$M73:$P73) -> 8601356.1 | W73: =IF(PAC!$V73>0,PAC!$V73,PAC!$Q73) -> 8601356.1 | Y73: OGU | AA73: 36 | AB73: F01 - CAPTAÇÃO DE RECURSO | AC73: 05 - À LICITAR | AF73: Enviar projetos para análise Qualitativa pela Mandatária | AG73: Aguardando manifestação da CAIXA - documentação em análise na CAIXA enviada pela CONDER dia 24/07. | AH73: 46322 | AI73: - Enviar projetos para análise qualitativa pela Mandatária - Enviar documentos para atendimento à Cláusula Suspensiva - Realizar Visita Técnica pela Mandatária ao local da Obra - Elaboração TR e Edital - Publicar Aviso da Licitação - Abertura das Propostas - Homologar e Adjudicar Licitação - Publicar Contrato de Execução - Enviar documentos para obtenção do VRPL - Emissão de AIO - Emissão de Alvará - Emitir Ordem de Serviço | AJ73: 56000001616/2025 56011/2025 | AK73: 986129 | AL73: 03 - Cláusula Vigente | AM73: Titularidade de àrea, PB, Licença Ambiental préviae Declaração sobre sustentabilidade do objeto, Anteprojeto ou TR Conj Art 12, inc. I ou III, "a", da Port conjuntiva MGI/MF/CGU nº3224 | AN73: 46751 | AO73: https://governodabahia.plataformatarget.com.br/web/c17e03cd-9478-4ad9-b7b3-482597707cc0/home | AX73: CE GIGOV SA 6100 2026 - Apontamentos da análise técnica - Etapa Ubaíra CE GIGOVSA 5739 2026 - Prazo da Suspensiva - TC OGU 986129 2025 - Macrodrenagem G2 IPI IOS ITO SAM JUA UBA DME MED - Caixa informas novo Prazo para obtenção da Suspensiva 30 dez 27 Elementos técnicos enviados via TGOV. Manifestação da CAIXA até 27/08 (Verificar divisão de poligonal do empreendimento FGTS 639469). CE GIGOV/SA 4015/2026 - Incorporação de Nota de Empenho - CAIXA informa a incorporação dos dados orçamentários e financeiros de recursos. CE GIGOV/SA 2816/2026 - Prorrogação do prazo para atendimento da condição suspensiva Ministério das Cidades autorizou a prorrogação do prazo de cumprimento da condição suspensiva para as operações de Drenagem contratadas em dezembro/2025, abrangendo o Termo de Compromisso referenciado. Tal medida contempla as Etapas 02 a 09 (Ilhéus; Itororó; Juazeiro 01; Juazeiro 02; Ubaíra; Santo Amaro; Dário Meira (2ª etapa); Medeiros Neto). Novo prazo 29/07/2026 | AY73: CAIXA analisar a proposta | BA73: Anteprojeto | BB73: =IFERROR(IF(PAC!$AB73="F01 - CAPTAÇÃO DE RECURSO",1,""),"") -> 1 | BC73: =IFERROR(IF(PAC!$AB73="F02 - LICITAÇÃO",1,""),"") | BD73: =IFERROR(IF(PAC!$AB$6:$AB$581="F03 - EXECUÇÃO DO OBJETO",1,""),"") | BE73: =IFERROR(IF(PAC!$AB$6:$AB$581="F04 - CONCLUÍDA",1,""),"") | BF73: =IF(PAC!$V73>0,0,PAC!$Q73) -> 8601356.1
A74: =ROW()-5 -> 69 | B74: 2023 | C74: OBRA | D74: PAC SELEÇÕES | E74: CANAL LIGAÇÃO JAGUARIBE - CONTRATAÇÃO INTEGRADA DE EMPRESA DE ENGENHARIA ESPECIALIZADA PARA DESENVOLVIMENTO DE PROJETOS E EXECUÇÃO DE OBRAS PARA AMORTECIMENTO DE CHEIAS NO MÉDIO E ALTO JAGUARIBE (1ª ETAPA), EM SALVADOR/BA. | F74: Prevenção a Desastres Naturais | G74: Drenagem Urbana | H74: SEDUR | I74: 14 - Gov. Estado - CONDER | J74: Salvador | L74: 17996756 | M74: 1.1452756e+08 | Q74: =SUM(PAC!$M74:$P74) -> 1.1452756e+08 | V74: 59525759 | W74: =IF(PAC!$V74>0,PAC!$V74,PAC!$Q74) -> 59525759 | X74: CONSÓRCIO BACIA DO JAGUARIBE (CBS CONSTRUTORA BAHIANA DE SANEAMENTO LTDA / IBI ENGENHARIA CONSULTIVA S/S) | Y74: OGU | AA74: 19 | AB74: F02 - LICITAÇÃO | AC74: 04 - LICITAÇÃO /CONTRATAÇÃO | AF74: Enviar documentos para obtenção do VRPL | AG74: CONDER proceder com o envio da documentação para obtenção do VRPL | AI74: -Verificação da Realização do Processo Licitatório - VRPL; -Autorização do Ministério Gestor para os eventos de assinatura de contratos; -Autorização para Início de Objeto - AIO -Assinatura da Ordem de Serviço; -Monitoramento da Execução de Obras; | AJ74: 24845/2024 56000001031/2023 | AK74: 969064/2024 | AL74: 01 - Retirada Total | AO74: https://governodabahia.plataformatarget.com.br/web/fc5720e9-b456-471a-9f6b-2df10d649844/home | AP74: https://maps.app.goo.gl/BNWu9uq2XF2WrG9Q6 | AR74: 46119 | AS74: 46189 | AX74: CE GIGOV/SA 5506/2026 - Verificação do Resultado do Processo Licitatório - Etapa 04 (Jaguaribe) CE GIGOVSA 4977 2026 - ETAPA 05 - MACRODRENAGEM JAGUARIBE - Análise licitação. Caixa solicita a ajustes e complementações. Decreto de desapropriação n 24656 publicado no DOE 09/07/26 CE GIGOV/SA 4012/2026 - Laudo de Análise de Instrumento de Planejamento Social - Etapa 5 Jaguaribe. CE GIGOV/SA 1745/2026 - Informa emissão do laudo e solicita comprovação de abertura do processo licitatório - TC MCIDADES 969064/2024 - Operação 1098381-91 - Solicita comprovação de abertura do processo licitatório CE GIGOV/SA 1592/2026 - Enviado dia 20/03/26 - Informamos a pendência para o desbloqueio no valor de R$ 621.669,05. CE GIGOV/SA 1099/2026 - Enviado dia 27/02/2026 - A CONDER encaminhou por e-mail em 12/02/2026 documentação para prosseguimento da análise dos projetos. CE GIGOV/SA 1099/2026 - ANÁLISE TÉCNICA. Caixa solicita Agendamento de visita Técnica e laudo complementar atestando que as lagoas de estabilização de esgoto da EMBASA constantes na poligonal não terão influencia nos dispositivos (barramentos e vertedouros) propostos no projeto. CE GIGOV/SA 890/2026 - Enviado dia 12/02/2026 - Utilização do Saldo do Repasse. Recepcionado CE GIGOV 6290/2025 - CONDER Solicitou à CAIXA através do Of758/2025 prorrogação do prazo para retirada da clausula suspensiva. Recepcionado CE GIGOV 4833/2025 com Apontamentos da análise preliminar da macrodrenagem Bacia Jaguaribe e solicitação de complementações para prosseguimento na análise. CE GIGOV/SA 4063/2025 - Enviado dia 16/09/25 - Comunica o crédito, sob bloqueio, de R$ 1.118.669,63 em 11/09/2025, para o Termo nº 0402487-88/2012, no âmbito do Programa Gestão de Riscos, do Ministério das Cidades. CE GIGOV/SA 4022/2025 - Enviado dia 12/09/25 -Placa da obra/Alteração metodologia executiva no Canal Mangabeira. Cronograma cadastrado no TRANSFEREGOV - Prazo de execução - 19 meses, conclusão Prevista 30/08/28. Clausula Suspensiva: Apresentação dos itens (Anteprojeto, Projeto Básico, TR, Comprovação de propriedade do imóvel, Licenciamento Ambiental, Declaração de Sustentabilidade e PTS) até 08/07/25 Publicada no DOE 05/11 LEI Nº 14.784 DE 04 DE NOVEMBRO DE 2024 Autoriza o Poder Executivo a contratar operação de crédito interno junto à Caixa Econômica Federal - CEF. Na formalização se solicitou a unificação da Proposta 1031; Todo Material foi incluído na plataforma TGOV; Em fase de formalização, anterior ao TC; Ministério tem prazo de 30 dias para devolver a caixa - 13/10/24; CAIXA retornar ao proponente até 17/10 solicitando ou não complementações; A modalidade de Licitação adotada será Integrada, todas em um Termo de Compromisso com cinco metas. | AY74: Resultado final, homologação, Adjudicação e convocação para Assinatura de Contrato da LP Nº 039/26 publicado no DOE 16/07/26 AVISO - LICITAÇÃO PRESENCIAL Nº 039/26 - CONDER Abertura: 19/06/2026 Assinatura e publicação do termo de compromisso publicado no DOU - 19/11/2024 | BA74: Anteprojeto | BB74: =IFERROR(IF(PAC!$AB74="F01 - CAPTAÇÃO DE RECURSO",1,""),"") | BC74: =IFERROR(IF(PAC!$AB74="F02 - LICITAÇÃO",1,""),"") -> 1 | BD74: =IFERROR(IF(PAC!$AB$6:$AB$581="F03 - EXECUÇÃO DO OBJETO",1,""),"") | BE74: =IFERROR(IF(PAC!$AB$6:$AB$581="F04 - CONCLUÍDA",1,""),"") | BF74: =IF(PAC!$V74>0,0,PAC!$Q74) -> 0
A75: =ROW()-5 -> 70 | B75: 2023 | C75: OBRA | D75: PAC SELEÇÕES | E75: CAMURUJIPE - CONTRATAÇÃO DE EMPRESA ESPECIALIZADA PARA DESENVOLVIMENTO DE PROJETOS E EXECUÇÃO DE OBRAS DE MACRODRENAGEM DE COMPLEMENTAÇÃO DA MACRODRENAGEM DO RIO CAMARAJIPE, NA CIDADE DE SALVADOR - BAHIA. | F75: Prevenção a Desastres Naturais | G75: Drenagem Urbana | H75: SEDUR | I75: 14 - Gov. Estado - CONDER | J75: Salvador | L75: 97299327 | M75: 30187058 | Q75: =SUM(PAC!$M75:$P75) -> 30187058 | W75: =IF(PAC!$V75>0,PAC!$V75,PAC!$Q75) -> 30187058 | X75: CBS CONSTRUTORA BAHIANA DE SANEAMENTO LTDA | Y75: OGU | AA75: 17 | AB75: F02 - LICITAÇÃO | AC75: 04 - LICITAÇÃO /CONTRATAÇÃO | AF75: Emissão de AIO | AG75: VRPL Concluida, após o período de defeso eleitoral o Ministério poderá emitir AIO | AI75: -Autorização para Início de Objeto - AIO -Assinatura da Ordem de Serviço; -Monitoramento da Execução de Obras; | AJ75: 24845/2024 56000001031/2023 | AK75: 969064/2024 | AL75: 01 - Retirada Total | AO75: https://governodabahia.plataformatarget.com.br/web/6289c3ce-9ecf-45d2-87aa-5ad1398eb9ea/home | AR75: 44992 | AS75: 46162 | AT75: 46190 | AX75: CE GIGOV SA 5949 2026 - Pendência para Solicitação de AIO ao Ministério - Caixa solicita documentação complementar. CE GIGOV/SA 4908/2026 - Conclusão da Análise do Processo Licitatório e Impossibilidade de Solicitação de AIO ao Ministério. A emissão da AIO está condicionada ao fim do período de defeso eleitoral. CE GIGOVSA 4726 2026 - Condicionante para Continuidade do Processo VRPL. CAIXA solicita revisão da Declaração. CE GIGOV/SA 4371/2026 - Pendência de Licitação - Processo Licitatório nº 024/2026 Caixa solicita ajustes na documentação enviada. CE GIGOV/SA 1592/2026 - Enviado dia 20/03/26 - Informamos a pendência para o desbloqueio no valor de R$ 621.669,05. AVISO LP 024/26 publicado no DOE 07/03 CE GIGOV/SA 1285/2026 - Recepcionado 09/03 Ofício de orientações para continuidade do TC - Processo Licitatório. LAE Concedido e definido prazo de 60 dias para licitação CE GIGOV/SA 1285/2026 - Enviado dia 09/03/26 - Comunicamos que a quarta etapa, do referido Termo de Compromisso foi considerada tecnicamente viável, com a consequente retirada da cláusula suspensiva, e está apto para prosseguimento das análises pós-contratuais pertinentes. Recepcionado 19/02/26 CE GIGOVSA 939_2026 Caixa informa da necessidade de ajustes dos itens BDI na PO para finalização da análise. CE GIGOV/SA 5248/2025 - Enviado dia 17/11/25 - Após análise da documentação encaminhada através do ofício nº 268/2025 – Etapa Camaragipe, informamos que a documentação encaminhada atende ao solicitado, entretanto necessita de alguns esclarecimentos/ajustes. Recepcionado 30/09 CE GIGOV/SA 4300/2025 - Análise Preliminar 02 (Reiteração/Complementação) Recepcionado dia 15/09/25 CE GIGOV/SA 4069/2025 - Análise Preliminar - Etapa 04 - Macrodrenagem Camarajipe - TC OGU. Recepcionado dia 15/01/25 o Ofício nº 119 / 2025 / GIGOV/SA - Resposta do MCidades sobre Licenciamento Ambiental e Titularidade de Área; Cronograma cadastrado no TRANSFEREGOV - Prazo de execução - 17 meses, conclusão Prevista 23/12/26. Clausula Suspensiva: Apresentação dos itens (Anteprojeto, Projeto Básico, TR, Comprovação de propriedade do imóvel, Licenciamento Ambiental, Declaração de Sustentabilidade e PTS) até 08/07/25; Publicada no DOE 05/11 LEI Nº 14.784 DE 04 DE NOVEMBRO DE 2024 Autoriza o Poder Executivo a contratar operação de crédito interno junto à Caixa Econômica Federal - CEF. Na formalização se solicitou a unificação da Proposta 1031; Todo Material foi incluído na plataforma TGOV; Em fase de formalização, anterior ao TC; Ministério tem prazo de 30 dias para devolver a caixa - 13/10/24; CAIXA retornar ao proponente até 17/10 solicitando ou não complementações; A modalidade de Licitação adotada será Integrada, todas em um Termo de Compromisso com cinco metas. | AY75: RESUMO DO CT 077/2026 - DOE 17/06/2026 - CONDER AVISO LP 024/26 publicado no DOE 07/03 Abertura: 20/05/202 Assinatura e publicação do termo de compromisso publicado no DOU - 19/11/2024 | BA75: Anteprojeto | BB75: =IFERROR(IF(PAC!$AB75="F01 - CAPTAÇÃO DE RECURSO",1,""),"") | BC75: =IFERROR(IF(PAC!$AB75="F02 - LICITAÇÃO",1,""),"") -> 1 | BD75: =IFERROR(IF(PAC!$AB$6:$AB$581="F03 - EXECUÇÃO DO OBJETO",1,""),"") | BE75: =IFERROR(IF(PAC!$AB$6:$AB$581="F04 - CONCLUÍDA",1,""),"") | BF75: =IF(PAC!$V75>0,0,PAC!$Q75) -> 30187058
A76: =ROW()-5 -> 71 | B76: 2023 | C76: OBRA | D76: PAC SELEÇÕES | E76: G5/G6 LOTE 01 B - Encosta - PDE 119.2 complementar - Vila Leal - Bairro Campinas de Pirajá | F76: Prevenção a Desastres Naturais | G76: Encosta | H76: SEDUR | I76: 14 - Gov. Estado - CONDER | J76: Salvador | L76: 8408272.5 | N76: 442540.66 | P76: 8408272.5 | Q76: =SUM(PAC!$M76:$P76) -> 8850813.1 | V76: 2955772.5 | W76: =IF(PAC!$V76>0,PAC!$V76,PAC!$Q76) -> 2955772.5 | X76: Lima Diniz Construções Ltda | Y76: CONTRAPARTIDA FINANCIAMENTO | Z76: FGTS | AA76: 12 | AB76: F03 - EXECUÇÃO DO OBJETO | AC76: 02 - ANDAMENTO | AD76: 46421 | AE76: 12 | AF76: Execução da Obra | AG76: Monitorar execução da obra. | AH76: 46421 | AI76: Monitorar execução da obra. | AJ76: 56000000206/2023 | AK76: 643.910-25 | AO76: https://governodabahia.plataformatarget.com.br/web/49bcb485-2f68-4513-ae60-055b28fd0951/home | AP76: https://maps.app.goo.gl/yPAcvkPGkJoSJwCC9 | AR76: 45966 | AS76: 45993 | AT76: 46037 | AU76: 46052 | AV76: 46421 | AW76: 46421 | AX76: CE GIGOV/SA 5741/2026 - Enviado dia 09/09/26 Solicitação de desembolso ref julho/2026. CE GIGOV/SA 5201/2026 - Enviado dia 19/08/26 - Suspende o acompanhamento físico-financeiro da operação. CE GIGOV/SA 5086/2026 - Enviado dia 13/08/26 Alteração de agente promotor: disponibiliza nova Rerrati para assinatura. CE GIGOV/SA 4182/2026 - Enviado dia 08/07/26 - Placa de Obras (período de defeso eleitoral). CE GIGOV/SA 4040/2026 - Enviado dia 01/07/26- Alteração de agente promotor: impossibilidade de alteração da minuta contratual. ALTERA ANEXO: CE GIGOV/SA 3243/2026 - Enviado dia 26/06/26 Alteração de agente promotor: envia instrumento formalizador. CE GIGOV/SA 3243/2026 - Enviado dia 29/05/26 - A Caixa encaminhou o Instrumento de Rerratificação para inclusão da CONDER como agente promotor, solicitando assinatura e devolução. Informou ainda a cobrança de tarifa de R$ 1.700,00 e a necessidade de publicação do extrato no Diário Oficial. CE GIGOV/SA 3010/2026 - Enviado dia 20/05/26 - A CAIXA analisou o pedido de desbloqueio da BM/RRE 01 do Lote B (G6), mas solicitou complementações: projeto executivo e peças gráficas do PDE 098, ART de fiscalização definitiva, ART compatível com projeto executivo, comprovação de registro no SCPO e esclarecimento sobre divergências de valores/Fatores de Segurança entre projeto básico e executivo. Também pediu adequação do RRE e QCI aos dados do contrato, incluindo PDEs zerados. A análise seguirá após atendimento das pendências. RETIFICA: ADITA CE GIGOV/SA 2696/2026 - Enviado dia 14/05/26 - ateste e condicionantes para o 1º desembolso. CE GIGOV/SA 0860/2026 - Enviado dia 11/02/26 -Envio de ordem de serviço. CE GIGOV/SA 0330/2026 - Enviado dia 20/01/2026 -informa aceite PTS. CE GIGOV/SA 0356/2026 - Enviado dia 20/01/2026 -Documentação complementar referente ao processo licitatório. CE GIGOV/SA 0219/2026 Alteração contratual - CT 0639469-97/2025 Macrodrenagem na Bahia - macrodrenagem nos municípios de Ubaíra e Itororó de maneira mais abrangente. Ofício nº 001/2026 – SEDUR/GAB/SGT, de 06/01/2026 contendo justificativa técnica para ampliação de escopo das intervenções de macrodrenagem nos municípios de Ubaíra e Itororó/BA e a supressão das intervenções de macrodrenagem nos Municípios Ilhéus e Ipiaú/BA. | AY76: CT 001/2026 - Monitorar execução da obra com previsão de conclusão 03/02/2027. | BB76: =IFERROR(IF(PAC!$AB76="F01 - CAPTAÇÃO DE RECURSO",1,""),"") | BC76: =IFERROR(IF(PAC!$AB76="F02 - LICITAÇÃO",1,""),"") | BD76: =IFERROR(IF(PAC!$AB$6:$AB$581="F03 - EXECUÇÃO DO OBJETO",1,""),"") -> 1 | BE76: =IFERROR(IF(PAC!$AB$6:$AB$581="F04 - CONCLUÍDA",1,""),"") | BF76: =IF(PAC!$V76>0,0,PAC!$Q76) -> 0
